Workbook

Sheet Лист4
A1: № | B1: Наименование Проекта | C1: Дата решение Правления/СД | D1: Регион | E1: Застройщик | F1: БИН Застройщика | G1: Уполномоченная компания | H1: БИН Уполномоченной компании | I1: Стоимость, тенге | J1: Площадь, кв.м по Проекту | K1: Площадь квартир, кв.м по Проекту | L1: Себестоимость тыс.тенге/1 м2 | M1: Цена реал. тыс.тенге/1 м2 | N1: Дата заключения договора о предоставлении гарантии | O1: Количество квартир по Проекту | P1: Количество квартир по факту (после ввода)* | Q1: Этажность | R1: Дата начала строительства | S1: Дата завершения | T1: Дата пролонгации 1 | U1: Дата пролонгации 2 | V1: Дата пролонгации 3 | W1: Дата завершения 2 | X1: Гарантийный взнос, тенге | Y1: № ДПГ | Z1: Стоимость увеличение/уменьшение обзятельств | AA1: Исполнитель | AB1: Балл Застройщика | AC1: Кол-во продлении | AD1: Кол-во модерации | AE1: Номер в SB | AF1: Наличие "Зеленого сертификатв" | AG1: Статус
A2: 1 | B2: ЖК "Миллениум парк", пятно 2, 14 блок | C2: 42870 | D2: г. Астана | E2: ТОО "BAZIS-A Corp." | F2: 960340000376 | G2: ТОО "Аллея тысячелетия-2" | H2: 160340010693 | I2: 2516814000 | J2: 14000 | N2: 42873 | O2: 178 | P2: 178 | Q2: 24 | R2: 42513 | S2: 43519 | W2: 43154 | X2: 50336280 | Y2: ДПГ-17-01-001-02/001 | AB2: 100 | AG2: Завершенные
A3: 2 | B3: ЖК "Легенда", 1 очередь (пятна 1-6) | C3: 42968 | D3: г. Алматы | E3: ТОО "BAZIS-A Corp." | F3: 960340000376 | G3: ТОО "KAT-Construction" | H3: 160640015734 | I3: 6866978080 | J3: 35371.3 | N3: 43000 | O3: 400 | P3: 396 | Q3: 14-16 | R3: 42895 | S3: 43474 | W3: 43454 | X3: 137339562 | Y3: ДПГ-17-02-001/002 | AB3: 100 | AG3: Завершенные
A4: 3 | B4: ЖК Алтын Ұя | C4: 43090 | D4: г. Астана | E4: ТОО "Comfort Development KZ" | F4: 210940032945 | G4: ТОО "AKAN Engineering" | H4: 140540020406 | I4: 1576632159 | J4: 13084 | N4: 43122 | O4: 148 | P4: 167 | Q4: 10 | R4: 42765 | S4: 43339 | W4: 43339 | X4: 18956603 | Y4: ДПГ-17-01-002/003 | AB4: 67 | AG4: Завершенные
A5: 4 | B5: МЖК Легенда, 2 очередь, ПАРКИНГ | C5: 43132 | D5: г. Алматы | E5: ТОО "BAZIS-A Corp." | F5: 960340000376 | G5: ТОО "KAT-Construction" | H5: 160640015734 | I5: 1348115202 | J5: 8303.1 | N5: 43146 | O5: 233 | P5: 233 | Q5: 1 | R5: 43005 | S5: 43461 | W5: 43454 | X5: 24756844 | Y5: доп.согл. №1 к ДПГ-17-02-001/002 | AB5: 100 | AG5: Завершенные
A6: 5 | B6: МЖК Alma City, 1 очередь | C6: 43193 | D6: г. Алматы | E6: ТОО "Qazaq Stroy" | F6: 050540016141 | G6: ТОО "Елимай-Invest" | H6: 160640016168 | I6: 1543068030 | J6: 26577.5 | N6: 43214 | O6: 300 | P6: 360 | Q6: 5 | R6: 43161 | S6: 43526 | W6: 43482 | X6: 28414166 | Y6: ДПГ-18-02-005/006 | AB6: 91 | AG6: Завершенные
A7: 6 | B7: ЖК на Гагарина 1 | C7: 43206 | D7: г. Уральск | E7: ТОО "Караванный путь" | F7: 030840007596 | G7: ТОО "Stroy Baiterek" | H7: 170740034528 | I7: 1279348120 | J7: 7546.7 | N7: 43218 | O7: 126 | P7: 126 | Q7: 9 | R7: 42964 | S7: 43512 | W7: 43477 | X7: 15796882 | Y7: ДПГ-18-07-006/007 | AB7: 64 | AG7: Завершенные
A8: 7 | B8: МЖК Alma City, 2 очередь | C8: 43325 | D8: г. Алматы | E8: ТОО "Qazaq Stroy" | F8: 050540016141 | G8: ТОО "Елимай-Invest" | H8: 160640016168 | I8: 1543068032 | J8: 26577.5 | N8: 43326 | O8: 300 | P8: 360 | Q8: 5 | R8: 43161 | S8: 43526 | W8: 43482 | X8: 30861361 | Y8: доп.согл. 1 к ДПГ-18-02-005/006 | AB8: 90 | AG8: Завершенные
A9: 8 | B9: МЖК Легенда, 3 очередь, пятна 7, 8, | C9: 43159 | D9: г. Алматы | E9: ТОО "BAZIS-A Corp." | F9: 960340000376 | G9: ТОО "KAT-Construction" | H9: 160640015734 | I9: 2198326780 | J9: 12592.6 | N9: 43175 | O9: 134 | P9: 134 | Q9: 14-15 | R9: 43116 | S9: 43540 | T9: 43632 | W9: 43633 | X9: 43145556 | Y9: доп.согл. №2 к ДПГ-17-02-001/002 | AB9: 100 | AG9: Завершенные
A10: 9 | B10: ЖК SUNRISE | C10: 43325 | D10: г. Астана | E10: ТОО "Милан-Астана" | F10: 110540015593 | G10: ТОО "Тенгри Хаус Астана" | H10: 130340016121 | I10: 7519312044 | J10: 29141.3 | N10: 43341 | O10: 458 | P10: 569 | Q10: 8-9 | R10: 43230 | S10: 43718 | W10: 43703 | X10: 141232414 | Y10: доп.согл. №1 к ДПГ-18-01-008/009 | AB10: 78 | AG10: Завершенные
A11: 10 | B11: ЖК Nova City | C11: 43390 | D11: г. Астана | E11: ТОО "Милан-Астана" | F11: 110540015593 | G11: ТОО "Камал Центр Астана" | H11: 170540018975 | I11: 6690458969 | J11: 28555.6 | N11: 43398 | O11: 467 | P11: 467 | Q11: 9 | R11: 43296 | S11: 43799 | T11: 43799 | W11: 43784 | X11: 127426511 | Y11: ДПГ-18-01-008/011 | AB11: 78 | AG11: Завершенные
A12: 11 | B12: ЖК Alma City-2 | C12: 43454 | D12: г. Алматы | E12: ТОО "Qazaq Stroy" | F12: 050540016141 | G12: ТОО "Нұр City Investment" | H12: 181140015247 | I12: 7891739810 | J12: 66742.5 | N12: 43458 | O12: 984 | P12: 1059 | Q12: 9 | R12: 43431 | S12: 43795 | W12: 43788 | X12: 141881753 | Y12: ДПГ-18-02-005/012 | AB12: 90 | AG12: Завершенные
A13: 12 | B13: ЖК Биік Шаңырақ | C13: 43147 | D13: г. Астана | E13: ТОО "НАЕК" | F13: 940140001482 | G13: ТОО "Биік Шаңырақ" | H13: 140740007872 | I13: 2146903508 | J13: 17848.8 | N13: 43162 | O13: 260 | P13: 276 | Q13: 14 | R13: 43160 | S13: 29.02.2019 | T13: 43616 | U13: 43708 | V13: 43890 | W13: 43803 | X13: 36796147 | Y13: ДПГ-18-01-003/004 | Z13: 1302438420 | AB13: 77 | AG13: Завершенные
A14: 13 | B14: ЖК Бахыт, 1 очередь | C14: 43166 | D14: г. Шымкент | E14: ТОО "Оңтүстік құрылыс Сервис" | F14: 010340004024 | G14: ТОО "Композит-7" | H14: 050640012251 | I14: 2458898850 | J14: 16417.7 | N14: 43194 | O14: 104 | P14: 104 | Q14: 9 | R14: 43160 | S14: 30.04.2019 | T14: 43676 | U14: 43768 | V14: 43860 | W14: 43824 | X14: 46976477 | Y14: ДПГ-18-13-004/005 | Z14: 2458898850 | AB14: 64 | AG14: Завершенные
A15: 14 | B15: МЖК Легенда, 5 очередь, пятна 9, 10 | C15: 43313 | D15: г. Алматы | E15: ТОО "BAZIS-A Corp." | F15: 960340000376 | G15: ТОО "KAT-Construction" | H15: 160640015734 | I15: 2502632570 | J15: 12341.8 | N15: 43315 | O15: 94 | P15: 94 | Q15: 14-15 | R15: 43280 | S15: 43859 | W15: 43822 | X15: 48468231 | Y15: доп.согл. №3 к ДПГ-17-02-001/002 | AB15: 83 | AG15: Завершенные
A16: 15 | B16: ЖК Триумфальная арка-2 | C16: 43334 | D16: г. Астана | E16: ТОО "Ңұр Астана Құрылыс" | F16: 060140000846 | G16: ТОО "Мангилик Ел Курылыс" | H16: 170240033531 | I16: 5341879260 | J16: 23920.8 | N16: 43385 | O16: 142 | P16: 136 | Q16: 4,7,9 | R16: 43269 | S16: 44000 | W16: 43977 | X16: 93091230 | Y16: ДПГ-18-01-009/010 | AB16: 67 | AG16: Завершенные
A17: 16 | B17: МЖК Багыстан, 1-я очередь, 2-очередь, 1, 3 позиции | C17: 43210 | D17: г. Астана | E17: ТОО "Шар Курылыс" | F17: 980740001878 | G17: ТОО "Бағыстан" | H17: 161140023096 | I17: 6541727260 | J17: 41688.6 | N17: 43216 | O17: 324 | P17: 324 | Q17: 5,7,9 | R17: 42921 | S17: 1 позиция - 10.08.2021г.; 3 позиция - 20.10.2021г. | T17: 44134 | U17: 44226 | V17: 44316 | W17: 44489 | X17: 110832077 | Y17: ДПГ-18-01-007/008 | AB17: 83 | AG17: Завершенные
A18: 17 | B18: МЖК Багыстан, 3-я очередь, 7 позиция | C18: 43286 | D18: г. Астана | E18: ТОО "Шар Курылыс" | F18: 980740001878 | G18: ТОО "Бағыстан" | H18: 161140023096 | I18: 3024902930 | J18: 13362.1 | N18: 43291 | O18: 152 | P18: 152 | Q18: 5,7,9 | R18: 43040 | S18: 20.10.2021 | T18: 44134 | U18: 44226 | V18: 44316 | W18: 44489 | X18: 56590879 | Y18: доп.согл.№1 к ДПГ-18-01-007/008 | AB18: 83 | AG18: Завершенные
A19: 18 | B19: МЖК Багыстан, 4-я очередь, 11 позиция | C19: 43325 | D19: г. Астана | E19: ТОО "Шар Курылыс" | F19: 980740001878 | G19: ТОО "Бағыстан" | H19: 161140023096 | I19: 3014702450 | J19: 13367.2 | N19: 43336 | O19: 152 | P19: 152 | Q19: 5,7,9 | R19: 43266 | S19: 30.07.2020 | T19: 44134 | U19: 44226 | V19: 44316 | W19: 44489 | X19: 59088033 | Y19: доп.согл.№3 к ДПГ-18-01-007/008 | AB19: 83 | AG19: Завершенные
A20: 19 | B20: МЖК Sezim Qala, 1 очередь | C20: 43515 | D20: г. Астана | E20: ТОО "Милан-Астана" | F20: 110540015593 | G20: ТОО "Туран Сити" | H20: 170340033307 | I20: 4220953472 | J20: 21443 | N20: 43518 | O20: 277 | P20: 266 | Q20: 9.12 | R20: 43441 | S20: 44142 | W20: 43824 | X20: 79630069 | Y20: доп.согл.№1 к ДПГ-19-01-008/015 | AB20: 78 | AG20: Завершенные
A21: 20 | B21: ЖК Легенда, 4 очередь (пятна 11, 12) | C21: 43523 | D21: г. Алматы | E21: ТОО "BAZIS-A Corp." | F21: 960340000376 | G21: ТОО "KAT-Construction" | H21: 160640015734 | I21: 1957311630 | J21: 12418.3 | N21: 43543 | O21: 142 | P21: 142 | Q21: 14-15 | R21: 43481 | S21: 43815 | T21: 43906 | W21: 43866 | X21: 37257013 | Y21: доп.согл.№7 к ДПГ-17-02-001/002 | AB21: 83 | AG21: Завершенные
A22: 21 | B22: МЖК Nova City, 19 очередь | C22: 43501 | D22: г. Астана | E22: ТОО "Милан-Астана" | F22: 110540015593 | G22: ТОО "Esil Town" | H22: 181140019271 | I22: 2227028801 | J22: 8855.87 | N22: 43511 | O22: 150 | P22: 150 | Q22: 9 | R22: 43521 | S22: 43946 | W22: 43938 | X22: 43834498 | Y22: ДПГ-19-01-001/014 | AB22: 78 | AG22: Завершенные
A23: 22 | B23: МЖК Alma City, 3-оч. 1-й пуск.комплекс | C23: 43726 | D23: г. Алматы | E23: ТОО "Qazaq Stroy" | F23: 050540016141 | G23: ТОО "ЫРЫСТЫ 46/2" | H23: 190340022583 | I23: 6600809540 | J23: 64684.2 | N23: 43728 | O23: 1008 | P23: 1118 | Q23: 9 | R23: 43711 | S23: 44257 | W23: 43965 | X23: 132016191 | Y23: ДПГ-19-02-005/024 | AB23: 81 | AG23: Завершенные
A24: 23 | B24: МЖК Амстердам, пятна 4,5,6,7,15.1 | C24: 43482 | D24: г. Астана | E24: ТОО "BAZIS-A Corp." | F24: 960340000376 | G24: ТОО "Amsterdam City" | H24: 180640022394 | I24: 3484165830 | J24: 20748.3 | N24: 43518 | O24: 110 | P24: 100 | Q24: 9-10 | R24: 43357 | S24: 44042 | W24: 44039 | X24: 68156153 | Y24: ДПГ-19-01-001/013 | AB24: 83 | AG24: Завершенные
A25: 24 | B25: ЖК Nova City 16 очередь | C25: 43634 | D25: г. Астана | E25: ТОО "Милан-Астана" | F25: 110540015593 | G25: ТОО "NC16" | H25: 181240011486 | I25: 4429569296 | J25: 20614.56 | N25: 43647 | O25: 242 | P25: 242 | Q25: 9 | R25: 43588 | S25: 44107 | W25: 44049 | X25: 86509774 | Y25: ДПГ-19-01-008/016 | AB25: 91 | AG25: Завершенные
A26: 25 | B26: МЖК Парасат, пятно 1,2 | C26: 43783 | D26: г. Алматы | E26: ТОО "SHEBERBUILD" | F26: 070240017648 | G26: ТОО "SHEBERGOOD" | H26: 070240017648 | I26: 1733779999 | J26: 7731.36 | N26: 43796 | O26: 143 | P26: 143 | Q26: 9 | R26: 43760 | S26: 43973 | T26: 44065 | W26: 44064 | X26: 30929009 | Y26: ДПГ-19-02-013/030 | AB26: 70 | AG26: Завершенные
A27: 26 | B27: ЖК Премьера | C27: 43676 | D27: г. Шымкент | E27: ТОО "Оңтүстік құрылыс Сервис" | F27: 010340004024 | G27: ТОО "Dostyq Invest Group" | H27: 190140008530 | I27: 1355115090 | J27: 8903.44 | N27: 43697 | O27: 80 | P27: 80 | Q27: 5 | R27: 43635 | S27: 43970 | T27: 44062 | U27: 44123 | W27: 44068 | X27: 24228296 | Y27: ДПГ-19-13-004/020 | AB27: 61 | AG27: Завершенные
A28: 27 | B28: МЖК Nova City, 22 очередь | C28: 43676 | D28: г. Астана | E28: ТОО "Милан-Астана" | F28: 110540015593 | G28: ТОО "NC 22" | H28: 190340029392 | I28: 2453517883 | J28: 8855.87 | N28: 43689 | O28: 150 | P28: 150 | Q28: 9 | R28: 43626 | S28: 44114 | W28: 44112 | X28: 48045915 | Y28: ДПГ-19-01-008/021 | AB28: 91 | AG28: Завершенные
A29: 28 | B29: ЖК ASQAT | C29: 43665 | D29: г. Астана | E29: ТОО "АсТи-Строй" | F29: 030740000258 | G29: ТОО "ASTI GROUP" | H29: 071240012104 | I29: 3019265161 | J29: 15344.61 | N29: 43677 | O29: 108 | P29: 108 | Q29: 7 | R29: 43633 | S29: 44180 | W29: 44165 | X29: 50272872 | Y29: ДПГ-19-01-010/018 | AB29: 91 | AG29: Завершенные
A30: 29 | B30: МЖК Argento, пятно 3 | C30: 44081 | D30: г. Астана | E30: ТОО "BAZIS-A Corp." | F30: 960340000376 | G30: ТОО "Строй Билдинг Астана" | H30: 170840009898 | I30: 1136489476 | J30: 7918.13 | N30: 43670 | O30: 85 | P30: 85 | Q30: 18 | R30: 43956 | S30: 44413 | W30: 44398 | X30: 19307570 | Y30: ДПГ-19-01-001/017 | AB30: 84 | AG30: Завершенные
A31: 30 | B31: МЖК 12 месяцев (на Макатаева), 1-очередь | C31: 43726 | D31: г. Алматы | E31: ТОО "Qazaq Stroy" | F31: 050540016141 | G31: ТОО "Макатаева 127" | H31: 190340022513 | I31: 5130621336 | J31: 36276.5 | N31: 43728 | O31: 432 | P31: 468 | Q31: 12 | R31: 43712 | S31: 44188 | W31: 44188 | X31: 102612427 | Y31: ДПГ-19-02-005/025 | AB31: 81 | AG31: Завершенные
A32: 31 | B32: ЖК Argento пятно 4, Наружные сети | C32: 43643 | D32: г. Астана | E32: ТОО "BAZIS-A Corp." | F32: 960340000376 | G32: ТОО "Строй Билдинг Астана" | H32: 170840009898 | I32: 2161436079 | J32: 12298.3 | N32: 43670 | O32: 100 | P32: 100 | Q32: 21 | R32: 43614 | S32: 44103 | T32: 44194 | W32: 44193 | X32: 41160642 | Y32: ДПГ-19-01-001/017 | AB32: 78 | AG32: Завершенные
A33: 32 | B33: ЖК Амстердам, пятна 1,2,3 | C33: 43777 | D33: г. Астана | E33: ТОО "BAZIS-A Corp." | F33: 960340000376 | G33: ТОО "Amsterdam City" | H33: 180640022394 | I33: 2176943630 | J33: 11705.1 | N33: 43783 | O33: 82 | P33: 82 | Q33: 9.1 | R33: 43712 | S33: 44193 | W33: 44193 | X33: 42801333 | Y33: доп.согл.№ 1 к ДПГ-19-01-001/013 | AB33: 84 | AG33: Завершенные
A34: 33 | B34: ЖК Бахыт, 2 очередь | C34: 43628 | D34: г. Шымкент | E34: ТОО "Оңтүстік құрылыс Сервис" | F34: 010340004024 | G34: ТОО "Композит-7" | H34: 050640012251 | I34: 4853681279 | J34: 27937.7 | N34: 43629 | O34: 168 | P34: 168 | Q34: 9 | R34: 43588 | S34: 44258 | T34: 44350 | W34: 44247 | X34: 77180276 | Y34: доп.согл. №3 к ДПГ-18-13-004/005 | Z34: 3859013800 | AB34: 61 | AG34: Завершенные
A35: 34 | B35: ЖК Ак Дидар, пятна 9-13 | C35: 43692 | D35: г. Астана | E35: ТОО "BAZIS-A Corp." | F35: 960340000376 | G35: ТОО "Ак Дидар-2" | H35: 170840012253 | I35: 2415410355 | J35: 16376.6 | N35: 43711 | O35: 276 | P35: 248 | Q35: 9 | R35: 43613 | S35: 44255 | T35: 44344 | W35: 44284 | X35: 48308207 | Y35: ДПГ-19-01-001/022 | AB35: 78 | AG35: Завершенные
B36: Увеличение стоимости ЖК "Ак Дидар", (пятна 9-13) | C36: 43875 | D36: г. Астана | E36: ТОО "BAZIS-A Corp." | F36: 960340000376 | G36: ТОО "Ак Дидар-2" | H36: 170840012253 | I36: 698876654 | J36: 4954 | N36: 43880 | O36: 0 | P36: 0 | Q36: - | R36: 43613 | S36: 44255 | T36: 44344 | W36: 44284 | X36: 13977533 | Y36: доп.согл. №1 к ДПГ-19-01-001/022 | AB36: 78 | AG36: Завершенные
A37: 35 | B37: ЖК Aspan City | C37: 43665 | D37: Алматинская обл. | E37: ТОО "Exclusive Construction (Эксклюзив Констракшн)" | F37: 051040013647 | G37: ТОО "Aspan City 2" | H37: 181040020140 | I37: 4672680111 | J37: 23277.66 | N37: 43679 | O37: 288 | P37: 267 | Q37: 12 | R37: 43651 | S37: 44058 | T37: 44150 | U37: 44242 | V37: 44331 | W37: 44321 | X37: 93453602 | Y37: ДПГ-19-02-011/019 | AB37: 73 | AG37: Завершенные
A38: 36 | B38: МЖК Бестерек, пятно 1 | C38: 43726 | D38: г. Астана | E38: ТОО "Милан-Астана" | F38: 110540015593 | G38: ТОО "BI-Village Deluxe" | H38: 070340010951 | I38: 6019547133 | J38: 26723.09 | N38: 43735 | O38: 307 | P38: 307 | Q38: 8 | R38: 43662 | S38: 44363 | W38: 44361 | X38: 119220603 | Y38: ДПГ-19-01-008/023 | AB38: 91 | AG38: Завершенные
A39: 37 | B39: МЖК Sezim Qala, 4 очередь | C39: 43791 | D39: г. Астана | E39: ТОО "Милан-Астана" | F39: 110540015593 | G39: ТОО "Туран Сити" | H39: 170340033307 | I39: 3663548205 | J39: 19815.5 | N39: 43791 | O39: 278 | P39: 278 | Q39: 2, 9, 12 | R39: 43759 | S39: 44393 | W39: 44363 | X39: 72343291 | Y39: доп.согл.№3 к ДПГ-19-01-008/015 | AB39: 91 | AG39: Завершенные
A40: 38 | B40: ЖК Sezim Qala, 7 очередь | C40: 43748 | D40: г. Астана | E40: ТОО "Милан-Астана" | F40: 110540015593 | G40: ТОО "Туран Сити" | H40: 170340033307 | I40: 5814608330 | J40: 32516 | N40: 43749 | O40: 408 | P40: 408 | Q40: 22 | R40: 43704 | S40: 44496 | W40: 44347 | X40: 114777807 | Y40: доп.согл.№2 к ДПГ-19-01-008/015 | AB40: 91 | AG40: Завершенные
A41: 39 | B41: ЖК Гулдер, 2-очередь, пятна 9,10,11,12,13,14 | C41: 43777 | D41: г. Алматы | E41: ТОО "Милан-Астана" | F41: 110540015593 | G41: ТОО "Сармат Групп-2" | H41: 190640001234 | I41: 6837749056 | J41: 32575.2 | N41: 43783 | O41: 431 | P41: 431 | Q41: 12.16 | R41: 43731 | S41: 18.05.2021 | T41: 44426 | W41: 44376 | X41: 134440701 | Y41: ДПГ-19-01-008/028 | AB41: 91 | AG41: Завершенные
A42: 40 | B42: ЖК Сердце Столицы, 1 очередь | C42: 43748 | D42: г. Астана | E42: ТОО "Милан-Астана" | F42: 110540015593 | G42: ТОО "Turan Towers" | H42: 161040020830 | I42: 6825821599 | J42: 34967.37 | N42: 43759 | O42: 291 | P42: 291 | Q42: 7,9,12,19 | R42: 43692 | S42: 03.08.2021 | T42: 44290 | U42: 44381 | V42: 44473 | W42: 44411 | X42: 132982359 | Y42: ДПГ-19-01-008/027 | AB42: 91 | AG42: Завершенные
B43: Увеличение стоимости МЖК Сердце Столицы, 1 оч. Наружные инженерные сети | C43: 43936 | D43: г. Астана | E43: ТОО "Милан-Астана" | F43: 110540015593 | G43: ТОО "Turan Towers" | H43: 161040020830 | I43: 1323442100 | J43: 0 | N43: 43970 | O43: 0 | P43: 0 | Q43: 1, 7, 9, 12, 19 | R43: 43928 | S43: 44658 | W43: 44411 | X43: 26468842 | Y43: доп.согл.№1 к ДПГ-19-01-008/027 | AB43: 91 | AG43: Завершенные
A44: 41 | B44: ЖК Абылайхан-2, пятна 4, 5, 6, 7 | C44: 43748 | D44: г. Астана | E44: ТОО "Корпорация Астана-Стройинвест" | F44: 000740002447 | G44: ТОО "СУ АСИ" | I44: 5253239788 | J44: 38863.78 | N44: 43755 | O44: 346 | P44: 348 | Q44: 13 | R44: 43721 | S44: 44324 | T44: 44416 | U44: 44508 | W44: 44494 | X44: 93660141 | Y44: ДПГ-19-01-012/026 | AB44: 75 | AG44: Завершенные
A45: 42 | B45: ЖК Discovery, Пятно 3. Блоки 1, 2, 5 | C45: 43777 | D45: г. Астана | E45: ТОО "BAZIS-A Corp." | F45: 960340000376 | G45: ТОО "Astana Real Estate 2017" | H45: 170640002219 | I45: 2439912400 | J45: 19742.65 | N45: 43802 | O45: 165 | P45: 165 | Q45: 9 | R45: 43635 | S45: 44123 | T45: 44215 | U45: 44305 | W45: 44637 | X45: 47152489 | Y45: ДПГ-19-01-001/029 | Z45: 820792616 | AA45: Нуржубалин Н. | AB45: 78 | AG45: Завершенные
A46: 43 | B46: ЖК ASQAT, очередь 2 | C46: 43875 | D46: г. Астана | E46: ТОО "АсТи-Строй" | F46: 030740000258 | G46: ТОО "ASTI GROUP" | H46: 071240012104 | I46: 1604244431 | J46: 9352.08 | N46: 43878 | O46: 106 | P46: 106 | Q46: 7 | R46: 43851 | S46: 44161 | T46: 44165 | W46: 44165 | X46: 44498721 | Y46: доп.согл. №1 к ДПГ-19-01-010/018 | AB46: 91 | AG46: Завершенные
A47: 44 | B47: ЖК ASQAT, очередь 3 | C47: 43875 | D47: г. Астана | E47: ТОО "АсТи-Строй" | F47: 030740000258 | G47: ТОО "ASTI GROUP" | H47: 071240012104 | I47: 1643232216 | J47: 9309.83 | N47: 43878 | O47: 107 | P47: 107 | Q47: 7 | R47: 43852 | S47: 44161 | T47: 44165 | W47: 44165 | AB47: 91 | AG47: Завершенные
A48: 45 | B48: МЖК Alma City, 3-оч. 2-й пуск.комплекс | C48: 43860 | D48: г. Алматы | E48: ТОО "Qazaq Stroy" | F48: 050540016141 | G48: ТОО "ЫРЫСТЫ 46/2" | H48: 190340022583 | I48: 7211511710 | J48: 78453.75 | N48: 43862 | O48: 1122 | P48: 1248 | Q48: 9 | R48: 43711 | S48: 44187 | W48: 44187 | X48: 129729726 | AB48: 84 | AG48: Завершенные
A49: 46 | B49: МЖК 12 месяцев (на Макатаева) | C49: 43860 | D49: г. Алматы | E49: ТОО "Qazaq Stroy" | F49: 050540016141 | G49: ТОО "Макатаева 127" | H49: 190340022513 | I49: 4696993688 | J49: 35931.5 | N49: 43862 | O49: 576 | P49: 624 | Q49: 12 | R49: 43843 | S49: 44188 | W49: 44188 | X49: 93939874 | Y49: доп.согл. №2 к ДПГ-19-02-005/025 | AB49: 84 | AG49: Завершенные
A50: 47 | B50: ЖК Нурсая | C50: 43970 | D50: г. Атырау | E50: ТОО "Direct Construction Service" | F50: 050440002386 | G50: ТОО "Yerkin Management Group" | H50: 170640031311 | I50: 405171695 | J50: 2903 | N50: 43992 | O50: 40 | P50: 40 | Q50: 4 | R50: 43903 | S50: 31.12.2020 | T50: 44222 | W50: 44196 | X50: 6007292 | Y50: ДПГ-20-06-018/040 | AB50: 80 | AG50: Завершенные
A51: 48 | B51: ЖК Стандарт | C51: 44070 | D51: г. Шымкент | E51: ТОО "Оңтүстік құрылыс Сервис" | F51: 010340004024 | G51: ТОО "ЖК Standard" | H51: 190140038552 | I51: 2099777543 | J51: 10658 | N51: 44088 | O51: 140 | P51: 140 | Q51: 5 | R51: 43999 | S51: 44244 | T51: 44303 | W51: 44301 | X51: 39779893 | Y51: ДПГ-20-13-004/045 | AB51: 62 | AG51: Завершенные
A52: 49 | B52: МЖК Land Mark | C52: 43875 | D52: г. Астана | E52: ТОО "BAZIS-A Corp." | F52: 960340000376 | G52: ТОО "Dostyk Land" | H52: 190240034484 | I52: 2565255008 | J52: 18164 | N52: 43889 | O52: 128 | P52: 128 | Q52: 9.12 | R52: 43803 | S52: 44160 | T52: 44252 | U52: 44341 | W52: 44301 | X52: 41256420 | Y52: доп.согл. №1 к ДПГ-20-01-001/037 | AB52: 78 | AG52: Завершенные
A53: 50 | B53: МЖК Парасат 2 очередь | C53: 43927 | D53: г. Алматы | E53: ТОО "SHEBERBUILD" | F53: 070240017648 | G53: ТОО "SHEBERGOOD" | H53: 070240017648 | I53: 3041291058 | J53: 15462.72 | N53: 43950 | O53: 288 | P53: 283 | Q53: 9 | R53: 43866 | S53: 44345 | T53: 44437 | W53: 44329 | X53: 60823921 | Y53: доп.согл. №1 к ДПГ-19-02-013/030 | AB53: 70 | AG53: Завершенные
A54: 51 | B54: МЖК SOHO | C54: 43481 | D54: г. Астана | E54: ТОО "BAZIS-A Corp." | F54: 960340000376 | G54: ТОО "Sovico group" | H54: 180240017561 | I54: 1991352860 | J54: 10697.91 | N54: 43867 | O54: 78 | P54: 78 | Q54: 7 | R54: 43783 | S54: 44227 | W54: 44214 | X54: 38237857 | Y54: ДПГ-20-01-001/32 | AB54: 78 | AG54: Завершенные
A55: 52 | B55: МЖК Nova City на Туране | C55: 43860 | D55: г. Астана | E55: ТОО "Милан-Астана" | F55: 110540015593 | G55: ТОО "СК БАЗАР" | H55: 190940030982 | I55: 5762175734 | J55: 27870 | N55: 43866 | O55: 348 | P55: 348 | Q55: 9 | R55: 43769 | S55: 44469 | W55: 44352 | X55: 110205578 | Y55: ДПГ-20-01-008/034 | AB55: 91 | AG55: Завершенные
B56: Увеличение стоимости МЖК Nova City на Туране, 1 очередь. Наружные инженерные сети. | C56: 44007 | D56: г. Астана | E56: ТОО "Милан-Астана" | F56: 110540015593 | G56: ТОО "СК БАЗАР" | H56: 190940030982 | I56: 737891954 | J56: 0 | N56: 44025 | O56: 0 | P56: 0 | Q56: - | R56: 43983 | S56: 44469 | W56: 44352 | X56: 14757839 | Y56: доп.согл. №1 к ДПГ-20-01-008/034 | AB56: 91 | AG56: Завершенные
A57: 53 | B57: МЖК Теремки, Блоки 16-27 | C57: 43998 | D57: г. Алматы | E57: ТОО "Елимай-Invest" | F57: 160640016168 | G57: ТОО "ЖК "Теремки" | H57: 200540007036 | I57: 7001848587 | J57: 55789.44 | N57: 43999 | O57: 864 | P57: 960 | Q57: 9 | R57: 43977 | S57: 44357 | T57: 44460 | W57: 44449 | X57: 140036972 | Y57: ДПГ-20-02-020/042 | AB57: 95 | AG57: Завершенные
A58: 54 | B58: МЖК Nova City на Рыскулбекова | C58: 43860 | D58: г. Астана | E58: ТОО "Милан-Астана" | F58: 110540015593 | G58: ТОО "Salamat Stroy" | H58: 180440012489 | I58: 5840045029 | J58: 31002.69 | N58: 43866 | O58: 334 | P58: 334 | Q58: 1,9,12 | R58: 43839 | S58: 44570 | W58: 44421 | X58: 115050538 | Y58: ДПГ-20-01-008/033 | AB58: 91 | AG58: Завершенные
A59: 55 | B59: МЖК Амстердам, пятна 8-10 | C59: 44053 | D59: г. Астана | E59: ТОО "BAZIS-A Corp." | F59: 960340000376 | G59: ТОО "Amsterdam City" | H59: 180640022394 | I59: 2015148840 | J59: 12132.8 | N59: 44063 | O59: 88 | P59: 88 | Q59: 10 | R59: 43955 | S59: 44620 | W59: 44377 | X59: 34813216 | Y59: доп.согл.№3 к ДПГ-19-01-001/013 | AB59: 84 | AG59: Завершенные
A60: 56 | B60: МЖК SOHO. Блок-секции 4,5,6 | C60: 44111 | D60: г. Астана | E60: ТОО "BAZIS-A Corp." | F60: 960340000376 | G60: ТОО "Sovico group" | H60: 180240017561 | I60: 3066214650 | J60: 15109.69 | N60: 44154 | O60: 119 | P60: 119 | Q60: 9.12 | R60: 43998 | S60: 44592 | W60: 44452 | X60: 52444166 | AB60: 84 | AG60: Завершенные
A61: 57 | B61: МЖК Alma City, 3-оч. 3-й пуск.комплекс | C61: 44175 | D61: г. Алматы | E61: ТОО "Qazaq Stroy" | F61: 050540016141 | G61: ТОО "ЫРЫСТЫ 46/2" | H61: 190340022583 | I61: 3080917422 | J61: 59963.8 | N61: 44179 | O61: 832 | P61: 928 | Q61: 9 | R61: 44118 | S61: 44452 | T61: 44543 | W61: 44441 | X61: 30809174 | Y61: доп.согл.№3 к ДПГ-19-02-005/024 | AB61: 71 | AG61: Завершенные
A62: 58 | B62: МЖК Nova City на Туране, 2 очередь | C62: 44060 | D62: г. Астана | E62: ТОО "Милан-Астана" | F62: 110540015593 | G62: ТОО "СК БАЗАР" | H62: 190940030982 | I62: 4767699843 | J62: 21896 | N62: 44062 | O62: 239 | P62: 239 | Q62: 9 | R62: 44001 | S62: 44530 | W62: 44477 | X62: 93279152 | Y62: доп.согл.№2 к ДПГ-20-02-008/034 | AB62: 81 | AG62: Завершенные
A63: 59 | B63: МЖК Асыл Мура, Блок А | C63: 43860 | D63: г. Астана | E63: ТОО "Милан-Астана" | F63: 110540015593 | G63: ТОО "Цесинстрой" | H63: 110340014607 | I63: 9154023704 | J63: 35661.7 | N63: 43866 | O63: 357 | P63: 358 | Q63: 16 | R63: 43843 | S63: 44477 | T63: 44569 | W63: 44553 | X63: 180082849 | Y63: ДПГ-20-01-008/031 | AB63: 91 | AG63: Завершенные
B64: Увеличение стоимости МЖК Асыл Мура, блок А. Наружные инженерные сети | C64: 44334 | D64: г. Астана | E64: ТОО "Милан-Астана" | F64: 110540015593 | G64: ТОО "Цесинстрой" | H64: 110340014607 | I64: 505795088 | J64: 0 | N64: 44344 | O64: 0 | P64: 0 | Q64: 0 | R64: 44172 | S64: 44553 | W64: 44553 | X64: 5057951 | AA64: Нуржубалин Н. | AB64: 91 | AG64: Завершенные
A65: 60 | B65: МЖК Олимпийский, 1 очередь | C65: 43875 | D65: г. Астана | E65: ТОО "Орда строй групп" | F65: 060240014641 | G65: ТОО "Orda Invest Development" | H65: 190840001896 | I65: 5767382086 | J65: 27950.19 | N65: 43903 | O65: 173 | P65: 172 | Q65: 10.18 | R65: 43817 | S65: 44487 | T65: 44579 | W65: 44559 | X65: 105944617 | Y65: ДПГ-20-01-015/036 | AB65: 70 | AG65: Завершенные
A66: 61 | B66: МЖК Терракота, 1 этап, Блоки 2, 2/1, 5, 8 и 10 | C66: 44015 | D66: г. Алматы | E66: ТОО "Елимай-Invest" | F66: 160640016168 | G66: ТОО "TEES" | H66: 190340014136 | I66: 6057003488 | J66: 39655.8 | N66: 44016 | O66: 484 | P66: 506 | Q66: 1, 18, 20 | R66: 43998 | S66: 44500 | T66: 44592 | W66: 44558 | X66: 121140070 | Y66: ДПГ-20-02-020/043 | AB66: 95 | AG66: Завершенные
A67: 62 | B67: МЖК Терракота, 2 этап, Блоки 4 и 7 | C67: 44060 | D67: г. Алматы | E67: ТОО "Елимай-Invest" | F67: 160640016168 | G67: ТОО "TEES" | H67: 190340014136 | I67: 2350110287 | J67: 16432.3 | N67: 44060 | O67: 208 | P67: 216 | Q67: 18, 20 | R67: 43998 | S67: 44592 | W67: 44558 | X67: 47002206 | Y67: доп.согл.№1 к ДПГ-20-02-020/043 | AB67: 95 | AG67: Завершенные
A68: 63 | B68: МЖК Sezim Qala 6 оч." | C68: 43875 | D68: г. Астана | E68: ТОО "Милан-Астана" | F68: 110540015593 | G68: ТОО "Туран Сити" | H68: 170340033307 | I68: 4490419686 | J68: 19814.66 | N68: 43878 | O68: 278 | P68: 278 | Q68: 2,9,12 | R68: 43784 | S68: 44302 | T68: 44393 | U68: 44510 | V68: 44602 | W68: 44557 | X68: 89098085 | Y68: доп.согл.№4 к ДПГ-19-01-008/015 | AB68: 91 | AG68: Завершенные
A69: 64 | B69: МЖК Sezim Qala 8 очередь | C69: 43927 | D69: г. Астана | E69: ТОО "Милан-Астана" | F69: 110540015593 | G69: ТОО "Туран Сити" | H69: 170340033307 | I69: 5708411131 | J69: 31505.3 | N69: 44154 | O69: 416 | P69: 416 | Q69: 1,2,22 | R69: 43892 | S69: 44622 | W69: 44559 | X69: 112958261 | AB69: 91 | AG69: Завершенные
A70: 65 | B70: МЖК Амстердам, 2 очередь, пятна 11-14 | C70: 44187 | D70: г. Астана | E70: ТОО "BAZIS-A Corp." | F70: 960340000376 | G70: ТОО "Amsterdam city" | H70: 180640022394 | I70: 2608583568 | J70: 16101.6 | N70: 44193 | O70: 116 | P70: 116 | Q70: 10 | R70: 43986 | S70: 44712 | W70: 44482 | X70: 24583147 | Y70: доп.согл.№4 к ДПГ-19-01-001/013 | Z70: 311733873 | AB70: 84 | AG70: Завершенные
A71: 66 | B71: МЖК Ак Дидар, пятна 14, 15 | C71: 44187 | D71: г. Астана | E71: ТОО "BAZIS-A Corp." | F71: 960340000376 | G71: ТОО "Ак Дидар-2" | H71: 170840012253 | I71: 1657025210 | J71: 12551.1 | N71: 44195 | O71: 171 | P71: 171 | Q71: 9.12 | R71: 44090 | S71: 44865 | W71: 44501 | X71: 15578040 | Y71: доп.согл. №3к ДПГ-19-01-001/022 | Z71: 211128707 | AB71: 84 | AG71: Завершенные
A72: 67 | B72: МЖК Гулдер 3 очередь | C72: 44109 | D72: г. Алматы | E72: ТОО "Компания Индустрия Строительства" | F72: 110640013302 | G72: ТОО "Сармат Групп" | H72: 170840035976 | I72: 4323925897 | J72: 17609.2 | N72: 44165 | O72: 237 | P72: 237 | Q72: 16 | R72: 44090 | S72: 44729 | W72: 44722 | X72: 85270009 | Y72: ДПГ-20-01-022/048 | AB72: 98 | AG72: Завершенные
A73: 68 | B73: МЖК Athletic | C73: 44175 | D73: г. Астана | E73: ТОО "Comfort Development KZ" | F73: 210940032945 | G73: ТОО "Comfort Туран" | H73: 190940031752 | I73: 2855648417 | J73: 13898.8 | N73: 44209 | O73: 126 | P73: 126 | Q73: 12 | R73: 44096 | S73: 44642 | W73: 44376 | X73: 16 330 080 | Y73: ДПГ-20-01-002/049 | AA73: Нурбаев Н. | AB73: 77 | AG73: Завершенные
A74: 69 | B74: МЖК Аллея тысячелетия, блок 24 | C74: 44232 | D74: г. Астана | E74: ТОО "BAZIS-A Corp." | F74: 960340000376 | G74: ТОО "Аллея тысячелетия-4" | H74: 180540027976 | I74: 2435069335 | J74: 16551 | N74: 44256 | O74: 144 | P74: 144 | Q74: 7 | R74: 43964 | S74: 44574 | W74: 44491 | X74: 21061933 | Y74: ДПГ-21-01-001/053 | AB74: 84 | AG74: Завершенные
A75: 70 | B75: МЖК Сити Плюс, 1-й пусковой комплекс, блоки 1-11 | C75: 44391 | D75: г. Алматы | E75: ТОО "Елимай-Invest" | F75: 160640016168 | G75: ТОО "Commercial Estate Company" | H75: 200440009039 | I75: 4706806971 | J75: 55984.28 | N75: 44403 | O75: 756 | P75: 844 | Q75: 9 | R75: 44355 | S75: 44561 | W75: 44558 | X75: 47068070 | Y75: ДПГ-21-02-020/075 | AA75: Сарсембаева Ж. | AB75: 68 | AG75: Завершенные
A76: 71 | B76: МЖК Nova City на Рыскулбекова 2 очередь | C76: 44336 | D76: г. Астана | E76: ТОО "Милан-Астана" | F76: 110540015593 | G76: ТОО "Salamat stroy" | H76: 180440012489 | I76: 3935294461 | J76: 19799.46 | N76: 44344 | O76: 207 | P76: 207 | Q76: 9, 12 | R76: 44242 | S76: 44734 | W76: 44522 | X76: 38776285 | AB76: 81 | AG76: Завершенные
A77: 72 | B77: МЖК Сердце Столицы, 2 оч. | C77: 44287 | D77: г. Астана | E77: ТОО "Милан-Астана" | F77: 110540015593 | G77: ТОО "Turan Towers" | H77: 161040020830 | I77: 6857592308 | J77: 35711.7 | N77: 44309 | O77: 291 | P77: 291 | Q77: 1, 7, 9, 12, 19 | R77: 44293 | S77: 44658 | W77: 44553 | X77: 67971878 | AB77: 81 | AG77: Завершенные
A78: 73 | B78: МЖК SOHO, блок 3,4 | C78: 44232 | D78: г. Астана | E78: ТОО "BAZIS-A Corp." | F78: 960340000376 | G78: ТОО "Sovico group" | H78: 180240017561 | I78: 3481930375 | J78: 17098.46 | N78: 44256 | O78: 80 | P78: 80 | Q78: 7.9 | R78: 09.12.2020 г. – блок 3 (секции 7,8,9); 19.08.2020 г. – блок 4 (паркинг) | S78: 44592 | W78: 44506 | X78: 30330124 | AB78: 84 | AG78: Завершенные
A79: 74 | B79: МЖК Шахристан | C79: 44230 | D79: г. Астана | E79: ТОО "Жетісу ЖҚ" | F79: 031240005283 | G79: ТОО "УК Шахристан" | H79: 200140012157 | I79: 3336486162 | J79: 16227.57 | N79: 44251 | O79: 160 | P79: 182 | Q79: 7, 9 | R79: 44158 | S79: 44615 | W79: 44538 | X79: 28025328 | AB79: 63 | AG79: Завершенные
A80: 75 | B80: МЖК Argento п 1,2 | C80: 44378 | D80: г. Астана | E80: ТОО "BAZIS-A Corp." | F80: 960340000376 | G80: ТОО "Строй Билдинг Астана" | H80: 170840009898 | I80: 2206013208 | J80: 15957 | N80: 44404 | O80: 170 | P80: 170 | Q80: 18 | R80: 44246 | S80: 44611 | W80: 44532 | X80: 19793732 | AB80: 74 | AG80: Завершенные
A81: 76 | B81: МЖК в г. Атырау | C81: 44375 | D81: г. Атырау | E81: ТОО "Direct Construction Service" | F81: 050440002386 | G81: ТОО "Yerkin Management Group" | H81: 170640031311 | I81: 922782493 | J81: 6326.2 | N81: 44398 | O81: 72 | P81: 72 | Q81: 9 | R81: 44234 | S81: 44642 | W81: 44615 | X81: 8506904 | Y81: ДПГ-21-06-018/072 | AB81: 80 | AG81: Завершенные
A82: 77 | B82: МЖК Алма Тау, пятна 7,8 | C82: 44313 | D82: Алматинская обл. | E82: ТОО "Строительная Компания Элитстрой" | F82: 060740002715 | G82: ТОО "УК "Алма Тау 2021" | H82: 210240029444 | I82: 2271535493 | J82: 11439.2 | N82: 44356 | O82: 234 | P82: 234 | Q82: 9 | R82: 44260 | S82: 44686 | W82: 44510 | X82: 18977698 | AB82: 73 | AG82: Завершенные
A83: 78 | B83: МЖК Esil Tower, 1 оч. | C83: 44287 | D83: г. Астана | E83: ТОО "Ethna Group" | F83: 940940000027 | G83: ТОО "Riverside Tower" | H83: 201040021501 | I83: 2374319871 | J83: 15603.49 | N83: 44309 | O83: 131 | P83: 159 | Q83: 24 | R83: 44235 | S83: 44688 | W83: 44606 | X83: 20073340 | AB83: 77 | AG83: Завершенные
A84: 79 | B84: МЖК HEAVEN | C84: 44299 | D84: г. Алматы | E84: ТОО "Елимай-Invest" | F84: 160640016168 | G84: ТОО "КапСтрой Девелопмент" | H84: 190140012211 | I84: 1499679126 | J84: 19657.2 | N84: 44309 | O84: 303 | P84: 322 | Q84: 12, 13, 16 | R84: 44217 | S84: 44702 | W84: 44557 | X84: 13332057 | Y84: ДПГ-21-02-020/060 | AA84: Сарсембаева Ж. | AB84: 95 | AG84: Завершенные
A85: 80 | B85: МЖК Асыл Мура, блок F | C85: 44260 | D85: г. Астана | E85: ТОО "Garant stroy" | F85: 170140020417 | G85: ТОО "УКиСС" | H85: 060140001190 | I85: 5890831329 | J85: 29839.25 | N85: 44287 | O85: 256 | P85: 256 | Q85: 9 | R85: 44239 | S85: 44693 | W85: 44686 | X85: 57798194 | Z85: 1401206941 | AB85: 92 | AG85: Завершенные
A86: 81 | B86: МЖК Gul Ana | C86: 44362 | D86: г. Алматы | E86: ТОО "KazSMU" | F86: 970540007997 | G86: ТОО "Gul-Ana" | H86: 111240020442 | I86: 3185907288 | J86: 14982.7 | N86: 44390 | O86: 184 | P86: 184 | Q86: 12 | R86: 44286 | S86: 44742 | W86: 44672 | X86: 26936820 | AB86: 68 | AG86: Завершенные
A87: 82 | B87: МЖК Әулиет | C87: 44321 | D87: г. Астана | E87: ТОО "Ңұр Астана Құрылыс" | F87: 060140000846 | G87: ТОО "AULET CONSTRUCTION" | H87: 191040008123 | I87: 9247229121 | J87: 37650.2 | N87: 44355 | O87: 328 | P87: 360 | Q87: 9, 12 | R87: 44222 | S87: 44707 | W87: 44694 | X87: 78601448 | AB87: 70 | AG87: Завершенные
A88: 83 | B88: МЖК Landmark | C88: 44217 | D88: г. Астана | E88: ТОО "BAZIS-A Corp." | F88: 960340000376 | G88: ТОО "Dostyk Land" | H88: 190240034484 | I88: 2762404808 | J88: 17400.61 | N88: 44239 | O88: 136 | P88: 136 | Q88: 18 | R88: 44187 | S88: 44795 | W88: 44792 | X88: 25201828 | Z88: 1080839705 | AB88: 84 | AG88: Завершенные
A89: 84 | B89: МЖК АТМОСФЕРА | C89: 44462 | D89: г. Астана | E89: ТОО "Tau House Development" | F89: 110540008868 | G89: ТОО "BERKAT-BUILDING" | H89: 190440023486 | I89: 8276765515 | J89: 29337.95 | N89: 44474 | O89: 322 | P89: 332 | Q89: 9 | R89: 44302 | S89: 44758 | W89: 44719 | X89: 72595753 | AB89: 72 | AG89: Завершенные
A90: 85 | B90: МЖК Гулдер 3 очередь, 1 пусковой | C90: 44287 | D90: г. Алматы | E90: ТОО "Компания Индустрия Строительства" | F90: 110640013302 | G90: ТОО "Сармат Групп" | H90: 170840035976 | I90: 3001447327 | J90: 14814.8 | N90: 44342 | O90: 165 | P90: 165 | Q90: 12 | R90: 44187 | S90: 44734 | W90: 44722 | X90: 29331899 | Y90: ДПГ-20-01-022/048 от 30.11.2020 доп.согл.№1 от 26.05.2021 | Z90: 862013053 | AA90: Нуржубалин Н. | AB90: 98 | AG90: Завершенные
A91: 86 | B91: МЖК Теремки, 1-й пусковой комплекс, блоки 2-15 | C91: 44375 | D91: г. Алматы | E91: ТОО "Елимай-Invest" | F91: 160640016168 | G91: ТОО "ЖК "Теремки" | H91: 200540007036 | I91: 7142974193 | J91: 73948.3 | N91: 44392 | O91: 882 | P91: 1058 | Q91: 9 | R91: 44347 | S91: 44742 | W91: 44719 | X91: 71429472 | Y91: ДПГ-20-02-020\042 от 17.06.2020 доп.согл. № 2 от 15.07.2021 к | AA91: Сарсембаева Ж. | AB91: 68 | AG91: Завершенные
A92: 87 | B92: МЖК Alma City 4-1, 1 этап | C92: 44455 | D92: г. Алматы | E92: ТОО "Елимай-Invest" | F92: 160640016168 | G92: ТОО "Ңұр City Invest" | H92: 160940030233 | I92: 7304262241 | J92: 80501.6 | N92: 44469 | O92: 980 | P92: 980 | Q92: 5 | R92: 44410 | S92: 44744 | W92: 44741 | X92: 73042624 | Y92: ДПГ-21-02-020/085 | AA92: Сарсембаева Ж. | AB92: 68 | AG92: Завершенные
A93: 88 | B93: МЖК Alma City 4-1, 2 этап, Блоки 1-8, 36-39, 43-46 | C93: 44509 | D93: г. Алматы | E93: ТОО "Елимай-Invest" | F93: 160640016168 | G93: ТОО "Ңұр City Invest" | H93: 160940030233 | I93: 4899793782 | J93: 60494 | N93: 44525 | O93: 730 | P93: 730 | Q93: 5 | R93: 44410 | S93: 44744 | W93: 44741 | X93: 48997938 | Y93: ДПГ-21-02-020/085 от 30.09.2021 доп.согл. №1 от 25.11.2021 к | AA93: Сарсембаева Ж. | AB93: 68 | AG93: Завершенные
A94: 89 | B94: МЖК Стандарт, 2 очередь | C94: 44404 | D94: г. Шымкент | E94: ТОО "Оңтүстік құрылыс Сервис" | F94: 010340004024 | G94: ТОО "ЖК Standard" | H94: 190140038552 | I94: 6015465822 | J94: 24557.72 | N94: 44421 | O94: 288 | P94: 288 | Q94: 9 | R94: 44348 | S94: 44805 | W94: 44754 | X94: 60154658 | Y94: ДПГ-21-13-004/078 | AA94: Нурбаев Н. | AB94: 88 | AG94: Завершенные
A95: 90 | B95: МЖК Терракота, 3 этап, блоки 3, 6, 9, 11 и 12 | C95: 44238 | D95: г. Алматы | E95: ТОО "Елимай-Invest" | F95: 160640016168 | G95: ТОО "TEES" | H95: 190340014136 | I95: 4039352205 | J95: 47954.7 | N95: 44257 | O95: 353 | P95: 374 | Q95: 1, 18, 20 | R95: 44119 | S95: 44757 | W95: 44750 | X95: 40393522 | Y95: ДПГ-20-02-020/043 доп.согл. № 2 от 02.03.2021г. | AA95: Сарсембаева Ж. | AB95: 95 | AG95: Завершенные
A96: 91 | B96: МЖК Ақан Сері | C96: 44306 | D96: г. Астана | E96: ТОО "MabexTrade Ltd" | F96: 040640007005 | G96: ТОО "MAB Qurylys KZ" | H96: 210140033558 | I96: 3601621272 | J96: 17438.6 | N96: 44330 | O96: 165 | P96: 165 | Q96: 7 | R96: 44246 | S96: 44792 | W96: 44706 | X96: 35250302 | Y96: ДПГ-21-01-027/061 | AA96: Далматова Д. | AB96: 80 | AG96: Завершенные
A97: 92 | B97: МЖК Millenium Park, пятно 3, блок 23 | C97: 44341 | D97: г. Астана | E97: ТОО "BAZIS-A Corp." | F97: 960340000376 | G97: ТОО "Аллея Тысячелетия-4" | H97: 180540027976 | I97: 2037222803 | J97: 16601 | N97: 44358 | O97: 114 | P97: 114 | Q97: 7 | R97: 44271 | S97: 44880 | W97: 44725 | AB97: 84 | AG97: Завершенные
A98: 93 | B98: МЖК Балауса | C98: 44434 | D98: г. Астана | E98: ТОО "Sensata Construction" | F98: 041040007551 | G98: ТОО "Sigma Byild" | H98: 191040024998 | I98: 7302547392 | J98: 26569.7 | N98: 44454 | O98: 285 | P98: 285 | Q98: 9 | R98: 44334 | S98: 44793 | W98: 44726 | X98: 46197444 | Y98: ДПГ-21-01-036/082 | AA98: Сарсембаева Ж. | AB98: 93 | AG98: Завершенные
A99: 94 | B99: МЖК NEXPO CITY | C99: 44270 | D99: г. Астана | E99: ТОО "Garant stroy" | F99: 170140020417 | G99: ТОО "NEXPO City" | H99: 210140037639 | I99: 9031081158 | J99: 51904.6 | N99: 44287 | O99: 400 | P99: 447 | Q99: 9,10,15 | R99: 44240 | S99: 45029 | W99: 44736 | X99: 87400172 | Y99: ДПГ-21-01-025/056 | Z99: 3732693043 | AA99: Сарсембаева Ж. | AB99: 92 | AG99: Завершенные
A100: 95 | B100: МЖК Монако пятно 3 | C100: 44250 | D100: г. Астана | E100: ТОО "BAZIS-A Corp." | F100: 960340000376 | G100: ТОО "Euro City-1" | H100: 190440041434 | I100: 3619711613 | J100: 21468.49 | N100: 44285 | O100: 141 | P100: 141 | Q100: 8,12,14 | R100: 44224 | S100: 44862 | W100: 44846 | X100: 35 604 422 | Y100: ДПГ-21-01-001/054 | Z100: 910647998 | AA100: Нуржубалин Н. | AB100: 84 | AG100: Завершенные
...

Sheet Действующие
D1: Гарантийный случай
D2: Консервация
D3: ЧС
B4: Действующие проекты | D4: Акты ввода на регистрации
A6: № | B6: Наименование Проекта | C6: Дата решение Правления/СД | D6: Регион | E6: Застройщик | F6: БИН Застройщика | G6: Уполномоченная компания | H6: БИН Уполномоченной компании | I6: Стоимость, тенге | J6: Площадь, кв.м по Проекту | K6: Площадь квартир, кв.м по Проекту | L6: Площадь коммерческих помещений, кв.м. | M6: Себестоимость тыс.тенге/1 м2 | N6: Цена реал. тыс.тенге/1 м2 | O6: Дата заключения договора о предоставлении гарантии | P6: Количество квартир по Проекту | Q6: Количество квартир по факту (после ввода)* | R6: Этажность | S6: Дата начала строительства | T6: Дата завершения | U6: Дата пролонгации 1 | V6: Дата пролонгации 2 | W6: Дата пролонгации 3 | X6: Дата завершения 2/Дата по АПОЭ | Y6: Гарантийный взнос, тенге | Z6: № ДПГ | AA6: Итоговая стоимость с учетом снижения обязательств | AB6: Исполнитель | AC6: Куратор | AD6: Балл Застройщика | AE6: Кол-во продлении | AF6: Кол-во модерации | AG6: Номер в SB | AH6: Наличие "Зеленого сертификатв" | AI6: Регион Кол-во | AJ6: Регион Ст-ть | AK6: Год Кол-во | AL6: Год Ст-ть | AM6: Статус
A7: 1 | B7: МЖК JM CITY Дом Парк | C7: 44497 | D7: г. Астана | E7: ТОО "Каспий Құрылыс ЛТД" | F7: 060740001628 | G7: ТОО "Garant Investment" | H7: 170440014681 | I7: 14682663880 | J7: 52536.8 | K7: 35232.12 | L7: 3356.68 | M7: 279.474 | N7: 385 | O7: 44518 | P7: 390 | R7: 12.16 | S7: 44258 | T7: 45294 | U7: 45385 | V7: 45476 | W7: 45568 | X7: 03.10.2024 Гарантийный случай | Y7: 131346323 | Z7: ДПГ-21-01-039/098 | AB7: Баркинхоев А.М. | AC7: Алимжанова Д.К. | AD7: 100 | AE7: 3 | AI7: г. Астана | AJ7: г. Астана | AK7: =CONCATENATE(YEAR(O7)," год") -> 2021 год | AL7: =CONCATENATE(YEAR(O7)," год") -> 2021 год | AM7: 1
A8: 2 | B8: МЖК Алия, 2 очередь | C8: 44504 | D8: г. Актобе | E8: ТОО "Сартай Энерго Сервис" | F8: 070240022179 | G8: ТОО "K7 Engineering" | H8: 191040002530 | I8: 7324207552 | J8: =84002.5-35757.72 -> 48244.78 | K8: 35637.8 | M8: 154.4 | N8: 200 | O8: 44523 | P8: =1040-480 -> 560 | R8: 5 | S8: 45026 | T8: 45848 | X8: 45848 | Y8: 116526220 | Z8: ДПГ-21-04-021/096 | AB8: Аяпова Г.Н. | AC8: Жусанова Т.А. | AD8: 80 | AE8: 0 | AI8: г. Актобе | AJ8: г. Актобе | AK8: =CONCATENATE(YEAR(O8)," год") -> 2021 год | AL8: =CONCATENATE(YEAR(O8)," год") -> 2021 год | AM8: 1
A9: 3 | B9: МЖК Kerim | C9: 44749 | D9: г. Астана | E9: ТОО "Актау Коркем Курылыс" | F9: 180440021488 | G9: ТОО "ОрдаСтройИнжиниринг" | H9: 110940007041 | I9: 5361772296 | J9: 34095.27 | K9: 22518.75 | L9: 3377.59 | M9: 157.2 | N9: 320 | O9: 44783 | P9: 294 | R9: 8 | S9: 44636 | T9: 45185 | U9: 45276 | V9: 45367 | X9: 16.03.2024 Акт на регистрации | Y9: 22318259 | Z9: ДПГ-22-01-054/117 | AB9: Баркинхоев А.М. | AC9: Алимжанова Д.К. | AD9: 93 | AE9: 2 | AI9: г. Астана | AJ9: г. Астана | AK9: =CONCATENATE(YEAR(O9)," год") -> 2022 год | AL9: =CONCATENATE(YEAR(O9)," год") -> 2022 год | AM9: 1
A10: 4 | B10: МЖК SPARKLE DIAMOND | C10: 44777 | D10: г. Усть-Каменогорск | E10: ТОО "ВВД-Құрылыс" | F10: 060240025805 | G10: ТОО "SPARKLE DIAMOND" | H10: 220540001566 | I10: 3704798634 | J10: 10948.36 | K10: 7609.46 | L10: 1455.3 | M10: 338.388 | N10: 445.5 | O10: 44800 | P10: 93 | R10: 5 | S10: 44691 | T10: 45422 | U10: 45514 | X10: 10.08.2024 Гарантийный случай | Y10: 33068755 | Z10: ДПГ-22-16-055/120 | AB10: Баркинхоев А.М. | AC10: Алимжанова Д.К. | AD10: 84 | AE10: 1 | AG10: 273 | AI10: г. Усть-Каменогорск | AJ10: г. Усть-Каменогорск | AK10: =CONCATENATE(YEAR(O10)," год") -> 2022 год | AL10: =CONCATENATE(YEAR(O10)," год") -> 2022 год | AM10: 1
A11: 5 | B11: МЖК Cемья, 2 очередь | C11: 44796 | D11: г. Костанай | E11: ТОО "Trans Service Company AST" | F11: 080740001641 | G11: ТОО "ИННОВАЦИЯ ПЛЮС" | H11: 220240017482 | I11: 881590818 | J11: 6145.2 | K11: 2059.6 | M11: 216.9 | N11: 257.5 | O11: 44823 | P11: 68 | R11: 4 | S11: 44679 | T11: 45258 | U11: 45350 | V11: 28.05.2024/ продлен по ЧС до 12.07.2024 | X11: 12.07.2024 Акт на регистрации | Y11: 15542092 | Z11: ДПГ-22-10-056/121 | AB11: Кенесов М.Г. | AC11: Арыстанбекова А.И. | AD11: 81 | AE11: 2 | AG11: 246 | AI11: г. Костанай | AJ11: г. Костанай | AK11: =CONCATENATE(YEAR(O11)," год") -> 2022 год | AL11: =CONCATENATE(YEAR(O11)," год") -> 2022 год | AM11: 1
A12: 6 | B12: МЖК Яссауи | C12: 44939 | D12: г. Астана | E12: ТОО "Айзия KZ" | F12: 121240010070 | G12: ТОО "Astana oil trade" | H12: 100740015241 | I12: 6548335303 | J12: 30385.95 | K12: 17064.44 | L12: 1435.64 | M12: 304.773 | N12: 393.237 | O12: 44959 | P12: 295 | R12: 1,12,16 | S12: 44895 | T12: 45381 | U12: 45473 | V12: 45565 | W12: 45656 | X12: 45656 | Y12: 61057630 | Z12: ДПГ-23-01-029/129 | AB12: Баркинхоев А.М. | AC12: Алимжанова Д.К. | AD12: 75 | AE12: 1 | AG12: 301 | AI12: г. Астана | AJ12: г. Астана | AK12: =CONCATENATE(YEAR(O12)," год") -> 2023 год | AL12: =CONCATENATE(YEAR(O12)," год") -> 2023 год | AM12: 1
A13: 7 | B13: МЖК Asyl Tas | C13: 44978 | D13: г. Шымкент | E13: ТОО "ВВД-Құрылыс" | F13: 060240025805 | G13: ТОО "CRYSTAL SHYMKENT" | H13: 221140027032 | I13: 2757296296 | J13: 9446.26 | K13: 6432.11 | L13: 1306.1 | M13: 291.9 | N13: 421.9 | O13: 44991 | P13: 103 | R13: 5 | S13: 44903 | T13: 45268 | U13: 45359 | V13: 45451 | W13: 45543 | X13: 08.09.2024 Гарантийный случай | Y13: 24124259 | Z13: ДПГ-23-13-055/132 | AB13: Исмаков А.С. | AC13: Жакыпбеков А.Д. | AD13: 85 | AE13: 3 | AG13: 327 | AI13: г. Шымкент | AJ13: г. Шымкент | AK13: =CONCATENATE(YEAR(O13)," год") -> 2023 год | AL13: =CONCATENATE(YEAR(O13)," год") -> 2023 год | AM13: 1
A14: - | B14: Увеличение стоимости МЖК Kerim | C14: 44973 | D14: г. Астана | E14: ТОО "Актау Коркем Курылыс" | F14: 180440021488 | G14: ТОО "ОрдаСтройИнжиниринг" | H14: 110940007041 | I14: 2441858042 | J14: 0 | M14: - | N14: - | O14: 45000 | P14: 0 | R14: 0 | S14: 44636 | T14: 45185 | U14: 45276 | V14: 45367 | X14: 16.03.2024 Акт на регистрации | Y14: 24418580 | Z14: ДС № 2 к ДПГ-22-01-054/117 | AB14: Баркинхоев А.М. | AC14: Алимжанова Д.К. | AD14: 93 | AE14: 2 | AG14: 340 | AJ14: г. Астана | AL14: =CONCATENATE(YEAR(O14)," год") -> 2023 год
A15: 8 | B15: МЖК Аман пятно 7 | C15: 44992 | D15: г. Астана | E15: ТОО "BAZIS-A Corp." | F15: 960340000376 | G15: ТОО "Орынбор 2017" | H15: 160340010168 | I15: 2596718603 | J15: 10209.6 | K15: 7356.9 | L15: 489.7 | M15: 254.341 | N15: 390 | O15: 45016 | P15: 135 | R15: 16 | S15: 44853 | T15: 45370 | U15: до 19.03.2025 консервация проекта | X15: 45735 | Y15: 24521857 | Z15: ДПГ-23-01-001/134 | AB15: Баркинхоев А.М. | AC15: Алимжанова Д.К. | AD15: 85 | AE15: 0 | AG15: 322 | AI15: г. Астана | AJ15: г. Астана | AK15: =CONCATENATE(YEAR(O15)," год") -> 2023 год | AL15: =CONCATENATE(YEAR(O15)," год") -> 2023 год | AM15: 1
A16: 9 | B16: МЖК Apartex Burabay | C16: 45023 | D16: Акмолинская область, г. Щучинск | E16: ТОО "Биik Шаңырақ" | F16: 140740007872 | G16: ТОО "Apartex Burabay" | H16: 140340019900 | I16: 380442507 | J16: 2497.15 | K16: 1965.55 | M16: 152.351 | N16: 271.833 | O16: 45044 | P16: 60 | R16: 5 | S16: 44974 | T16: 45155 | U16: 45247 | V16: 45339 | W16: 17.05.2024/ продлен по ЧС до 28.06.2024 | X16: 27.06.2024 Акт на регистрации | Y16: 3406925 | Z16: ДПГ-23-03-034/137 | AB16: Кенесов М.Г. | AC16: Арыстанбекова А.И. | AD16: 89 | AE16: 3 | AG16: 354 | AI16: Акмолинская область | AJ16: Акмолинская область | AK16: =CONCATENATE(YEAR(O16)," год") -> 2023 год | AL16: =CONCATENATE(YEAR(O16)," год") -> 2023 год | AM16: 1
A17: 10 | B17: МЖК Sezim Qala, очередь 13 | C17: 45051 | D17: г. Астана | E17: ТОО "Nova City Development" | F17: 110540015593 | G17: ТОО "Ғимарат НС" | H17: 130740010573 | I17: 6608817195 | J17: 20565.12 | K17: 16685.12 | M17: 321.361 | N17: 440 | O17: 45077 | P17: 278 | R17: 20 | S17: 44981 | T17: 45620 | X17: 02.10.2024 Акт на регистрации | Y17: 66088172 | Z17: ДПГ-23-01-008/141 | AB17: Баркинхоев А.М. | AC17: Алимжанова Д.К. | AD17: 92 | AE17: 0 | AF17: 0 | AG17: 368 | AI17: г. Астана | AJ17: г. Астана | AK17: =CONCATENATE(YEAR(O17)," год") -> 2023 год | AL17: =CONCATENATE(YEAR(O17)," год") -> 2023 год | AM17: 1
A18: 11 | B18: МЖК Столичный -2, блок 4 | C18: 45104 | D18: г. Астана | E18: ТОО "MERIDIAN stroy LTD." | F18: 070740007004 | G18: ТОО "EGREGOR OF FINANCE SH.R." | H18: 180540002396 | I18: 3834322743 | J18: 12795 | K18: 9388.5 | L18: 526.5 | M18: 299.674 | N18: 440 | O18: 45126 | P18: 161 | R18: 24 | S18: 45027 | T18: 45454 | U18: 45546 | X18: 13.08.2024 Акт на регистрации | Y18: 33018568 | Z18: ДПГ-23-01-047/146 | AB18: Баркинхоев А.М. | AC18: Алимжанова Д.К. | AD18: 66 | AE18: 1 | AF18: 0 | AG18: 362 | AI18: г. Астана | AJ18: г. Астана | AK18: =CONCATENATE(YEAR(O18)," год") -> 2023 год | AL18: =CONCATENATE(YEAR(O18)," год") -> 2023 год | AM18: 1
A19: 12 | B19: МЖК "PARASAT II, 1 очередь (п.1-6)" | C19: 45111 | D19: г. Алматы | E19: ТОО "SHEBERGOOD" | F19: 070240017648 | G19: ТОО "PARASAT II" | H19: 210740017974 | I19: 11378893818 | J19: 26579 | K19: 20305.2 | L19: 1218.3 | M19: 428.115 | N19: 563.661 | O19: 45127 | P19: 381 | R19: 9 | S19: 45014 | T19: 45564 | U19: 45655 | X19: 45655 | Y19: 100323683 | Z19: ДПГ-23-02-064/147 | AB19: Кожухова Д.Б. | AC19: Смайлова Д.Н. | AD19: 63 | AE19: 0 | AF19: 0 | AG19: 393 | AI19: г. Алматы | AJ19: г. Алматы | AK19: =CONCATENATE(YEAR(O19)," год") -> 2023 год | AL19: =CONCATENATE(YEAR(O19)," год") -> 2023 год | AM19: 1
A20: 13 | B20: МЖК Лесная поляна, 12 очередь, 46Д | C20: 45125 | D20: Акмолинская область, г. Косшы | E20: ТОО "Марапат 2011" | F20: 111140016064 | G20: ТОО "LP City" | H20: 211040012059 | I20: 2953550085 | J20: 14028.4 | K20: 9219.4 | L20: 1971.1 | M20: 263.933 | N20: 289.371 | O20: 45156 | P20: 210 | R20: 5 | S20: 45005 | T20: 45588 | X20: 27.09.2024 акт на регистрации | Y20: 22334217 | Z20: ДПГ-23-03-049/148 | AB20: Кенесов М.Г. | AC20: Арыстанбекова А.И. | AD20: 86 | AE20: 0 | AF20: 1 | AG20: 401 | AI20: Акмолинская область | AJ20: Акмолинская область | AK20: =CONCATENATE(YEAR(O20)," год") -> 2023 год | AL20: =CONCATENATE(YEAR(O20)," год") -> 2023 год | AM20: 1
A21: 14 | B21: МЖК Маяк | C21: 45139 | D21: Алматинская область, г.Конаев | E21: ТОО "КОРПОРАЦИЯ "АСТАНА-СТРОЙИНВЕСТ" | F21: 000740002447 | G21: ТОО "MDI CONSTRUCTION" | H21: 190440002700 | I21: 4916104675 | J21: 15148.34 | K21: 13381.08 | L21: 574.5 | M21: 324.531 | N21: 450 | O21: 45156 | P21: 216 | R21: 4 | S21: 45112 | T21: 45356 | U21: 45448 | V21: 45540 | X21: 45540 | Y21: 44559067 | Z21: ДПГ-23-05-012/149 | AB21: Кожухова Д.Б. | AC21: Смайлова Д.Н. | AD21: 79 | AE21: 1 | AF21: 1 | AG21: 388 | AI21: Алматинская область | AJ21: Алматинская область | AK21: =CONCATENATE(YEAR(O21)," год") -> 2023 год | AL21: =CONCATENATE(YEAR(O21)," год") -> 2023 год | AM21: 1
A22: 15 | B22: МЖК New City 1-2 (МЖК Ferrum City) | C22: 45153 | D22: г. Астана | E22: ТОО "Ferrum Co." | F22: 091040005188 | G22: ТОО "New City1-2" | H22: 210740017161 | I22: 4002124719 | J22: 14200.88 | K22: 8791.97 | L22: 1122.58 | M22: 403.662 | N22: 458.76 | O22: 45177 | P22: 117 | R22: 9.18 | S22: 45083 | T22: 45632 | X22: 45632 | Y22: 32891558 | Z22: ДПГ-23-01-066/152 | AB22: Баркинхоев А.М. | AC22: Алимжанова Д.К. | AD22: 65 | AE22: 0 | AF22: 1 | AG22: 406 | AI22: г. Астана | AJ22: г. Астана | AK22: =CONCATENATE(YEAR(O22)," год") -> 2023 год | AL22: =CONCATENATE(YEAR(O22)," год") -> 2023 год | AM22: 1
A23: 16 | B23: МЖК Лесная поляна, 12 очередь, 49Д | C23: 45181 | D23: Акмолинская область, г. Косшы | E23: ТОО "Марапат 2011" | F23: 111140016064 | G23: ТОО "LP City" | H23: 211040012059 | I23: 2623982344 | J23: 11041.2 | K23: 7287.6 | L23: 1507.2 | M23: 237.654 | N23: 314.971 | O23: 45197 | P23: 140 | R23: 5 | S23: 45142 | T23: 45630 | X23: 45630 | Y23: 15415734 | Z23: доп.согл. №1 к ДПГ-23-03-049/148 от 18.08.23г. | AB23: Кенесов М.Г. | AC23: Арыстанбекова А.И. | AD23: 81 | AE23: 0 | AF23: 1 | AG23: 419 | AI23: Акмолинская область | AJ23: Акмолинская область | AK23: =CONCATENATE(YEAR(O23)," год") -> 2023 год | AL23: =CONCATENATE(YEAR(O23)," год") -> 2023 год | AM23: 1
A24: 17 | B24: МЖК Жаным, 1 пусковой комплекс (МЖК V Club) | C24: 45188 | D24: г. Усть-Каменогорск | E24: ТОО "Biryuza Construction» | F24: 040440036894 | G24: ТОО "УК Шанырак Строй" | H24: 230340036850 | I24: 1802298543 | J24: 6888.13 | K24: 5523.29 | M24: 261.652 | N24: 376.667 | O24: 45210 | P24: 63 | R24: 9 | S24: 45159 | T24: 45556 | U24: 45647 | X24: 45647 | Y24: 14849026 | Z24: ДПГ-23-16-068/155 | AB24: Баркинхоев А.М. | AC24: Алимжанова Д.К. | AD24: 66 | AE24: 0 | AF24: 1 | AG24: 426 | AI24: г. Усть-Каменогорск | AJ24: г. Усть-Каменогорск | AK24: =CONCATENATE(YEAR(O24)," год") -> 2023 год | AL24: =CONCATENATE(YEAR(O24)," год") -> 2023 год | AM24: 1
A25: 18 | B25: МЖК Лесная поляна, 12 очередь, 48 Д | C25: 45188 | D25: Акмолинская область, г. Косшы | E25: ТОО "Марапат 2011" | F25: 111140016064 | G25: ТОО "LP City" | H25: 211040012059 | I25: 1635711572 | J25: 6384.3 | K25: 4479.5 | L25: 975.9 | M25: 256.208 | N25: 309.409 | O25: 45217 | P25: 110 | R25: 5 | S25: 45156 | T25: 45522 | U25: 45614 | X25: 20.09.2024 акт на регистрации | Y25: 9595485 | Z25: доп.согл. №2 к ДПГ-23-03-049/148 от 18.08.2023 | AB25: Кенесов М.Г. | AC25: Арыстанбекова А.И. | AD25: 81 | AE25: 1 | AF25: 1 | AG25: 422 | AI25: Акмолинская область | AJ25: Акмолинская область | AK25: =CONCATENATE(YEAR(O25)," год") -> 2023 год | AL25: =CONCATENATE(YEAR(O25)," год") -> 2023 год | AM25: 1
A26: 19 | B26: МЖК Салем | C26: 45188 | D26: Акмолинская область, г.Кокшетау | E26: ТОО "Биik Шаңырақ" | F26: 140740007872 | G26: ТОО "M-Group Asia" | H26: 220240012372 | I26: 1088278078 | J26: 5851.02 | K26: 3760.1 | M26: 289.428 | N26: 314.459 | O26: 45217 | P26: 119 | R26: 12 | S26: 45131 | T26: 45436 | U26: продлен по ЧС до 19.07.2024 | X26: 45492 | Y26: 9145815 | Z26: ДПГ-23-03-034/154 | AB26: Кенесов М.Г. | AC26: Арыстанбекова А.И. | AD26: 77 | AE26: 0 | AF26: 1 | AG26: 421 | AI26: Акмолинская область | AJ26: Акмолинская область | AK26: =CONCATENATE(YEAR(O26)," год") -> 2023 год | AL26: =CONCATENATE(YEAR(O26)," год") -> 2023 год | AM26: 1
A27: 20 | B27: МЖК Гранд Виктория 2 | C27: 45237 | D27: г. Астана | E27: ТОО "Бағыстан" | F27: 161140023096 | G27: ТОО "BUILDINGPLUS" | H27: 180840024962 | I27: 9176506252 | J27: 28301.1 | K27: 18053.2 | L27: 1895.59 | M27: 324.245 | N27: 460.00315 | O27: 45251 | P27: 264 | R27: 1, 9 | S27: 45191 | T27: 45465 | U27: 45557 | V27: 45648 | X27: 45648 | Y27: 77965812 | Z27: ДПГ-23-01-069/158 | AB27: Баркинхоев А.М. | AC27: Алимжанова Д.К. | AD27: 78 | AE27: 1 | AF27: 1 | AG27: 445 | AH27: да | AI27: г. Астана | AJ27: г. Астана | AK27: =CONCATENATE(YEAR(O27)," год") -> 2023 год | AL27: =CONCATENATE(YEAR(O27)," год") -> 2023 год | AM27: 1
A28: 21 | B28: МЖК Otbasy 1 очередь | C28: 45267 | D28: г. Шымкент | E28: ТОО "Kanfar Building" | F28: 060340004172 | G28: ТОО "Otbasy Satu" | H28: 230240002119 | I28: 6804685307 | J28: 17783.17 | K28: 10454 | L28: 1386.47 | M28: 382.647 | N28: 440 | O28: 45288 | P28: 192 | R28: 9 | S28: 45198 | T28: 45533 | X28: 28.08.2024 акт на регистрации | Y28: 61009602 | Z28: ДПГ-23-17-050/159 | AB28: Исмаков А.С. | AC28: Жакыпбеков А.Д. | AD28: 73 | AE28: 0 | AF28: 1 | AG28: 455 | AH28: да | AI28: г. Шымкент | AJ28: г. Шымкент | AK28: =CONCATENATE(YEAR(O28)," год") -> 2023 год | AL28: =CONCATENATE(YEAR(O28)," год") -> 2023 год | AM28: 1
A29: 22 | B29: МЖК Бағыстан 1, 5 оч.позиция 2,4 | C29: 45272 | D29: г. Астана | E29: ТОО "Бағыстан" | F29: 161140023096 | G29: ТОО "NEW LINE PROJECT" | H29: 180240031389 | I29: 1.5986085e+10 | J29: 110897.01 | K29: 48140.85 | L29: 2545.6 | M29: 144.153 | N29: 374.57 | O29: 45288 | P29: 793 | R29: 7,9,12,15,17 | S29: 45191 | T29: 45891 | X29: 45891 | Y29: 1.5578159e+08 | Z29: ДПГ-23-01-069/160 | AB29: Баркинхоев А.М. | AC29: Алимжанова Д.К. | AD29: 83 | AE29: 0 | AF29: 1 | AG29: 450 | AH29: да | AI29: г. Астана | AJ29: г. Астана | AK29: =CONCATENATE(YEAR(O29)," год") -> 2023 год | AL29: =CONCATENATE(YEAR(O29)," год") -> 2023 год | AM29: 1
A30: 23 | B30: МЖК NOHO | C30: 45281 | D30: г. Астана | E30: ТОО "BAZIS-A Corp." | F30: 960340000376 | G30: ТОО "SOVICO GROUP" | H30: 180240017561 | I30: 10030993319 | J30: 54345.6 | K30: 32867.74 | L30: 3319.17 | M30: 277.199 | N30: 350 | O30: 45308 | P30: 423 | R30: 9,12,14,16 | S30: 45127 | T30: 45858 | X30: 45858 | Y30: 99060352 | Z30: ДПГ-24-01-001/162 | AB30: Баркинхоев А.М. | AC30: Алимжанова Д.К. | AD30: 91 | AE30: 0 | AF30: 2 | AG30: 444 | AI30: г. Астана | AJ30: г. Астана | AK30: =CONCATENATE(YEAR(O30)," год") -> 2024 год | AL30: =CONCATENATE(YEAR(O30)," год") -> 2024 год | AM30: 1
A31: 24 | B31: МЖК Salzburg, блок 3 | C31: 45274 | D31: г. Астана | E31: ТОО "BAZIS-A Corp." | F31: 960340000376 | G31: ТОО "Euro City-2" | H31: 190440041424 | I31: 1544370732 | J31: 7198.2 | K31: 4879.2 | L31: 716.4 | M31: 214.55 | N31: 350 | O31: 45309 | P31: 54 | R31: 8 | S31: 45175 | T31: 45541 | U31: 45632 | X31: 45632 | Y31: 14909071 | Z31: ДПГ-23-01-001/161 | AB31: Баркинхоев А.М. | AC31: Алимжанова Д.К. | AD31: 91 | AE31: 0 | AF31: 2 | AG31: 442 | AI31: г. Астана | AJ31: г. Астана | AK31: =CONCATENATE(YEAR(O31)," год") -> 2024 год | AL31: =CONCATENATE(YEAR(O31)," год") -> 2024 год | AM31: 1
A32: 25 | B32: МЖК Salzburg, блок 4 | C32: 45274 | D32: г. Астана | E32: ТОО "BAZIS-A Corp." | F32: 960340000376 | G32: ТОО "Euro City-2" | H32: 190440041424 | I32: 1372954735 | J32: 6094.3 | K32: 4080.6 | L32: 381.6 | M32: 225.285 | N32: 360 | O32: 45309 | P32: 40 | R32: 8 | S32: 45175 | T32: 45541 | U32: 45632 | X32: 45632 | Y32: 13001244 | Z32: ДПГ-23-01-001/161 | AB32: Баркинхоев А.М. | AC32: Алимжанова Д.К. | AD32: 91 | AE32: 0 | AF32: 2 | AG32: 443 | AI32: г. Астана | AJ32: г. Астана | AK32: =CONCATENATE(YEAR(O32)," год") -> 2024 год | AL32: =CONCATENATE(YEAR(O32)," год") -> 2024 год | AM32: 1
A33: 26 | B33: МЖК Modern City 2 | C33: 45300 | D33: г. Шымкент | E33: ТОО "Оңтүстік құрылыс Сервис" | F33: 010340004024 | G33: ТОО "OKS-Shymcity" | H33: 201140025012 | I33: 8967320951 | J33: 23220.52 | K33: 18073.93 | L33: 917.85 | M33: 386.181 | N33: 450.9 | O33: 45324 | P33: 271 | R33: 9 | S33: 45219 | T33: 45646 | X33: 45646 | Y33: 71541895 | Z33: доп.согл. №4 к ДПГ-22-13-004/106 от 11.02.2022 | AB33: Исмаков А.С. | AC33: Жакыпбеков А.Д. | AD33: 71 | AE33: 0 | AF33: 1 | AG33: 459 | AI33: г. Шымкент | AJ33: г. Шымкент | AK33: =CONCATENATE(YEAR(O33)," год") -> 2024 год | AL33: =CONCATENATE(YEAR(O33)," год") -> 2024 год | AM33: 1
A34: 27 | B34: МЖК Байтерек | C34: 45317 | D34: г. Уральск | E34: ТОО "Караванный путь" | F34: 030840007596 | G34: ТОО "Уркер Строй" | H34: 220340033735 | I34: 1886723001 | J34: 10334 | K34: 7497 | M34: 182.574 | N34: 280 | O34: 45348 | P34: 150 | R34: 5 | S34: 45352 | T34: 45566 | X34: 45566 | Y34: 18867230 | Z34: ДПГ-24-07-006/163 | AB34: Аяпова Г.Н. | AC34: Жусанова Т.А. | AD34: 73 | AE34: 0 | AF34: 3 | AG34: 456 | AI34: г. Уральск | AJ34: г. Уральск | AK34: =CONCATENATE(YEAR(O34)," год") -> 2024 год | AL34: =CONCATENATE(YEAR(O34)," год") -> 2024 год | AM34: 1
A35: 28 | B35: МЖК Английский квартал, г.Атырау | C35: 45337 | D35: г. Атырау | E35: ТОО "I BIGMA KZ" | F35: 080240012629 | G35: ТОО "КАСПИЙ-ЭКСПО" | H35: 080840016029 | I35: 3595425509 | J35: 25056.9 | K35: 18161.2 | L35: 2335.2 | M35: 143 | N35: 312 | O35: 45365 | P35: 240 | R35: 9 | S35: 45243 | T35: 45670 | X35: 45670 | Y35: 32350689 | Z35: ДПГ-24-06-070/164 | AB35: Аяпова Г.Н. | AC35: Жусанова Т.А. | AD35: 68 | AE35: 0 | AF35: 1 | AG35: 469 | AI35: г. Атырау | AJ35: г. Атырау | AK35: =CONCATENATE(YEAR(O35)," год") -> 2024 год | AL35: =CONCATENATE(YEAR(O35)," год") -> 2024 год | AM35: 1
A36: 29 | B36: МЖК Атамура, 2 очередь | C36: 45337 | D36: г. Астана | E36: ТОО "Жетісу ЖҚ" | F36: 031240005283 | G36: ТОО "Горде" | H36: 120540000160 | I36: 7672975159 | J36: 19294.2 | K36: 13480 | L36: 1150.8 | M36: 397.682 | N36: 488.649 | O36: 45371 | P36: 296 | R36: 9, 17 | S36: 45327 | T36: 45677 | X36: 45677 | Y36: 64691452 | Z36: доп.согл. №4 от 20.03.24г к ДПГ-22-01-024/116 от 11.08.22г | AB36: Баркинхоев А.М. | AC36: Алимжанова Д.К. | AD36: 65 | AE36: 0 | AF36: 1 | AG36: 473 | AI36: г. Астана | AJ36: г. Астана | AK36: =CONCATENATE(YEAR(O36)," год") -> 2024 год | AL36: =CONCATENATE(YEAR(O36)," год") -> 2024 год | AM36: 1
A37: 30 | B37: МЖК Престиж 3 (дома 5, 6) | C37: 45357 | D37: г. Шымкент | E37: ТОО "Композит-7" | F37: 050640012251 | G37: ТОО "PRESTIGE INVEST" | H37: 220140016321 | I37: 1613184111 | J37: 5712 | K37: 4190.55 | M37: 282 | N37: 433.8 | O37: 45380 | P37: 45 | R37: 5 | S37: 45316 | T37: 45621 | X37: 45621 | Y37: 14439086 | Z37: ДПГ-24-17-046/165 | AB37: Исмаков А.С. | AC37: Жакыпбеков А.Д. | AD37: 82 | AE37: 0 | AF37: 1 | AG37: 478 | AI37: г. Шымкент | AJ37: г. Шымкент | AK37: =CONCATENATE(YEAR(O37)," год") -> 2024 год | AL37: =CONCATENATE(YEAR(O37)," год") -> 2024 год | AM37: 1
A38: 31 | B38: МЖК Landmark, 3 очередь, пятна 1,3 | C38: 45366 | D38: г. Астана | E38: ТОО "BAZIS-A Corp." | F38: 960340000376 | G38: ТОО "DOSTYK LAND" | H38: 190240034484 | I38: 2815219201 | J38: 13082.17 | K38: 7430.63 | L38: 446.34 | M38: 301 | N38: 440 | O38: 45393 | P38: 75 | R38: 16.1 | S38: 45174 | T38: 45693 | X38: 45693 | Y38: 23678424 | Z38: доп.согл. №9 от 11.04.2024г к ДПГ-20-01-001/037 от28.02.20г | AB38: Баркинхоев А.М. | AC38: Алимжанова Д.К. | AD38: 92 | AE38: 0 | AF38: 1 | AG38: 481 | AI38: г. Астана | AJ38: г. Астана | AK38: =CONCATENATE(YEAR(O38)," год") -> 2024 год | AL38: =CONCATENATE(YEAR(O38)," год") -> 2024 год | AM38: 1
A39: 32 | B39: МЖК Bilim | C39: 45370 | D39: г. Астана | E39: ТОО "STROY OPT" | F39: 131240018048 | G39: ТОО "DAULETTI QALASHYQ" | H39: 170940003812 | I39: 13763471058 | J39: 66064.54 | K39: 42367.37 | L39: 3742.01 | M39: 208.334 | N39: 359 | O39: 45379 | P39: 674 | R39: 9,12,14,18 | S39: 45351 | T39: 45716 | X39: 45716 | Y39: 117673184 | Z39: ДПГ-24-01-044/166 | AB39: Баркинхоев А.М. | AC39: Алимжанова Д.К. | AD39: 85 | AE39: 0 | AF39: 1 | AG39: 484 | AI39: г. Астана | AJ39: г. Астана | AK39: =CONCATENATE(YEAR(O39)," год") -> 2024 год | AL39: =CONCATENATE(YEAR(O39)," год") -> 2024 год | AM39: 1
A40: 33 | B40: МЖК RAAF | C40: 45384 | D40: г. Алматы | E40: ТОО "EXCLUSIVE KURMANGAZY" | F40: 170840003753 | G40: ТОО "Exclusive Star" | H40: 200440003119 | I40: 6933930768 | J40: 31440.78 | K40: 19913.75 | L40: 1970.11 | M40: 220.539 | N40: 674.786 | O40: 45394 | P40: 261 | R40: 8.9 | S40: 45273 | T40: 45974 | X40: 45974 | Y40: 69339308 | Z40: ДПГ-24-02-071/167 | AB40: Кожухова Д.Б. | AC40: Смайлова Д.Н. | AD40: 64 | AE40: 0 | AF40: 1 | AG40: 476 | AI40: г. Алматы | AJ40: г. Алматы | AK40: =CONCATENATE(YEAR(O40)," год") -> 2024 год | AL40: =CONCATENATE(YEAR(O40)," год") -> 2024 год | AM40: 1
A41: 34 | B41: МЖК в мкр.Береке №18 | C41: 45391 | D41: г. Костанай | E41: ТОО "БК-СТРОЙ" | F41: 031040001233 | G41: ТОО "БК-Береке 18" | H41: 240140030559 | I41: 2341382653 | J41: 10974.61 | K41: 6795.68 | M41: 213.345 | N41: 360 | O41: 45418 | P41: 120 | R41: 5 | S41: 45414 | T41: 45718 | X41: 45718 | Y41: 23413827 | Z41: ДПГ-24-10-048|170 | AB41: Кенесов М.Г. | AC41: Арыстанбекова А.И. | AD41: 96 | AE41: 0 | AF41: 1 | AG41: 485 | AI41: г. Костанай | AJ41: г. Костанай | AK41: =CONCATENATE(YEAR(O41)," год") -> 2024 год | AL41: =CONCATENATE(YEAR(O41)," год") -> 2024 год | AM41: 1
A42: 35 | B42: МЖК Мангилик парк | C42: 45398 | D42: г. Астана | E42: ТОО "ТҰРАН ҚҰРЫЛЫС НС" | F42: 050640009251 | G42: ТОО "EL INVEST" | H42: 181140022389 | I42: 7417681106 | J42: 21357.11 | K42: 15245.91 | L42: 360.35 | M42: 475.302 | N42: 538.985 | O42: 45440 | P42: 209 | R42: 12.13 | S42: 45342 | T42: 45828 | X42: 45828 | Y42: 44482873 | Z42: ДПГ-24-01-023/165 | AB42: Баркинхоев А.М. | AC42: Алимжанова Д.К. | AD42: 85 | AE42: 0 | AF42: 1 | AG42: 479 | AI42: г. Астана | AJ42: г. Астана | AK42: =CONCATENATE(YEAR(O42)," год") -> 2024 год | AL42: =CONCATENATE(YEAR(O42)," год") -> 2024 год | AM42: 1
A43: 36 | B43: МЖК Береке-2, дом 17 | C43: 45400 | D43: г. Костанай | E43: ТОО "БК-СТРОЙ" | F43: 031040001233 | G43: ТОО "БК-Береке 17" | H43: 240240014520 | I43: 2838193666 | J43: 13734.47 | K43: 8561.63 | M43: 206.647 | N43: 370 | O43: 45425 | P43: 155 | R43: 5 | S43: 45439 | T43: 45743 | X43: =T43 -> 45743 | Y43: 28381937 | Z43: ДПГ-24-10-048/171 | AB43: Кенесов М.Г. | AC43: Арыстанбекова А.И. | AD43: 96 | AE43: 0 | AF43: - | AG43: 486 | AI43: г. Костанай | AJ43: г. Костанай | AK43: =CONCATENATE(YEAR(O43)," год") -> 2024 год | AL43: =CONCATENATE(YEAR(O43)," год") -> 2024 год | AM43: 1
A44: 37 | B44: МЖК Мегаполис | C44: 45400 | D44: г. Астана | E44: ТОО "Марапат 2011" | F44: 111140016064 | G44: ТОО "УПРАВЛЯЮЩАЯ КОМПАНИЯ "RESMAN" | H44: 160140004651 | I44: 9904943139 | J44: 36505.1 | K44: 23133.01 | L44: 1924.31 | M44: 271.33 | N44: 433.773 | O44: 45441 | P44: 450 | R44: 9 | S44: 44971 | T44: 45549 | U44: 45640 | X44: 45640 | Y44: 55757073 | Z44: ДПГ-24-01-049/169 | AB44: Баркинхоев А.М. | AC44: Алимжанова Д.К. | AD44: 75 | AE44: 0 | AF44: 4 | AG44: 477 | AI44: г. Астана | AJ44: г. Астана | AK44: =CONCATENATE(YEAR(O44)," год") -> 2024 год | AL44: =CONCATENATE(YEAR(O44)," год") -> 2024 год | AM44: 1
A45: 38 | B45: МЖК Otbasy 2 очередь | C45: 45456 | D45: г. Шымкент | E45: ТОО "Kanfar Building" | F45: 060340004172 | G45: ТОО "Otbasy Satu" | H45: 230240002119 | I45: 11265640030 | J45: 33009.83 | K45: 20716.57 | L45: 1103.86 | M45: 341.281 | N45: 440 | O45: 45483 | P45: 348 | R45: 1, 9 | S45: 45411 | T45: 45990 | X45: 45990 | Y45: 101373086 | Z45: доп.согл. №2 к ДПГ-23-17-050-159 от 28.12.2023 | AB45: Исмаков А.С. | AC45: Жакыпбеков А.Д. | AD45: 83 | AE45: 0 | AF45: 1 | AG45: 488 | AI45: г. Шымкент | AJ45: г. Шымкент | AK45: =CONCATENATE(YEAR(O45)," год") -> 2024 год | AL45: =CONCATENATE(YEAR(O45)," год") -> 2024 год | AM45: 1
A46: 39 | B46: МЖК Жаным 2 пусковой комплекс, 2 очередь, блок Б | C46: 45491 | D46: г. Усть-Каменогорск | E46: ТОО "Biryuza Construction» | F46: 040440036894 | G46: ТОО "УК Шанырак Строй" | H46: 230340036850 | I46: 898033122 | J46: 3419.26 | K46: 2732.59 | M46: 328.638 | N46: 369.444 | O46: 45513 | P46: 36 | R46: 9 | S46: 45449 | T46: 45783 | X46: 45783 | Y46: 7521250 | Z46: доп.согл. №1 к ДПГ-23-16-068/155 от 11.10.2023г. | AB46: Баркинхоев А.М. | AC46: Алимжанова Д.К. | AD46: 72 | AE46: 0 | AF46: 0 | AG46: 490 | AI46: г. Усть-Каменогорск | AJ46: г. Усть-Каменогорск | AK46: =CONCATENATE(YEAR(O46)," год") -> 2024 год | AL46: =CONCATENATE(YEAR(O46)," год") -> 2024 год | AM46: 1
A47: 40 | B47: МЖК "PARASAT II", 2 очередь (п.10,11) | C47: 45484 | D47: г. Алматы | E47: ТОО "SHEBERGOOD" | F47: 070240017648 | G47: ТОО "PARASAT II" | H47: 210740017974 | I47: 3103406715 | J47: 8853.6 | K47: 7182.3 | M47: 350.525 | N47: 432.091 | O47: 45513 | P47: 142 | R47: 9.1 | S47: 45444 | T47: 45658 | X47: 45658 | Y47: 27444388 | Z47: доп.согл. №1 к ДПГ-23-02-064/147 от 20.07.2023г. | AB47: Кожухова Д.Б. | AC47: Смайлова Д.Н. | AD47: 80 | AE47: 0 | AF47: 1 | AG47: 489 | AI47: г. Алматы | AJ47: г. Алматы | AK47: =CONCATENATE(YEAR(O47)," год") -> 2024 год | AL47: =CONCATENATE(YEAR(O47)," год") -> 2024 год | AM47: 1
A48: 41 | B48: МЖК Жаным 2 пусковой комплекс, 2 очередь, блок А | C48: 45491 | D48: г. Усть-Каменогорск | E48: ТОО "Biryuza Construction» | F48: 040440036894 | G48: ТОО "УК Шанырак Строй" | H48: 230340036850 | I48: 680140869 | J48: 2726.43 | K48: 1784.9 | L48: 308.24 | M48: 324.938 | N48: 380 | O48: 45516 | P48: 24 | R48: 9 | S48: 45462 | T48: 45827 | X48: 45827 | Y48: 5473612 | Z48: доп.согл. №2 к ДПГ-23-16-068/155 от 11.10.2023г. | AB48: Баркинхоев А.М. | AC48: Алимжанова Д.К. | AD48: 72 | AE48: 0 | AF48: 0 | AG48: 495 | AI48: г. Усть-Каменогорск | AJ48: г. Усть-Каменогорск | AK48: =CONCATENATE(YEAR(O48)," год") -> 2024 год | AL48: =CONCATENATE(YEAR(O48)," год") -> 2024 год | AM48: 1
A49: 42 | B49: МЖК Даулетті қалашық, 2 очередь | C49: 45517 | D49: г. Астана | E49: ТОО "STROY OPT" | F49: 131240018048 | G49: ТОО "DAULETTI QALASHYQ" | H49: 170940003812 | I49: 5390249441 | J49: 29864.22 | K49: 19052.13 | L49: 16884.03 | M49: 180.492 | N49: 403.83 | O49: 45520 | P49: 329 | R49: 1, 9, 12 | S49: 45497 | T49: 45954 | X49: 45954 | Y49: 45450566 | Z49: доп.согл. №1 к ДПГ-24-01-044/166 от 28.03.2024г. | AB49: Баркинхоев А.М. | AC49: Алимжанова Д.К. | AD49: 85 | AF49: 0 | AG49: 493 | AI49: г. Астана | AJ49: г. Астана | AK49: =CONCATENATE(YEAR(O49)," год") -> 2024 год | AL49: =CONCATENATE(YEAR(O49)," год") -> 2024 год | AM49: 1
A50: 43 | B50: МЖК Qasiet | C50: 45498 | D50: г. Астана | E50: ТОО "SENSAТA CONSТRUCТION" | F50: 041040007551 | G50: ТОО "SENSAТA URBAN DEVELOPMENТ" | H50: 201240028378 | I50: 10243010511 | J50: 35314.24 | K50: 22802.18 | L50: 385.17 | M50: 290 | N50: 470 | O50: 45530 | P50: 377 | R50: 9, 12, 16 | S50: 45450 | T50: 45937 | X50: 45937 | Y50: 87753132 | Z50: ДПГ-24-01-036/172 | AB50: Баркинхоев А.М. | AC50: Алимжанова Д.К. | AD50: 82 | AE50: 0 | AF50: 0 | AG50: 494 | AI50: г. Астана | AJ50: г. Астана | AK50: =CONCATENATE(YEAR(O50)," год") -> 2024 год | AL50: =CONCATENATE(YEAR(O50)," год") -> 2024 год | AM50: 1
A51: 44 | B51: МЖК Asar house, 3 очередь | C51: 45513 | D51: г. Шымкент | E51: ТОО "КОМПОЗИТ-7" | F51: 050640012251 | G51: ТОО "Asar house" | H51: 210740014236 | I51: 2835753390 | J51: 9803.7 | K51: 6712.14 | M51: 289.253 | N51: 427 | O51: 45540 | P51: 130 | R51: 5 | S51: 45449 | T51: 45753 | X51: 45753 | Y51: 26255342 | Z51: ДПГ-24-14-046/173 | AB51: Исмаков А.С. | AC51: Жакыпбеков А.Д. | AD51: 89 | AF51: 1 | AG51: 497 | AI51: г. Шымкент | AJ51: г. Шымкент | AK51: =CONCATENATE(YEAR(O51)," год") -> 2024 год | AL51: =CONCATENATE(YEAR(O51)," год") -> 2024 год | AM51: 1
A52: 45 | B52: МЖК Salzburg, блок 1,2,5 | C52: 45520 | D52: г. Астана | E52: ТОО "BAZIS-A Corp." | F52: 960340000376 | G52: ТОО "Euro City-2" | H52: 190440041424 | I52: 6454916135 | J52: 17342.5 | K52: 7461 | L52: 1053.3 | M52: 372.202 | N52: 635.625 | O52: 45540 | P52: 80 | R52: 8 | S52: 45392 | T52: 46091 | X52: 46091 | Y52: 63686003 | Z52: доп.согл. №1 к ДПГ -21-01-001/161 от 18.01.2024г. | AB52: Баркинхоев А.М. | AC52: Алимжанова Д.К. | AD52: 95 | AF52: 0 | AG52: 499 | AI52: г. Астана | AJ52: г. Астана | AK52: =CONCATENATE(YEAR(O52)," год") -> 2024 год | AL52: =CONCATENATE(YEAR(O52)," год") -> 2024 год | AM52: 1
A53: 46 | B53: МЖК Центральный сквер, 4 очередь | C53: 45538 | D53: г. Астана | E53: ТОО "SENSAТA CONSТRUCТION" | F53: 041040007551 | G53: ТОО "Sensata Build" | H53: 201240024454 | I53: 5936601406 | J53: 17629.99 | K53: 11241.39 | L53: 1264 | M53: 336.733 | N53: 475.665 | O53: 45567 | P53: 188 | R53: 9, 12 | S53: 45474 | T53: 45809 | X53: 45809 | Y53: 44093533 | Z53: ДПГ-24-01-036/174 | AB53: Баркинхоев А.М. | AC53: Алимжанова Д.К. | AD53: 82 | AE53: 0 | AF53: 1 | AG53: 498 | AI53: г. Астана | AJ53: г. Астана | AK53: =CONCATENATE(YEAR(O53)," год") -> 2024 год | AL53: =CONCATENATE(YEAR(O53)," год") -> 2024 год | AM53: 1
A54: 47 | B54: МЖК Landmark, 3 очередь, пятно 2 | C54: 45538 | D54: г. Астана | E54: ТОО "BAZIS-A Corp." | F54: 960340000376 | G54: ТОО "Dostyk Land" | H54: 190240034484 | I54: 2589603399 | J54: 10791.17 | K54: 8276.55 | L54: 460.19 | M54: 239.974 | N54: 450 | O54: 45566 | P54: 102 | R54: 18 | S54: 45415 | T54: 45841 | X54: 45841 | Y54: 24739461 | Z54: доп.согл. №10 к ДПГ-20-01-001/037 от 28.02.2024г. | AB54: Баркинхоев А.М. | AC54: Алимжанова Д.К. | AD54: 95 | AE54: 0 | AF54: 2 | AG54: 491 | AI54: г. Астана | AJ54: г. Астана | AK54: =CONCATENATE(YEAR(O54)," год") -> 2024 год | AL54: =CONCATENATE(YEAR(O54)," год") -> 2024 год | AM54: 1
A55: 48 | B55: ЖК Maxima City | C55: 45575 | D55: г. Алматы | E55: ТОО "KazSMU" | F55: 970540007997 | G55: ТОО "Maxima City" | H55: 030940000344 | I55: 3249330210 | J55: 9118.5 | K55: 5713.11 | L55: 414.81 | M55: 569 | N55: 582 | O55: на подписании | P55: 120 | R55: 7.9 | S55: 45524 | T55: 45736 | X55: 45736 | Y55: 32493302 | AB55: Кожухова Д.Б. | AC55: Смайлова Д.Н. | AD55: 74 | AE55: 0 | AG55: 496 | AI55: г. Алматы | AJ55: г. Алматы | AK55: =CONCATENATE(YEAR(O55)," год") -> #VALUE! | AL55: =CONCATENATE(YEAR(O55)," год") -> #VALUE! | AM55: 0
A56: 49 | B56: МЖК Кеменгер | C56: 45594 | D56: г.Астана | E56: ТОО "Sensata constraction" | F56: 041040007551 | G56: ТОО "Tarih construction" | H56: 220340017367 | I56: 14447740388 | J56: 42569.13 | K56: 25310.32 | L56: 1267.97 | M56: 339 | N56: 512 | O56: на подписании | P56: 360 | R56: 9 | S56: 45496 | T56: 46104 | X56: 46104 | Y56: 120324403 | AB56: Баркинхоев А.М. | AC56: Арыстанбекова А. | AD56: 82 | AF56: 1 | AG56: 503 | AH56: да | AK56: =CONCATENATE(YEAR(O56)," год") -> #VALUE! | AL56: =CONCATENATE(YEAR(O56)," год") -> #VALUE! | AM56: 0
A57: 50 | B57: МЖК Прайм Парк 2-ой пусковой комплекс | C57: 45594 | D57: г.Шымкент | E57: ТОО "Standard construction-7" | F57: 190140038552 | G57: ТОО "Prime park" | H57: 200240004050 | I57: 5526119723 | J57: 13508.59 | K57: 10214.31 | L57: 1299 | M57: 409 | N57: 450 | O57: на подписании | P57: 176 | R57: 9 | S57: 45398 | T57: 45763 | X57: 45763 | Y57: 49541572 | AB57: Кенесов М.Г. | AC57: Арыстанбекова А.И. | AD57: 84 | AF57: 1 | AG57: 502 | AH57: да | AK57: =CONCATENATE(YEAR(O57)," год") -> #VALUE! | AL57: =CONCATENATE(YEAR(O57)," год") -> #VALUE! | AM57: 0
A58: =CONCATENATE("ВСЕГО ДЕЙСТВУЮЩИЕ ГАРАНТИЙ ПО ",D65," ПРОЕКТОВ") -> ВСЕГО ДЕЙСТВУЮЩИЕ ГАРАНТИЙ ПО 47 ПРОЕКТОВ | I58: =SUMIF(ТаблицаД[Дата заключения договора о предоставлении гарантии],"<>на подписании",ТаблицаД[Стоимость, тенге]) -> 2.5158717e+11 | J58: =SUMIF(ТаблицаД[Дата заключения договора о предоставлении гарантии],"<>на подписании",ТаблицаД[Площадь, кв.м по Проекту]) -> 1008141.5 | K58: =SUMIF(ТаблицаД[Дата заключения договора о предоставлении гарантии],"<>на подписании",ТаблицаД[Площадь квартир, кв.м по Проекту]) -> 645986.49 | L58: =SUMIF(ТаблицаД[Дата заключения договора о предоставлении гарантии],"<>на подписании",ТаблицаД[Площадь коммерческих помещений, кв.м.]) -> 63867.68 | P58: =SUMIF(ТаблицаД[Дата заключения договора о предоставлении гарантии],"<>на подписании",ТаблицаД[Количество квартир по Проекту]) -> 10261 | Y58: =SUMIF(ТаблицаД[Дата заключения договора о предоставлении гарантии],"<>на подписании",ТаблицаД[Гарантийный взнос, тенге]) -> 2.2246872e+09 | AM58: =SUBTOTAL(2,ТаблицаД[Статус]) -> 50
A59: =CONCATENATE("ИТОГО ГАРАНТИЙ ПО ",AM58," ПРОЕКТАМ") -> ИТОГО ГАРАНТИЙ ПО 50 ПРОЕКТАМ | I59: =SUM(I7:I57) -> 2.7481036e+11 | J59: =SUM(J7:J55) -> 1017260 | K59: =SUM(K7:K57) -> 687224.23 | L59: =SUM(L7:L57) -> 66849.46 | P59: =SUM(P7:P55) -> 10381 | Y59: =SUM(Y7:Y57) -> 2.4270465e+09
D62: количество проектов | E62: стоимость по Проектам | F62: площадь по Проектам | G62: кол-во квартир по Проектам
B63: ВСЕГО ПРОГАРАНТИРОВАНО | D63: =D64+D65+D67 -> 243 | E63: =E64+E65+E67 -> 1.1589287e+12 | F63: =F64+F65+F67 -> 5869925.7 | G63: =G64+G65+G67 -> 66580 | H63: ВСЕГО СУММА ГАРАНТИЙНОГО ВЗНОСА ПО ВЫДАННЫМ ГАРАНТИЯМ | J63: =J64+J65 -> 1.289331e+10
B64: ИЗ НИХ ВВЕДЕНЫ В ЭКСПЛУАТАЦИЮ | D64: =Завершенные!D223 -> 190 | E64: =Завершенные!F223 -> 891770127090 | F64: =Завершенные!E223 -> 4781059.7 | G64: =Завершенные!G223 -> 55361 | H64: ИЗ НИХ ПО ВВЕДЕННЫМ В ЭКСПЛУАТАЦИЮ | J64: =Завершенные!Y218 -> 1.0668622e+10
B65: ДЕЙСТВУЮТ ГАРАНТИИ | D65: =COUNTIF($AM$7:$AM$57,"1") -> 47 | E65: =I58 -> 2.5158717e+11 | F65: =J58 -> 1008141.5 | G65: =P58 -> 10261 | H65: ПО ДЕЙСТВУЮЩИМ ГАРАНТИЯМ | J65: =Y58 -> 2.2246872e+09
B66: ПРОЕКТЫ НА РАССМОТРЕНИИ | D66: ='На рассмотрении'!A4 -> 0 | E66: ='На рассмотрении'!I5 -> 0 | F66: ='На рассмотрении'!K5 -> 0 | G66: ='На рассмотрении'!J5 -> 0 | H66: ПО РАССМАТРИВАЕМЫМ ПРОЕКТАМ | J66: -
B67: РАСТОРГНУТЫЕ ДОГОВОРА (после подписания ДПГ) | D67: 6 | E67: ='Отказ и расторжение'!D71 -> 15571424908 | F67: ='Отказ и расторжение'!E71 -> 80724.46 | G67: ='Отказ и расторжение'!F71 -> 958 | H67: ПО РАСТОРГНУТЫМ ПРОЕКТАМ | J67: ='Отказ и расторжение'!N66 -> 1.2556212e+08
B69: В разрезе по годам по действующим проектам | C69: количество проектов | D69: стоимость по Проектам | E69: площадь по Проектам | F69: кол-во квартир по Проектам
B70: 2021 год | C70: =COUNTIF($AK$7:$AK$54,B70) -> 2 | D70: =SUMIF($AL$7:$AL$55,$B70,$I$7:$I$55) -> 22006871432 | E70: =SUMIF($AL$7:$AL$55,$B70,$J$7:$J$55) -> 100781.58 | F70: =SUMIF($AL$7:$AL$55,$B70,$P$7:$P$55) -> 950
B71: 2022 год | C71: =COUNTIF($AK$7:$AK$54,B71) -> 3 | D71: =SUMIF($AL$7:$AL$55,$B71,$I$7:$I$55) -> 9948161748 | E71: =SUMIF($AL$7:$AL$55,$B71,$J$7:$J$55) -> 51188.83 | F71: =SUMIF($AL$7:$AL$57,$B71,$P$7:$P$57) -> 455
B72: 2023 год | C72: =COUNTIF($AK$7:$AK$54,B72) -> 17 | D72: =SUMIF($AL$7:$AL$55,$B72,$I$7:$I$55) -> 8.7536011e+10 | E72: =SUMIF($AL$7:$AL$55,$B72,$J$7:$J$55) -> 343001.63 | F72: =SUMIF($AL$7:$AL$55,$B72,$P$7:$P$55) -> 3637
B73: 2024 год | C73: =COUNTIF($AK$7:$AK$54,B73) -> 25 | D73: =SUMIF($AL$7:$AL$55,$B73,$I$7:$I$55) -> 132096124126 | E73: =SUMIF($AL$7:$AL$55,$B73,$J$7:$J$55) -> 513169.44 | F73: =SUMIF($AL$7:$AL$55,$B73,$P$7:$P$55) -> 5219
B74: ВСЕГО | C74: =SUM(C70:C73) -> 47 | D74: =SUM(D70:D73) -> 2.5158717e+11 | E74: =SUM(E70:E73) -> 1008141.5 | F74: =SUM(F70:F73) -> 10261
B77: В разрезе регионов по действующим проектам | C77: количество проектов | D77: стоимость по Проектам | E77: площадь по Проектам | F77: кол-во квартир по Проектам
B78: г. Астана | C78: =SUMIFS(ТаблицаД[Статус],ТаблицаД[Регион Кол-во],$B78,ТаблицаД[Дата заключения договора о предоставлении гарантии],"<>на подписании") -> 22 | D78: =SUMIFS(ТаблицаД[Стоимость, тенге],ТаблицаД[Регион Ст-ть],$B78,ТаблицаД[Дата заключения договора о предоставлении гарантии],"<>на подписании") -> 1.5637619e+11 | E78: =SUMIFS(ТаблицаД[Площадь, кв.м по Проекту],ТаблицаД[Регион Ст-ть],$B78,ТаблицаД[Дата заключения договора о предоставлении гарантии],"<>на подписании") -> 648870.07 | F78: =SUMIFS(ТаблицаД[Количество квартир по Проекту],ТаблицаД[Регион Ст-ть],$B78,ТаблицаД[Дата заключения договора о предоставлении гарантии],"<>на подписании") -> 6024
B79: г. Алматы | C79: =SUMIFS(ТаблицаД[Статус],ТаблицаД[Регион Кол-во],$B79,ТаблицаД[Дата заключения договора о предоставлении гарантии],"<>на подписании") -> 3 | D79: =SUMIFS(ТаблицаД[Стоимость, тенге],ТаблицаД[Регион Ст-ть],$B79,ТаблицаД[Дата заключения договора о предоставлении гарантии],"<>на подписании") -> 21416231301 | E79: =SUMIFS(ТаблицаД[Площадь, кв.м по Проекту],ТаблицаД[Регион Ст-ть],$B79,ТаблицаД[Дата заключения договора о предоставлении гарантии],"<>на подписании") -> 66873.38 | F79: =SUMIFS(ТаблицаД[Количество квартир по Проекту],ТаблицаД[Регион Ст-ть],$B79,ТаблицаД[Дата заключения договора о предоставлении гарантии],"<>на подписании") -> 784
B80: Алматинская область | C80: =SUMIFS(ТаблицаД[Статус],ТаблицаД[Регион Кол-во],$B80,ТаблицаД[Дата заключения договора о предоставлении гарантии],"<>на подписании") -> 1 | D80: =SUMIFS(ТаблицаД[Стоимость, тенге],ТаблицаД[Регион Ст-ть],$B80,ТаблицаД[Дата заключения договора о предоставлении гарантии],"<>на подписании") -> 4916104675 | E80: =SUMIFS(ТаблицаД[Площадь, кв.м по Проекту],ТаблицаД[Регион Ст-ть],$B80,ТаблицаД[Дата заключения договора о предоставлении гарантии],"<>на подписании") -> 15148.34 | F80: =SUMIFS(ТаблицаД[Количество квартир по Проекту],ТаблицаД[Регион Ст-ть],$B80,ТаблицаД[Дата заключения договора о предоставлении гарантии],"<>на подписании") -> 216
B81: г. Шымкент | C81: =SUMIFS(ТаблицаД[Статус],ТаблицаД[Регион Кол-во],$B81,ТаблицаД[Дата заключения договора о предоставлении гарантии],"<>на подписании") -> 6 | D81: =SUMIFS(ТаблицаД[Стоимость, тенге],ТаблицаД[Регион Ст-ть],$B81,ТаблицаД[Дата заключения договора о предоставлении гарантии],"<>на подписании") -> 34243880085 | E81: =SUMIFS(ТаблицаД[Площадь, кв.м по Проекту],ТаблицаД[Регион Ст-ть],$B81,ТаблицаД[Дата заключения договора о предоставлении гарантии],"<>на подписании") -> 98975.48 | F81: =SUMIFS(ТаблицаД[Количество квартир по Проекту],ТаблицаД[Регион Ст-ть],$B81,ТаблицаД[Дата заключения договора о предоставлении гарантии],"<>на подписании") -> 1089
B82: г. Актау | C82: =SUMIFS(ТаблицаД[Статус],ТаблицаД[Регион Кол-во],$B82,ТаблицаД[Дата заключения договора о предоставлении гарантии],"<>на подписании") -> 0 | D82: =SUMIFS(ТаблицаД[Стоимость, тенге],ТаблицаД[Регион Ст-ть],$B82,ТаблицаД[Дата заключения договора о предоставлении гарантии],"<>на подписании") -> 0 | E82: =SUMIFS(ТаблицаД[Площадь, кв.м по Проекту],ТаблицаД[Регион Ст-ть],$B82,ТаблицаД[Дата заключения договора о предоставлении гарантии],"<>на подписании") -> 0 | F82: =SUMIFS(ТаблицаД[Количество квартир по Проекту],ТаблицаД[Регион Ст-ть],$B82,ТаблицаД[Дата заключения договора о предоставлении гарантии],"<>на подписании") -> 0
B83: г. Уральск | C83: =SUMIFS(ТаблицаД[Статус],ТаблицаД[Регион Кол-во],$B83,ТаблицаД[Дата заключения договора о предоставлении гарантии],"<>на подписании") -> 1 | D83: =SUMIFS(ТаблицаД[Стоимость, тенге],ТаблицаД[Регион Ст-ть],$B83,ТаблицаД[Дата заключения договора о предоставлении гарантии],"<>на подписании") -> 1886723001 | E83: =SUMIFS(ТаблицаД[Площадь, кв.м по Проекту],ТаблицаД[Регион Ст-ть],$B83,ТаблицаД[Дата заключения договора о предоставлении гарантии],"<>на подписании") -> 10334 | F83: =SUMIFS(ТаблицаД[Количество квартир по Проекту],ТаблицаД[Регион Ст-ть],$B83,ТаблицаД[Дата заключения договора о предоставлении гарантии],"<>на подписании") -> 150
B84: г. Усть-Каменогорск | C84: =SUMIFS(ТаблицаД[Статус],ТаблицаД[Регион Кол-во],$B84,ТаблицаД[Дата заключения договора о предоставлении гарантии],"<>на подписании") -> 4 | D84: =SUMIFS(ТаблицаД[Стоимость, тенге],ТаблицаД[Регион Ст-ть],$B84,ТаблицаД[Дата заключения договора о предоставлении гарантии],"<>на подписании") -> 7085271168 | E84: =SUMIFS(ТаблицаД[Площадь, кв.м по Проекту],ТаблицаД[Регион Ст-ть],$B84,ТаблицаД[Дата заключения договора о предоставлении гарантии],"<>на подписании") -> 23982.18 | F84: =SUMIFS(ТаблицаД[Количество квартир по Проекту],ТаблицаД[Регион Ст-ть],$B84,ТаблицаД[Дата заключения договора о предоставлении гарантии],"<>на подписании") -> 216
B85: г. Актобе | C85: =SUMIFS(ТаблицаД[Статус],ТаблицаД[Регион Кол-во],$B85,ТаблицаД[Дата заключения договора о предоставлении гарантии],"<>на подписании") -> 1 | D85: =SUMIFS(ТаблицаД[Стоимость, тенге],ТаблицаД[Регион Ст-ть],$B85,ТаблицаД[Дата заключения договора о предоставлении гарантии],"<>на подписании") -> 7324207552 | E85: =SUMIFS(ТаблицаД[Площадь, кв.м по Проекту],ТаблицаД[Регион Ст-ть],$B85,ТаблицаД[Дата заключения договора о предоставлении гарантии],"<>на подписании") -> 48244.78 | F85: =SUMIFS(ТаблицаД[Количество квартир по Проекту],ТаблицаД[Регион Ст-ть],$B85,ТаблицаД[Дата заключения договора о предоставлении гарантии],"<>на подписании") -> 560
B86: г. Атырау | C86: =SUMIFS(ТаблицаД[Статус],ТаблицаД[Регион Кол-во],$B86,ТаблицаД[Дата заключения договора о предоставлении гарантии],"<>на подписании") -> 1 | D86: =SUMIFS(ТаблицаД[Стоимость, тенге],ТаблицаД[Регион Ст-ть],$B86,ТаблицаД[Дата заключения договора о предоставлении гарантии],"<>на подписании") -> 3595425509 | E86: =SUMIFS(ТаблицаД[Площадь, кв.м по Проекту],ТаблицаД[Регион Ст-ть],$B86,ТаблицаД[Дата заключения договора о предоставлении гарантии],"<>на подписании") -> 25056.9 | F86: =SUMIFS(ТаблицаД[Количество квартир по Проекту],ТаблицаД[Регион Ст-ть],$B86,ТаблицаД[Дата заключения договора о предоставлении гарантии],"<>на подписании") -> 240
B87: г. Костанай | C87: =SUMIFS(ТаблицаД[Статус],ТаблицаД[Регион Кол-во],$B87,ТаблицаД[Дата заключения договора о предоставлении гарантии],"<>на подписании") -> 3 | D87: =SUMIFS(ТаблицаД[Стоимость, тенге],ТаблицаД[Регион Ст-ть],$B87,ТаблицаД[Дата заключения договора о предоставлении гарантии],"<>на подписании") -> 6061167137 | E87: =SUMIFS(ТаблицаД[Площадь, кв.м по Проекту],ТаблицаД[Регион Ст-ть],$B87,ТаблицаД[Дата заключения договора о предоставлении гарантии],"<>на подписании") -> 30854.28 | F87: =SUMIFS(ТаблицаД[Количество квартир по Проекту],ТаблицаД[Регион Ст-ть],$B87,ТаблицаД[Дата заключения договора о предоставлении гарантии],"<>на подписании") -> 343
B88: Акмолинская область | C88: =SUMIFS(ТаблицаД[Статус],ТаблицаД[Регион Кол-во],$B88,ТаблицаД[Дата заключения договора о предоставлении гарантии],"<>на подписании") -> 5 | D88: =SUMIFS(ТаблицаД[Стоимость, тенге],ТаблицаД[Регион Ст-ть],$B88,ТаблицаД[Дата заключения договора о предоставлении гарантии],"<>на подписании") -> 8681964586 | E88: =SUMIFS(ТаблицаД[Площадь, кв.м по Проекту],ТаблицаД[Регион Ст-ть],$B88,ТаблицаД[Дата заключения договора о предоставлении гарантии],"<>на подписании") -> 39802.07 | F88: =SUMIFS(ТаблицаД[Количество квартир по Проекту],ТаблицаД[Регион Ст-ть],$B88,ТаблицаД[Дата заключения договора о предоставлении гарантии],"<>на подписании") -> 639
B89: ВСЕГО | C89: =SUM(C78:C88) -> 47 | D89: =SUM(D78:D88) -> 2.5158717e+11 | E89: =SUM(E78:E88) -> 1008141.5 | F89: =SUM(F78:F88) -> 10261
C90: =C74=C89 -> TRUE | D90: =D74=D89 -> TRUE | E90: =E74=E89 -> TRUE | F90: =F74=F89 -> TRUE
B94: В разрезе регионам по действующим и завершенным проектам | C94: количество проектов | D94: из них завершенные | E94: из них действующие | F94: из них расторгнутые
B95: г. Астана | C95: =SUM(D95:F95) -> #REF! | D95: =Завершенные!C237 -> 104 | E95: =#REF! -> #REF! | F95: 1
B96: г. Алматы | C96: =SUM(D96:F96) -> #REF! | D96: =Завершенные!C238 -> 49 | E96: =#REF! -> #REF!
B97: Алматинская обл. | C97: =SUM(D97:F97) -> #REF! | D97: =Завершенные!C239 -> 9 | E97: =#REF! -> #REF! | F97: 2
B98: г. Шымкент | C98: =SUM(D98:F98) -> #REF! | D98: =Завершенные!C241 -> 16 | E98: =#REF! -> #REF! | F98: 1
B99: г. Уральск | C99: =SUM(D99:F99) -> #REF! | D99: =Завершенные!C240 -> 2 | E99: =#REF! -> #REF!
B100: г. Актау | C100: =SUM(D100:F100) -> #REF! | D100: =Завершенные!C242 -> 1 | E100: =#REF! -> #REF!
B101: г. Актобе | C101: =SUM(D101:F101) -> #REF! | D101: =Завершенные!C243 -> 1 | E101: =#REF! -> #REF! | F101: 1
B102: г. Атырау | C102: =SUM(D102:F102) -> #REF! | D102: =Завершенные!C244 -> 5 | E102: =#REF! -> #REF!
B103: г. Костанай | C103: =SUM(D103:F103) -> #REF! | D103: =Завершенные!C245 -> 2 | E103: =#REF! -> #REF!
B104: г.Караганда | F104: 0
B105: Акмолинская обл. | C105: =SUM(D105:F105) -> #REF! | D105: =Завершенные!C246 -> 1 | E105: =#REF! -> #REF!
B106: г. Усть-Каменогорск | C106: =SUM(D106:F106) -> #REF! | E106: =#REF! -> #REF! | F106: 1
B107: ВСЕГО | C107: =SUM(C95:C106) -> #REF! | D107: =SUM(D95:D106) -> 190 | E107: =SUM(E95:E106) -> #REF! | F107: =SUM(F95:F106) -> 6

Sheet Завершенные
B1: Завершенные проекты
A3: № | B3: Наименование Проекта | C3: Дата решение Правления/СД | D3: Регион | E3: Застройщик | F3: БИН Застройщика | G3: Уполномоченная компания | H3: БИН Уполномоченной компании | I3: Стоимость, тенге | J3: Площадь, кв.м по Проекту | K3: Площадь квартир, кв.м по Проекту | L3: Площадь коммерческих помещений, кв.м. | M3: Себестоимость тыс.тенге/1 м2 | N3: Цена реал. тыс.тенге/1 м2 | O3: Дата заключения договора о предоставлении гарантии | P3: Количество квартир по Проекту | Q3: Количество квартир по факту (после ввода)* | R3: Этажность | S3: Дата начала строительства | T3: Дата завершения | U3: Дата пролонгации 1 | V3: Дата пролонгации 2 | W3: Дата пролонгации 3 | X3: Дата завершения 2/Дата по АПОЭ | Y3: Гарантийный взнос, тенге | Z3: № ДПГ | AA3: Итоговая стоимость с учетом снижения обязательств | AB3: Исполнитель | AC3: Куратор | AD3: Балл Застройщика | AE3: Кол-во продлении | AF3: Кол-во модерации | AG3: Номер в SB | AH3: Наличие "Зеленого сертификатв" | AI3: Регион Кол-во | AJ3: Регион Ст-ть | AK3: Год Кол-во | AL3: Год Ст-ть | AM3: Статус
A4: 1 | B4: ЖК "Миллениум парк", пятно 2, 14 блок | C4: 42870 | D4: г. Астана | E4: ТОО "BAZIS-A Corp." | F4: 960340000376 | G4: ТОО "Аллея тысячелетия-2" | H4: 160340010693 | I4: 2516814000 | J4: 14000 | O4: 42873 | P4: 178 | Q4: 178 | R4: 24 | S4: 42513 | T4: 43519 | X4: 43154 | Y4: 50336280 | Z4: ДПГ-17-01-001-02/001 | AD4: 100 | AI4: г. Астана | AJ4: г. Астана | AK4: =CONCATENATE(YEAR(O4)," год") -> 2017 год | AL4: =CONCATENATE(YEAR(O4)," год") -> 2017 год | AM4: =1 -> 1
A5: 2 | B5: ЖК "Легенда", 1 очередь (пятна 1-6) | C5: 42968 | D5: г. Алматы | E5: ТОО "BAZIS-A Corp." | F5: 960340000376 | G5: ТОО "KAT-Construction" | H5: 160640015734 | I5: 6866978080 | J5: 35371.3 | O5: 43000 | P5: 400 | Q5: 396 | R5: 14-16 | S5: 42895 | T5: 43474 | X5: 43454 | Y5: 137339562 | Z5: ДПГ-17-02-001/002 | AD5: 100 | AI5: г. Алматы | AJ5: г. Алматы | AK5: =CONCATENATE(YEAR(O5)," год") -> 2017 год | AL5: =CONCATENATE(YEAR(O5)," год") -> 2017 год | AM5: =1 -> 1
A6: 3 | B6: ЖК Алтын Ұя | C6: 43090 | D6: г. Астана | E6: ТОО "Comfort Development KZ" | F6: 210940032945 | G6: ТОО "AKAN Engineering" | H6: 140540020406 | I6: 1576632159 | J6: 13084 | O6: 43122 | P6: 148 | Q6: 167 | R6: 10 | S6: 42765 | T6: 43339 | X6: 43339 | Y6: 18956603 | Z6: ДПГ-17-01-002/003 | AD6: 67 | AI6: г. Астана | AJ6: г. Астана | AK6: =CONCATENATE(YEAR(O6)," год") -> 2018 год | AL6: =CONCATENATE(YEAR(O6)," год") -> 2018 год | AM6: =1 -> 1
A7: 4 | B7: МЖК Легенда, 2 очередь, ПАРКИНГ | C7: 43132 | D7: г. Алматы | E7: ТОО "BAZIS-A Corp." | F7: 960340000376 | G7: ТОО "KAT-Construction" | H7: 160640015734 | I7: 1348115202 | J7: 8303.1 | O7: 43146 | P7: 233 | Q7: 233 | R7: 1 | S7: 43005 | T7: 43461 | X7: 43454 | Y7: 24756844 | Z7: доп.согл. №1 к ДПГ-17-02-001/002 | AD7: 100 | AI7: г. Алматы | AJ7: г. Алматы | AK7: =CONCATENATE(YEAR(O7)," год") -> 2018 год | AL7: =CONCATENATE(YEAR(O7)," год") -> 2018 год | AM7: =1 -> 1
A8: 5 | B8: МЖК Alma City, 1 очередь | C8: 43193 | D8: г. Алматы | E8: ТОО "Qazaq Stroy" | F8: 050540016141 | G8: ТОО "Елимай-Invest" | H8: 160640016168 | I8: 1543068030 | J8: 26577.5 | O8: 43214 | P8: 300 | Q8: 360 | R8: 5 | S8: 43161 | T8: 43526 | X8: 43482 | Y8: 28414166 | Z8: ДПГ-18-02-005/006 | AD8: 91 | AI8: г. Алматы | AJ8: г. Алматы | AK8: =CONCATENATE(YEAR(O8)," год") -> 2018 год | AL8: =CONCATENATE(YEAR(O8)," год") -> 2018 год | AM8: =1 -> 1
A9: 6 | B9: ЖК на Гагарина 1 | C9: 43206 | D9: г. Уральск | E9: ТОО "Караванный путь" | F9: 030840007596 | G9: ТОО "Stroy Baiterek" | H9: 170740034528 | I9: 1279348120 | J9: 7546.7 | O9: 43218 | P9: 126 | Q9: 126 | R9: 9 | S9: 42964 | T9: 43512 | X9: 43477 | Y9: 15796882 | Z9: ДПГ-18-07-006/007 | AD9: 64 | AI9: г. Уральск | AJ9: г. Уральск | AK9: =CONCATENATE(YEAR(O9)," год") -> 2018 год | AL9: =CONCATENATE(YEAR(O9)," год") -> 2018 год | AM9: =1 -> 1
A10: 7 | B10: МЖК Alma City, 2 очередь | C10: 43325 | D10: г. Алматы | E10: ТОО "Qazaq Stroy" | F10: 050540016141 | G10: ТОО "Елимай-Invest" | H10: 160640016168 | I10: 1543068032 | J10: 26577.5 | O10: 43326 | P10: 300 | Q10: 360 | R10: 5 | S10: 43161 | T10: 43526 | X10: 43482 | Y10: 30861361 | Z10: доп.согл. №1 к ДПГ-18-02-005/006 | AD10: 90 | AI10: г. Алматы | AJ10: г. Алматы | AK10: =CONCATENATE(YEAR(O10)," год") -> 2018 год | AL10: =CONCATENATE(YEAR(O10)," год") -> 2018 год | AM10: =1 -> 1
A11: 8 | B11: МЖК Легенда, 3 очередь, пятна 7, 8, | C11: 43159 | D11: г. Алматы | E11: ТОО "BAZIS-A Corp." | F11: 960340000376 | G11: ТОО "KAT-Construction" | H11: 160640015734 | I11: 2198326780 | J11: 12592.6 | O11: 43175 | P11: 134 | Q11: 134 | R11: 14-15 | S11: 43116 | T11: 43540 | U11: 43632 | X11: 43633 | Y11: 43145556 | Z11: доп.согл. №2 к ДПГ-17-02-001/002 | AD11: 100 | AI11: г. Алматы | AJ11: г. Алматы | AK11: =CONCATENATE(YEAR(O11)," год") -> 2018 год | AL11: =CONCATENATE(YEAR(O11)," год") -> 2018 год | AM11: =1 -> 1
A12: 9 | B12: ЖК SUNRISE | C12: 43325 | D12: г. Астана | E12: ТОО "Милан-Астана" | F12: 110540015593 | G12: ТОО "Тенгри Хаус Астана" | H12: 130340016121 | I12: 7519312044 | J12: 29141.3 | O12: 43341 | P12: 458 | Q12: 569 | R12: 8-9 | S12: 43230 | T12: 43718 | X12: 43703 | Y12: 141232414 | Z12: доп.согл. №1 к ДПГ-18-01-008/009 | AD12: 78 | AI12: г. Астана | AJ12: г. Астана | AK12: =CONCATENATE(YEAR(O12)," год") -> 2018 год | AL12: =CONCATENATE(YEAR(O12)," год") -> 2018 год | AM12: =1 -> 1
A13: 10 | B13: ЖК Nova City | C13: 43390 | D13: г. Астана | E13: ТОО "Милан-Астана" | F13: 110540015593 | G13: ТОО "Камал Центр Астана" | H13: 170540018975 | I13: 6690458969 | J13: 28555.6 | O13: 43398 | P13: 467 | Q13: 467 | R13: 9 | S13: 43296 | T13: 43799 | U13: 43799 | X13: 43784 | Y13: 127426511 | Z13: ДПГ-18-01-008/011 | AD13: 78 | AI13: г. Астана | AJ13: г. Астана | AK13: =CONCATENATE(YEAR(O13)," год") -> 2018 год | AL13: =CONCATENATE(YEAR(O13)," год") -> 2018 год | AM13: =1 -> 1
A14: 11 | B14: ЖК Alma City-2 | C14: 43454 | D14: г. Алматы | E14: ТОО "Qazaq Stroy" | F14: 050540016141 | G14: ТОО "Нұр City Investment" | H14: 181140015247 | I14: 7891739810 | J14: 66742.5 | O14: 43458 | P14: 984 | Q14: 1059 | R14: 9 | S14: 43431 | T14: 43795 | X14: 43788 | Y14: 141881753 | Z14: ДПГ-18-02-005/012 | AD14: 90 | AI14: г. Алматы | AJ14: г. Алматы | AK14: =CONCATENATE(YEAR(O14)," год") -> 2018 год | AL14: =CONCATENATE(YEAR(O14)," год") -> 2018 год | AM14: =1 -> 1
A15: 12 | B15: ЖК Биік Шаңырақ | C15: 43147 | D15: г. Астана | E15: ТОО "НАЕК" | F15: 940140001482 | G15: ТОО "Биік Шаңырақ" | H15: 140740007872 | I15: 2146903508 | J15: 17848.8 | O15: 43162 | P15: 260 | Q15: 276 | R15: 14 | S15: 43160 | T15: 29.02.2019 | U15: 43616 | V15: 43708 | W15: 43890 | X15: 43803 | Y15: 36796147 | Z15: ДПГ-18-01-003/004 | AA15: 1302438420 | AD15: 77 | AI15: г. Астана | AJ15: г. Астана | AK15: =CONCATENATE(YEAR(O15)," год") -> 2018 год | AL15: =CONCATENATE(YEAR(O15)," год") -> 2018 год | AM15: =1 -> 1
A16: 13 | B16: ЖК Бахыт, 1 очередь | C16: 43166 | D16: г. Шымкент | E16: ТОО "Оңтүстік құрылыс Сервис" | F16: 010340004024 | G16: ТОО "Композит-7" | H16: 050640012251 | I16: 2458898850 | J16: 16417.7 | O16: 43194 | P16: 104 | Q16: 104 | R16: 9 | S16: 43160 | T16: 30.04.2019 | U16: 43676 | V16: 43768 | W16: 43860 | X16: 43824 | Y16: 46976477 | Z16: ДПГ-18-13-004/005 | AA16: 2458898850 | AD16: 64 | AI16: г. Шымкент | AJ16: г. Шымкент | AK16: =CONCATENATE(YEAR(O16)," год") -> 2018 год | AL16: =CONCATENATE(YEAR(O16)," год") -> 2018 год | AM16: =1 -> 1
A17: 14 | B17: МЖК Легенда, 5 очередь, пятна 9, 10 | C17: 43313 | D17: г. Алматы | E17: ТОО "BAZIS-A Corp." | F17: 960340000376 | G17: ТОО "KAT-Construction" | H17: 160640015734 | I17: 2502632570 | J17: 12341.8 | O17: 43315 | P17: 94 | Q17: 94 | R17: 14-15 | S17: 43280 | T17: 43859 | X17: 43822 | Y17: 48468231 | Z17: доп.согл. №3 к ДПГ-17-02-001/002 | AD17: 83 | AI17: г. Алматы | AJ17: г. Алматы | AK17: =CONCATENATE(YEAR(O17)," год") -> 2018 год | AL17: =CONCATENATE(YEAR(O17)," год") -> 2018 год | AM17: =1 -> 1
A18: 15 | B18: ЖК Триумфальная арка-2 | C18: 43334 | D18: г. Астана | E18: ТОО "Ңұр Астана Құрылыс" | F18: 060140000846 | G18: ТОО "Мангилик Ел Курылыс" | H18: 170240033531 | I18: 5341879260 | J18: 23920.8 | O18: 43385 | P18: 142 | Q18: 136 | R18: 4,7,9 | S18: 43269 | T18: 44000 | X18: 43977 | Y18: 93091230 | Z18: ДПГ-18-01-009/010 | AD18: 67 | AI18: г. Астана | AJ18: г. Астана | AK18: =CONCATENATE(YEAR(O18)," год") -> 2018 год | AL18: =CONCATENATE(YEAR(O18)," год") -> 2018 год | AM18: =1 -> 1
A19: 16 | B19: МЖК Багыстан, 1-я очередь, 2-очередь, 1, 3 позиции | C19: 43210 | D19: г. Астана | E19: ТОО "Шар Курылыс" | F19: 980740001878 | G19: ТОО "Бағыстан" | H19: 161140023096 | I19: 6541727260 | J19: 41688.6 | O19: 43216 | P19: 324 | Q19: 324 | R19: 5,7,9 | S19: 42921 | T19: 1 позиция - 10.08.2021г.; 3 позиция - 20.10.2021г. | U19: 44134 | V19: 44226 | W19: 44316 | X19: 44489 | Y19: 110832077 | Z19: ДПГ-18-01-007/008 | AD19: 83 | AI19: г. Астана | AJ19: г. Астана | AK19: =CONCATENATE(YEAR(O19)," год") -> 2018 год | AL19: =CONCATENATE(YEAR(O19)," год") -> 2018 год | AM19: =1 -> 1
A20: 17 | B20: МЖК Багыстан, 3-я очередь, 7 позиция | C20: 43286 | D20: г. Астана | E20: ТОО "Шар Курылыс" | F20: 980740001878 | G20: ТОО "Бағыстан" | H20: 161140023096 | I20: 3024902930 | J20: 13362.1 | O20: 43291 | P20: 152 | Q20: 152 | R20: 5,7,9 | S20: 43040 | T20: 20.10.2021 | U20: 44134 | V20: 44226 | W20: 44316 | X20: 44489 | Y20: 56590879 | Z20: доп.согл. №1 к ДПГ-18-01-007/008 | AD20: 83 | AI20: г. Астана | AJ20: г. Астана | AK20: =CONCATENATE(YEAR(O20)," год") -> 2018 год | AL20: =CONCATENATE(YEAR(O20)," год") -> 2018 год | AM20: =1 -> 1
A21: 18 | B21: МЖК Багыстан, 4-я очередь, 11 позиция | C21: 43325 | D21: г. Астана | E21: ТОО "Шар Курылыс" | F21: 980740001878 | G21: ТОО "Бағыстан" | H21: 161140023096 | I21: 3014702450 | J21: 13367.2 | O21: 43336 | P21: 152 | Q21: 152 | R21: 5,7,9 | S21: 43266 | T21: 30.07.2020 | U21: 44134 | V21: 44226 | W21: 44316 | X21: 44489 | Y21: 59088033 | Z21: доп.согл. №3 к ДПГ-18-01-007/008 | AD21: 83 | AI21: г. Астана | AJ21: г. Астана | AK21: =CONCATENATE(YEAR(O21)," год") -> 2018 год | AL21: =CONCATENATE(YEAR(O21)," год") -> 2018 год | AM21: =1 -> 1
A22: 19 | B22: МЖК Sezim Qala, 1 очередь | C22: 43515 | D22: г. Астана | E22: ТОО "Милан-Астана" | F22: 110540015593 | G22: ТОО "Туран Сити" | H22: 170340033307 | I22: 4220953472 | J22: 21443 | O22: 43518 | P22: 277 | Q22: 266 | R22: 9.12 | S22: 43441 | T22: 44142 | X22: 43824 | Y22: 79630069 | Z22: доп.согл. №1 к ДПГ-19-01-008/015 | AD22: 78 | AI22: г. Астана | AJ22: г. Астана | AK22: =CONCATENATE(YEAR(O22)," год") -> 2019 год | AL22: =CONCATENATE(YEAR(O22)," год") -> 2019 год | AM22: =1 -> 1
A23: 20 | B23: ЖК Легенда, 4 очередь (пятна 11, 12) | C23: 43523 | D23: г. Алматы | E23: ТОО "BAZIS-A Corp." | F23: 960340000376 | G23: ТОО "KAT-Construction" | H23: 160640015734 | I23: 1957311630 | J23: 12418.3 | O23: 43543 | P23: 142 | Q23: 142 | R23: 14-15 | S23: 43481 | T23: 43815 | U23: 43906 | X23: 43866 | Y23: 37257013 | Z23: доп.согл. №7 к ДПГ-17-02-001/002 | AD23: 83 | AI23: г. Алматы | AJ23: г. Алматы | AK23: =CONCATENATE(YEAR(O23)," год") -> 2019 год | AL23: =CONCATENATE(YEAR(O23)," год") -> 2019 год | AM23: =1 -> 1
A24: 21 | B24: МЖК Nova City, 19 очередь | C24: 43501 | D24: г. Астана | E24: ТОО "Милан-Астана" | F24: 110540015593 | G24: ТОО "Esil Town" | H24: 181140019271 | I24: 2227028801 | J24: 8855.87 | O24: 43511 | P24: 150 | Q24: 150 | R24: 9 | S24: 43521 | T24: 43946 | X24: 43938 | Y24: 43834498 | Z24: ДПГ-19-01-001/014 | AD24: 78 | AI24: г. Астана | AJ24: г. Астана | AK24: =CONCATENATE(YEAR(O24)," год") -> 2019 год | AL24: =CONCATENATE(YEAR(O24)," год") -> 2019 год | AM24: =1 -> 1
A25: 22 | B25: МЖК Alma City, 3-оч. 1-й пуск.комплекс | C25: 43726 | D25: г. Алматы | E25: ТОО "Qazaq Stroy" | F25: 050540016141 | G25: ТОО "ЫРЫСТЫ 46/2" | H25: 190340022583 | I25: 6600809540 | J25: 64684.2 | O25: 43728 | P25: 1008 | Q25: 1118 | R25: 9 | S25: 43711 | T25: 44257 | X25: 43965 | Y25: 132016191 | Z25: ДПГ-19-02-005/024 | AD25: 81 | AI25: г. Алматы | AJ25: г. Алматы | AK25: =CONCATENATE(YEAR(O25)," год") -> 2019 год | AL25: =CONCATENATE(YEAR(O25)," год") -> 2019 год | AM25: =1 -> 1
A26: 23 | B26: МЖК Амстердам, пятна 4,5,6,7,15.1 | C26: 43482 | D26: г. Астана | E26: ТОО "BAZIS-A Corp." | F26: 960340000376 | G26: ТОО "Amsterdam City" | H26: 180640022394 | I26: 3484165830 | J26: 20748.3 | O26: 43518 | P26: 110 | Q26: 100 | R26: 9-10 | S26: 43357 | T26: 44042 | X26: 44039 | Y26: 68156153 | Z26: ДПГ-19-01-001/013 | AD26: 83 | AI26: г. Астана | AJ26: г. Астана | AK26: =CONCATENATE(YEAR(O26)," год") -> 2019 год | AL26: =CONCATENATE(YEAR(O26)," год") -> 2019 год | AM26: =1 -> 1
A27: 24 | B27: ЖК Nova City 16 очередь | C27: 43634 | D27: г. Астана | E27: ТОО "Милан-Астана" | F27: 110540015593 | G27: ТОО "NC16" | H27: 181240011486 | I27: 4429569296 | J27: 20614.56 | O27: 43647 | P27: 242 | Q27: 242 | R27: 9 | S27: 43588 | T27: 44107 | X27: 44049 | Y27: 86509774 | Z27: ДПГ-19-01-008/016 | AD27: 91 | AI27: г. Астана | AJ27: г. Астана | AK27: =CONCATENATE(YEAR(O27)," год") -> 2019 год | AL27: =CONCATENATE(YEAR(O27)," год") -> 2019 год | AM27: =1 -> 1
A28: 25 | B28: МЖК Парасат, пятно 1,2 | C28: 43783 | D28: г. Алматы | E28: ТОО "SHEBERBUILD" | F28: 070240017648 | G28: ТОО "SHEBERGOOD" | H28: 070240017648 | I28: 1733779999 | J28: 7731.36 | O28: 43796 | P28: 143 | Q28: 143 | R28: 9 | S28: 43760 | T28: 43973 | U28: 44065 | X28: 44064 | Y28: 30929009 | Z28: ДПГ-19-02-013/030 | AD28: 70 | AI28: г. Алматы | AJ28: г. Алматы | AK28: =CONCATENATE(YEAR(O28)," год") -> 2019 год | AL28: =CONCATENATE(YEAR(O28)," год") -> 2019 год | AM28: =1 -> 1
A29: 26 | B29: ЖК Премьера | C29: 43676 | D29: г. Шымкент | E29: ТОО "Оңтүстік құрылыс Сервис" | F29: 010340004024 | G29: ТОО "Dostyq Invest Group" | H29: 190140008530 | I29: 1355115090 | J29: 8903.44 | O29: 43697 | P29: 80 | Q29: 80 | R29: 5 | S29: 43635 | T29: 43970 | U29: 44062 | V29: 44123 | X29: 44068 | Y29: 24228296 | Z29: ДПГ-19-13-004/020 | AD29: 61 | AI29: г. Шымкент | AJ29: г. Шымкент | AK29: =CONCATENATE(YEAR(O29)," год") -> 2019 год | AL29: =CONCATENATE(YEAR(O29)," год") -> 2019 год | AM29: =1 -> 1
A30: 27 | B30: МЖК Nova City, 22 очередь | C30: 43676 | D30: г. Астана | E30: ТОО "Милан-Астана" | F30: 110540015593 | G30: ТОО "NC 22" | H30: 190340029392 | I30: 2453517883 | J30: 8855.87 | O30: 43689 | P30: 150 | Q30: 150 | R30: 9 | S30: 43626 | T30: 44114 | X30: 44112 | Y30: 48045915 | Z30: ДПГ-19-01-008/021 | AD30: 91 | AI30: г. Астана | AJ30: г. Астана | AK30: =CONCATENATE(YEAR(O30)," год") -> 2019 год | AL30: =CONCATENATE(YEAR(O30)," год") -> 2019 год | AM30: =1 -> 1
A31: 28 | B31: ЖК ASQAT | C31: 43665 | D31: г. Астана | E31: ТОО "АсТи-Строй" | F31: 030740000258 | G31: ТОО "ASTI GROUP" | H31: 071240012104 | I31: 3019265161 | J31: 15344.61 | O31: 43677 | P31: 108 | Q31: 108 | R31: 7 | S31: 43633 | T31: 44180 | X31: 44165 | Y31: 50272872 | Z31: ДПГ-19-01-010/018 | AD31: 91 | AI31: г. Астана | AJ31: г. Астана | AK31: =CONCATENATE(YEAR(O31)," год") -> 2019 год | AL31: =CONCATENATE(YEAR(O31)," год") -> 2019 год | AM31: =1 -> 1
A32: 29 | B32: МЖК Argento, пятно 3 | C32: 44081 | D32: г. Астана | E32: ТОО "BAZIS-A Corp." | F32: 960340000376 | G32: ТОО "Строй Билдинг Астана" | H32: 170840009898 | I32: 1136489476 | J32: 7918.13 | O32: 43670 | P32: 85 | Q32: 85 | R32: 18 | S32: 43956 | T32: 44413 | X32: 44398 | Y32: 19307570 | Z32: ДПГ-19-01-001/017 | AD32: 84 | AI32: г. Астана | AJ32: г. Астана | AK32: =CONCATENATE(YEAR(O32)," год") -> 2019 год | AL32: =CONCATENATE(YEAR(O32)," год") -> 2019 год | AM32: =1 -> 1
A33: 30 | B33: МЖК 12 месяцев (на Макатаева), 1-очередь | C33: 43726 | D33: г. Алматы | E33: ТОО "Qazaq Stroy" | F33: 050540016141 | G33: ТОО "Макатаева 127" | H33: 190340022513 | I33: 5130621336 | J33: 36276.5 | O33: 43728 | P33: 432 | Q33: 468 | R33: 12 | S33: 43712 | T33: 44188 | X33: 44188 | Y33: 102612427 | Z33: ДПГ-19-02-005/025 | AD33: 81 | AI33: г. Алматы | AJ33: г. Алматы | AK33: =CONCATENATE(YEAR(O33)," год") -> 2019 год | AL33: =CONCATENATE(YEAR(O33)," год") -> 2019 год | AM33: =1 -> 1
A34: 31 | B34: ЖК Argento пятно 4, Наружные сети | C34: 43643 | D34: г. Астана | E34: ТОО "BAZIS-A Corp." | F34: 960340000376 | G34: ТОО "Строй Билдинг Астана" | H34: 170840009898 | I34: 2161436079 | J34: 12298.3 | O34: 43670 | P34: 100 | Q34: 100 | R34: 21 | S34: 43614 | T34: 44103 | U34: 44194 | X34: 44193 | Y34: 41160642 | Z34: ДПГ-19-01-001/017 | AD34: 78 | AI34: г. Астана | AJ34: г. Астана | AK34: =CONCATENATE(YEAR(O34)," год") -> 2019 год | AL34: =CONCATENATE(YEAR(O34)," год") -> 2019 год | AM34: =1 -> 1
A35: 32 | B35: ЖК Амстердам, пятна 1,2,3 | C35: 43777 | D35: г. Астана | E35: ТОО "BAZIS-A Corp." | F35: 960340000376 | G35: ТОО "Amsterdam City" | H35: 180640022394 | I35: 2176943630 | J35: 11705.1 | O35: 43783 | P35: 82 | Q35: 82 | R35: 9.1 | S35: 43712 | T35: 44193 | X35: 44193 | Y35: 42801333 | Z35: доп.согл. №1 к ДПГ-19-01-001/013 | AD35: 84 | AI35: г. Астана | AJ35: г. Астана | AK35: =CONCATENATE(YEAR(O35)," год") -> 2019 год | AL35: =CONCATENATE(YEAR(O35)," год") -> 2019 год | AM35: =1 -> 1
A36: 33 | B36: ЖК Бахыт, 2 очередь | C36: 43628 | D36: г. Шымкент | E36: ТОО "Оңтүстік құрылыс Сервис" | F36: 010340004024 | G36: ТОО "Композит-7" | H36: 050640012251 | I36: 4853681279 | J36: 27937.7 | O36: 43629 | P36: 168 | Q36: 168 | R36: 9 | S36: 43588 | T36: 44258 | U36: 44350 | X36: 44247 | Y36: 77180276 | Z36: доп.согл. №3 к ДПГ-18-13-004/005 | AA36: 3859013800 | AD36: 61 | AI36: г. Шымкент | AJ36: г. Шымкент | AK36: =CONCATENATE(YEAR(O36)," год") -> 2019 год | AL36: =CONCATENATE(YEAR(O36)," год") -> 2019 год | AM36: =1 -> 1
A37: 34 | B37: ЖК Ак Дидар, пятна 9-13 | C37: 43692 | D37: г. Астана | E37: ТОО "BAZIS-A Corp." | F37: 960340000376 | G37: ТОО "Ак Дидар-2" | H37: 170840012253 | I37: 2415410355 | J37: 16376.6 | O37: 43711 | P37: 276 | Q37: 248 | R37: 9 | S37: 43613 | T37: 44255 | U37: 44344 | X37: 44284 | Y37: 48308207 | Z37: ДПГ-19-01-001/022 | AD37: 78 | AI37: г. Астана | AJ37: г. Астана | AK37: =CONCATENATE(YEAR(O37)," год") -> 2019 год | AL37: =CONCATENATE(YEAR(O37)," год") -> 2019 год | AM37: =1 -> 1
A38: - | B38: Увеличение стоимости ЖК "Ак Дидар", (пятна 9-13) | C38: 43875 | D38: г. Астана | E38: ТОО "BAZIS-A Corp." | F38: 960340000376 | G38: ТОО "Ак Дидар-2" | H38: 170840012253 | I38: 698876654 | J38: 4954 | O38: 43880 | P38: 0 | Q38: 0 | R38: - | S38: 43613 | T38: 44255 | U38: 44344 | X38: 44284 | Y38: 13977533 | Z38: доп.согл. №1 к ДПГ-19-01-001/022 | AD38: 78 | AJ38: г. Астана | AL38: =CONCATENATE(YEAR(O38)," год") -> 2020 год
A39: 35 | B39: ЖК Aspan City | C39: 43665 | D39: Алматинская обл. | E39: ТОО "Exclusive Construction (Эксклюзив Констракшн)" | F39: 051040013647 | G39: ТОО "Aspan City 2" | H39: 181040020140 | I39: 4672680111 | J39: 23277.66 | O39: 43679 | P39: 288 | Q39: 267 | R39: 12 | S39: 43651 | T39: 44058 | U39: 44150 | V39: 44242 | W39: 44331 | X39: 44321 | Y39: 93453602 | Z39: ДПГ-19-02-011/019 | AD39: 73 | AI39: Алматинская область | AJ39: Алматинская область | AK39: =CONCATENATE(YEAR(O39)," год") -> 2019 год | AL39: =CONCATENATE(YEAR(O39)," год") -> 2019 год | AM39: =1 -> 1
A40: 36 | B40: МЖК Бестерек, пятно 1 | C40: 43726 | D40: г. Астана | E40: ТОО "Милан-Астана" | F40: 110540015593 | G40: ТОО "BI-Village Deluxe" | H40: 070340010951 | I40: 6019547133 | J40: 26723.09 | O40: 43735 | P40: 307 | Q40: 307 | R40: 8 | S40: 43662 | T40: 44363 | X40: 44361 | Y40: 119220603 | Z40: ДПГ-19-01-008/023 | AD40: 91 | AI40: г. Астана | AJ40: г. Астана | AK40: =CONCATENATE(YEAR(O40)," год") -> 2019 год | AL40: =CONCATENATE(YEAR(O40)," год") -> 2019 год | AM40: =1 -> 1
A41: 37 | B41: МЖК Sezim Qala, 4 очередь | C41: 43791 | D41: г. Астана | E41: ТОО "Милан-Астана" | F41: 110540015593 | G41: ТОО "Туран Сити" | H41: 170340033307 | I41: 3663548205 | J41: 19815.5 | O41: 43791 | P41: 278 | Q41: 278 | R41: 2, 9, 12 | S41: 43759 | T41: 44393 | X41: 44363 | Y41: 72343291 | Z41: доп.согл. №3 к ДПГ-19-01-008/015 | AD41: 91 | AI41: г. Астана | AJ41: г. Астана | AK41: =CONCATENATE(YEAR(O41)," год") -> 2019 год | AL41: =CONCATENATE(YEAR(O41)," год") -> 2019 год | AM41: =1 -> 1
A42: 38 | B42: ЖК Sezim Qala, 7 очередь | C42: 43748 | D42: г. Астана | E42: ТОО "Милан-Астана" | F42: 110540015593 | G42: ТОО "Туран Сити" | H42: 170340033307 | I42: 5814608330 | J42: 32516 | O42: 43749 | P42: 408 | Q42: 408 | R42: 22 | S42: 43704 | T42: 44496 | X42: 44347 | Y42: 114777807 | Z42: доп.согл. №2 к ДПГ-19-01-008/015 | AD42: 91 | AI42: г. Астана | AJ42: г. Астана | AK42: =CONCATENATE(YEAR(O42)," год") -> 2019 год | AL42: =CONCATENATE(YEAR(O42)," год") -> 2019 год | AM42: =1 -> 1
A43: 39 | B43: ЖК Гулдер, 2-очередь, пятна 9,10,11,12,13,14 | C43: 43777 | D43: г. Алматы | E43: ТОО "Милан-Астана" | F43: 110540015593 | G43: ТОО "Сармат Групп-2" | H43: 190640001234 | I43: 6837749056 | J43: 32575.2 | O43: 43783 | P43: 431 | Q43: 431 | R43: 12.16 | S43: 43731 | T43: 18.05.2021 | U43: 44426 | X43: 44376 | Y43: 134440701 | Z43: ДПГ-19-01-008/028 | AD43: 91 | AI43: г. Алматы | AJ43: г. Алматы | AK43: =CONCATENATE(YEAR(O43)," год") -> 2019 год | AL43: =CONCATENATE(YEAR(O43)," год") -> 2019 год | AM43: =1 -> 1
A44: 40 | B44: ЖК Сердце Столицы, 1 очередь | C44: 43748 | D44: г. Астана | E44: ТОО "Милан-Астана" | F44: 110540015593 | G44: ТОО "Turan Towers" | H44: 161040020830 | I44: 6825821599 | J44: 34967.37 | O44: 43759 | P44: 291 | Q44: 291 | R44: 7,9,12,19 | S44: 43692 | T44: 03.08.2021 | U44: 44290 | V44: 44381 | W44: 44473 | X44: 44411 | Y44: 132982359 | Z44: ДПГ-19-01-008/027 | AD44: 91 | AI44: г. Астана | AJ44: г. Астана | AK44: =CONCATENATE(YEAR(O44)," год") -> 2019 год | AL44: =CONCATENATE(YEAR(O44)," год") -> 2019 год | AM44: =1 -> 1
A45: - | B45: Увеличение стоимости МЖК Сердце Столицы, 1 оч. Наружные инженерные сети | C45: 43936 | D45: г. Астана | E45: ТОО "Милан-Астана" | F45: 110540015593 | G45: ТОО "Turan Towers" | H45: 161040020830 | I45: 1323442100 | J45: 0 | O45: 43970 | P45: 0 | Q45: 0 | R45: 1, 7, 9, 12, 19 | S45: 43928 | T45: 44658 | X45: 44411 | Y45: 26468842 | Z45: доп.согл. №1 к ДПГ-19-01-008/027 | AD45: 91 | AJ45: г. Астана | AL45: =CONCATENATE(YEAR(O45)," год") -> 2020 год
A46: 41 | B46: ЖК Абылайхан-2, пятна 4, 5, 6, 7 | C46: 43748 | D46: г. Астана | E46: ТОО "Корпорация Астана-Стройинвест" | F46: 000740002447 | G46: ТОО "СУ АСИ" | I46: 5253239788 | J46: 38863.78 | O46: 43755 | P46: 346 | Q46: 348 | R46: 13 | S46: 43721 | T46: 44324 | U46: 44416 | V46: 44508 | X46: 44494 | Y46: 93660141 | Z46: ДПГ-19-01-012/026 | AD46: 75 | AI46: г. Астана | AJ46: г. Астана | AK46: =CONCATENATE(YEAR(O46)," год") -> 2019 год | AL46: =CONCATENATE(YEAR(O46)," год") -> 2019 год | AM46: =1 -> 1
A47: 42 | B47: ЖК Discovery, Пятно 3. Блоки 1, 2, 5 | C47: 43777 | D47: г. Астана | E47: ТОО "BAZIS-A Corp." | F47: 960340000376 | G47: ТОО "Astana Real Estate 2017" | H47: 170640002219 | I47: 2439912400 | J47: 19742.65 | O47: 43802 | P47: 165 | Q47: 165 | R47: 9 | S47: 43635 | T47: 44123 | U47: 44215 | V47: 44305 | X47: 44637 | Y47: 47152489 | Z47: ДПГ-19-01-001/029 | AA47: 820792616 | AB47: Нуржубалин Н. | AD47: 78 | AI47: г. Астана | AJ47: г. Астана | AK47: =CONCATENATE(YEAR(O47)," год") -> 2019 год | AL47: =CONCATENATE(YEAR(O47)," год") -> 2019 год | AM47: =1 -> 1
A48: 43 | B48: ЖК ASQAT, очередь 2 | C48: 43875 | D48: г. Астана | E48: ТОО "АсТи-Строй" | F48: 030740000258 | G48: ТОО "ASTI GROUP" | H48: 071240012104 | I48: 1604244431 | J48: 9352.08 | O48: 43878 | P48: 106 | Q48: 106 | R48: 7 | S48: 43851 | T48: 44161 | U48: 44165 | X48: 44165 | Y48: 44498721 | Z48: доп.согл. №1 к ДПГ-19-01-010/018 | AD48: 91 | AI48: г. Астана | AJ48: г. Астана | AK48: =CONCATENATE(YEAR(O48)," год") -> 2020 год | AL48: =CONCATENATE(YEAR(O48)," год") -> 2020 год | AM48: =1 -> 1
A49: 44 | B49: ЖК ASQAT, очередь 3 | C49: 43875 | D49: г. Астана | E49: ТОО "АсТи-Строй" | F49: 030740000258 | G49: ТОО "ASTI GROUP" | H49: 071240012104 | I49: 1643232216 | J49: 9309.83 | O49: 43878 | P49: 107 | Q49: 107 | R49: 7 | S49: 43852 | T49: 44161 | U49: 44165 | X49: 44165 | Z49: доп.согл. №1 к ДПГ-19-01-010/018 | AD49: 91 | AI49: г. Астана | AJ49: г. Астана | AK49: =CONCATENATE(YEAR(O49)," год") -> 2020 год | AL49: =CONCATENATE(YEAR(O49)," год") -> 2020 год | AM49: =1 -> 1
A50: 45 | B50: МЖК Alma City, 3-оч. 2-й пуск.комплекс | C50: 43860 | D50: г. Алматы | E50: ТОО "Qazaq Stroy" | F50: 050540016141 | G50: ТОО "ЫРЫСТЫ 46/2" | H50: 190340022583 | I50: 7211511710 | J50: 78453.75 | O50: 43862 | P50: 1122 | Q50: 1248 | R50: 9 | S50: 43711 | T50: 44187 | X50: 44187 | Y50: 129729726 | Z50: доп.согл. №3 от 14.12.2020г. к ДПГ-19-02-005/024 от 20.09.2019г. | AD50: 84 | AI50: г. Алматы | AJ50: г. Алматы | AK50: =CONCATENATE(YEAR(O50)," год") -> 2020 год | AL50: =CONCATENATE(YEAR(O50)," год") -> 2020 год | AM50: =1 -> 1
A51: 46 | B51: МЖК 12 месяцев (на Макатаева) | C51: 43860 | D51: г. Алматы | E51: ТОО "Qazaq Stroy" | F51: 050540016141 | G51: ТОО "Макатаева 127" | H51: 190340022513 | I51: 4696993688 | J51: 35931.5 | O51: 43862 | P51: 576 | Q51: 624 | R51: 12 | S51: 43843 | T51: 44188 | X51: 44188 | Y51: 93939874 | Z51: доп.согл. №2 к ДПГ-19-02-005/025 | AD51: 84 | AI51: г. Алматы | AJ51: г. Алматы | AK51: =CONCATENATE(YEAR(O51)," год") -> 2020 год | AL51: =CONCATENATE(YEAR(O51)," год") -> 2020 год | AM51: =1 -> 1
A52: 47 | B52: ЖК Нурсая | C52: 43970 | D52: г. Атырау | E52: ТОО "Direct Construction Service" | F52: 050440002386 | G52: ТОО "Yerkin Management Group" | H52: 170640031311 | I52: 405171695 | J52: 2903 | O52: 43992 | P52: 40 | Q52: 40 | R52: 4 | S52: 43903 | T52: 31.12.2020 | U52: 44222 | X52: 44196 | Y52: 6007292 | Z52: ДПГ-20-06-018/040 | AD52: 80 | AI52: г. Атырау | AJ52: г. Атырау | AK52: =CONCATENATE(YEAR(O52)," год") -> 2020 год | AL52: =CONCATENATE(YEAR(O52)," год") -> 2020 год | AM52: =1 -> 1
A53: 48 | B53: ЖК Стандарт | C53: 44070 | D53: г. Шымкент | E53: ТОО "Оңтүстік құрылыс Сервис" | F53: 010340004024 | G53: ТОО "ЖК Standard" | H53: 190140038552 | I53: 2099777543 | J53: 10658 | O53: 44088 | P53: 140 | Q53: 140 | R53: 5 | S53: 43999 | T53: 44244 | U53: 44303 | X53: 44301 | Y53: 39779893 | Z53: ДПГ-20-13-004/045 | AD53: 62 | AI53: г. Шымкент | AJ53: г. Шымкент | AK53: =CONCATENATE(YEAR(O53)," год") -> 2020 год | AL53: =CONCATENATE(YEAR(O53)," год") -> 2020 год | AM53: =1 -> 1
A54: 49 | B54: МЖК Land Mark | C54: 43875 | D54: г. Астана | E54: ТОО "BAZIS-A Corp." | F54: 960340000376 | G54: ТОО "Dostyk Land" | H54: 190240034484 | I54: 2565255008 | J54: 18164 | O54: 43889 | P54: 128 | Q54: 128 | R54: 9.12 | S54: 43803 | T54: 44160 | U54: 44252 | V54: 44341 | X54: 44301 | Y54: 41256420 | Z54: доп.согл. №1 к ДПГ-20-01-001/037 | AD54: 78 | AI54: г. Астана | AJ54: г. Астана | AK54: =CONCATENATE(YEAR(O54)," год") -> 2020 год | AL54: =CONCATENATE(YEAR(O54)," год") -> 2020 год | AM54: =1 -> 1
A55: 50 | B55: МЖК Парасат 2 очередь | C55: 43927 | D55: г. Алматы | E55: ТОО "SHEBERBUILD" | F55: 070240017648 | G55: ТОО "SHEBERGOOD" | H55: 070240017648 | I55: 3041291058 | J55: 15462.72 | O55: 43950 | P55: 288 | Q55: 283 | R55: 9 | S55: 43866 | T55: 44345 | U55: 44437 | X55: 44329 | Y55: 60823921 | Z55: доп.согл. №1 к ДПГ-19-02-013/030 | AD55: 70 | AI55: г. Алматы | AJ55: г. Алматы | AK55: =CONCATENATE(YEAR(O55)," год") -> 2020 год | AL55: =CONCATENATE(YEAR(O55)," год") -> 2020 год | AM55: =1 -> 1
A56: 51 | B56: МЖК SOHO | C56: 43481 | D56: г. Астана | E56: ТОО "BAZIS-A Corp." | F56: 960340000376 | G56: ТОО "Sovico group" | H56: 180240017561 | I56: 1991352860 | J56: 10697.91 | O56: 43867 | P56: 78 | Q56: 78 | R56: 7 | S56: 43783 | T56: 44227 | X56: 44214 | Y56: 38237857 | Z56: ДПГ-20-01-001/032 | AD56: 78 | AI56: г. Астана | AJ56: г. Астана | AK56: =CONCATENATE(YEAR(O56)," год") -> 2020 год | AL56: =CONCATENATE(YEAR(O56)," год") -> 2020 год | AM56: =1 -> 1
A57: 52 | B57: МЖК Nova City на Туране | C57: 43860 | D57: г. Астана | E57: ТОО "Милан-Астана" | F57: 110540015593 | G57: ТОО "СК БАЗАР" | H57: 190940030982 | I57: 5762175734 | J57: 27870 | O57: 43866 | P57: 348 | Q57: 348 | R57: 9 | S57: 43769 | T57: 44469 | X57: 44352 | Y57: 110205578 | Z57: ДПГ-20-01-008/034 | AD57: 91 | AI57: г. Астана | AJ57: г. Астана | AK57: =CONCATENATE(YEAR(O57)," год") -> 2020 год | AL57: =CONCATENATE(YEAR(O57)," год") -> 2020 год | AM57: =1 -> 1
A58: - | B58: Увеличение стоимости МЖК Nova City на Туране, 1 очередь. Наружные инженерные сети. | C58: 44007 | D58: г. Астана | E58: ТОО "Милан-Астана" | F58: 110540015593 | G58: ТОО "СК БАЗАР" | H58: 190940030982 | I58: 737891954 | J58: 0 | O58: 44025 | P58: 0 | Q58: 0 | R58: - | S58: 43983 | T58: 44469 | X58: 44352 | Y58: 14757839 | Z58: доп.согл. №1 к ДПГ-20-01-008/034 | AD58: 91 | AJ58: г. Астана | AL58: =CONCATENATE(YEAR(O58)," год") -> 2020 год
A59: 53 | B59: МЖК Теремки, Блоки 16-27 | C59: 43998 | D59: г. Алматы | E59: ТОО "Елимай-Invest" | F59: 160640016168 | G59: ТОО "ЖК "Теремки" | H59: 200540007036 | I59: 7001848587 | J59: 55789.44 | O59: 43999 | P59: 864 | Q59: 960 | R59: 9 | S59: 43977 | T59: 44357 | U59: 44460 | X59: 44449 | Y59: 140036972 | Z59: ДПГ-20-02-020/042 | AD59: 95 | AI59: г. Алматы | AJ59: г. Алматы | AK59: =CONCATENATE(YEAR(O59)," год") -> 2020 год | AL59: =CONCATENATE(YEAR(O59)," год") -> 2020 год | AM59: =1 -> 1
A60: 54 | B60: МЖК Nova City на Рыскулбекова | C60: 43860 | D60: г. Астана | E60: ТОО "Милан-Астана" | F60: 110540015593 | G60: ТОО "Salamat Stroy" | H60: 180440012489 | I60: 5840045029 | J60: 31002.69 | O60: 43866 | P60: 334 | Q60: 334 | R60: 1,9,12 | S60: 43839 | T60: 44570 | X60: 44421 | Y60: 115050538 | Z60: ДПГ-20-01-008/033 | AD60: 91 | AI60: г. Астана | AJ60: г. Астана | AK60: =CONCATENATE(YEAR(O60)," год") -> 2020 год | AL60: =CONCATENATE(YEAR(O60)," год") -> 2020 год | AM60: =1 -> 1
A61: 55 | B61: МЖК Амстердам, пятна 8-10 | C61: 44053 | D61: г. Астана | E61: ТОО "BAZIS-A Corp." | F61: 960340000376 | G61: ТОО "Amsterdam City" | H61: 180640022394 | I61: 2015148840 | J61: 12132.8 | O61: 44063 | P61: 88 | Q61: 88 | R61: 10 | S61: 43955 | T61: 44620 | X61: 44377 | Y61: 34813216 | Z61: доп.согл. №3 к ДПГ-19-01-001/013 | AD61: 84 | AI61: г. Астана | AJ61: г. Астана | AK61: =CONCATENATE(YEAR(O61)," год") -> 2020 год | AL61: =CONCATENATE(YEAR(O61)," год") -> 2020 год | AM61: =1 -> 1
A62: 56 | B62: МЖК SOHO. Блок-секции 4,5,6 | C62: 44111 | D62: г. Астана | E62: ТОО "BAZIS-A Corp." | F62: 960340000376 | G62: ТОО "Sovico group" | H62: 180240017561 | I62: 3066214650 | J62: 15109.69 | O62: 44154 | P62: 119 | Q62: 119 | R62: 9.12 | S62: 43998 | T62: 44592 | X62: 44452 | Y62: 52444166 | Z62: доп.согл. №1 к ДПГ-20-01-001/032 от 06.02.2020г. | AD62: 84 | AI62: г. Астана | AJ62: г. Астана | AK62: =CONCATENATE(YEAR(O62)," год") -> 2020 год | AL62: =CONCATENATE(YEAR(O62)," год") -> 2020 год | AM62: =1 -> 1
A63: 57 | B63: МЖК Alma City, 3-оч. 3-й пуск.комплекс | C63: 44175 | D63: г. Алматы | E63: ТОО "Qazaq Stroy" | F63: 050540016141 | G63: ТОО "ЫРЫСТЫ 46/2" | H63: 190340022583 | I63: 3080917422 | J63: 59963.8 | O63: 44179 | P63: 832 | Q63: 928 | R63: 9 | S63: 44118 | T63: 44452 | U63: 44543 | X63: 44441 | Y63: 30809174 | Z63: доп.согл. №3 к ДПГ-19-02-005/024 | AD63: 71 | AI63: г. Алматы | AJ63: г. Алматы | AK63: =CONCATENATE(YEAR(O63)," год") -> 2020 год | AL63: =CONCATENATE(YEAR(O63)," год") -> 2020 год | AM63: =1 -> 1
A64: 58 | B64: МЖК Nova City на Туране, 2 очередь | C64: 44060 | D64: г. Астана | E64: ТОО "Милан-Астана" | F64: 110540015593 | G64: ТОО "СК БАЗАР" | H64: 190940030982 | I64: 4767699843 | J64: 21896 | O64: 44062 | P64: 239 | Q64: 239 | R64: 9 | S64: 44001 | T64: 44530 | X64: 44477 | Y64: 93279152 | Z64: доп.согл. №2 к ДПГ-20-02-008/034 | AD64: 81 | AI64: г. Астана | AJ64: г. Астана | AK64: =CONCATENATE(YEAR(O64)," год") -> 2020 год | AL64: =CONCATENATE(YEAR(O64)," год") -> 2020 год | AM64: =1 -> 1
A65: 59 | B65: МЖК Асыл Мура, Блок А | C65: 43860 | D65: г. Астана | E65: ТОО "Милан-Астана" | F65: 110540015593 | G65: ТОО "Цесинстрой" | H65: 110340014607 | I65: 9154023704 | J65: 35661.7 | O65: 43866 | P65: 357 | Q65: 358 | R65: 16 | S65: 43843 | T65: 44477 | U65: 44569 | X65: 44553 | Y65: 180082849 | Z65: ДПГ-20-01-008/031 | AD65: 91 | AI65: г. Астана | AJ65: г. Астана | AK65: =CONCATENATE(YEAR(O65)," год") -> 2020 год | AL65: =CONCATENATE(YEAR(O65)," год") -> 2020 год | AM65: =1 -> 1
A66: - | B66: Увеличение стоимости МЖК Асыл Мура, блок А. Наружные инженерные сети | C66: 44334 | D66: г. Астана | E66: ТОО "Милан-Астана" | F66: 110540015593 | G66: ТОО "Цесинстрой" | H66: 110340014607 | I66: 505795088 | J66: 0 | O66: 44344 | P66: 0 | Q66: 0 | R66: 0 | S66: 44172 | T66: 44553 | X66: 44553 | Y66: 5057951 | AB66: Нуржубалин Н. | AD66: 91 | AJ66: г. Астана | AL66: =CONCATENATE(YEAR(O66)," год") -> 2021 год
A67: 60 | B67: МЖК Олимпийский, 1 очередь | C67: 43875 | D67: г. Астана | E67: ТОО "Орда строй групп" | F67: 060240014641 | G67: ТОО "Orda Invest Development" | H67: 190840001896 | I67: 5767382086 | J67: 27950.19 | O67: 43903 | P67: 173 | Q67: 172 | R67: 10.18 | S67: 43817 | T67: 44487 | U67: 44579 | X67: 44559 | Y67: 105944617 | Z67: ДПГ-20-01-015/036 | AD67: 70 | AI67: г. Астана | AJ67: г. Астана | AK67: =CONCATENATE(YEAR(O67)," год") -> 2020 год | AL67: =CONCATENATE(YEAR(O67)," год") -> 2020 год | AM67: =1 -> 1
A68: 61 | B68: МЖК Терракота, 1 этап, Блоки 2, 2/1, 5, 8 и 10 | C68: 44015 | D68: г. Алматы | E68: ТОО "Елимай-Invest" | F68: 160640016168 | G68: ТОО "TEES" | H68: 190340014136 | I68: 6057003488 | J68: 39655.8 | O68: 44016 | P68: 484 | Q68: 506 | R68: 1, 18, 20 | S68: 43998 | T68: 44500 | U68: 44592 | X68: 44558 | Y68: 121140070 | Z68: ДПГ-20-02-020/043 | AD68: 95 | AI68: г. Алматы | AJ68: г. Алматы | AK68: =CONCATENATE(YEAR(O68)," год") -> 2020 год | AL68: =CONCATENATE(YEAR(O68)," год") -> 2020 год | AM68: =1 -> 1
A69: 62 | B69: МЖК Терракота, 2 этап, Блоки 4 и 7 | C69: 44060 | D69: г. Алматы | E69: ТОО "Елимай-Invest" | F69: 160640016168 | G69: ТОО "TEES" | H69: 190340014136 | I69: 2350110287 | J69: 16432.3 | O69: 44060 | P69: 208 | Q69: 216 | R69: 18, 20 | S69: 43998 | T69: 44592 | X69: 44558 | Y69: 47002206 | Z69: доп.согл. №1 к ДПГ-20-02-020/043 | AD69: 95 | AI69: г. Алматы | AJ69: г. Алматы | AK69: =CONCATENATE(YEAR(O69)," год") -> 2020 год | AL69: =CONCATENATE(YEAR(O69)," год") -> 2020 год | AM69: =1 -> 1
A70: 63 | B70: МЖК Sezim Qala 6 оч." | C70: 43875 | D70: г. Астана | E70: ТОО "Милан-Астана" | F70: 110540015593 | G70: ТОО "Туран Сити" | H70: 170340033307 | I70: 4490419686 | J70: 19814.66 | O70: 43878 | P70: 278 | Q70: 278 | R70: 2,9,12 | S70: 43784 | T70: 44302 | U70: 44393 | V70: 44510 | W70: 44602 | X70: 44557 | Y70: 89098085 | Z70: доп.согл. №4 к ДПГ-19-01-008/015 | AD70: 91 | AI70: г. Астана | AJ70: г. Астана | AK70: =CONCATENATE(YEAR(O70)," год") -> 2020 год | AL70: =CONCATENATE(YEAR(O70)," год") -> 2020 год | AM70: =1 -> 1
A71: 64 | B71: МЖК Sezim Qala 8 очередь | C71: 43927 | D71: г. Астана | E71: ТОО "Милан-Астана" | F71: 110540015593 | G71: ТОО "Туран Сити" | H71: 170340033307 | I71: 5708411131 | J71: 31505.3 | O71: 44154 | P71: 416 | Q71: 416 | R71: 1,2,22 | S71: 43892 | T71: 44622 | X71: 44559 | Y71: 112958261 | AD71: 91 | AI71: г. Астана | AJ71: г. Астана | AK71: =CONCATENATE(YEAR(O71)," год") -> 2020 год | AL71: =CONCATENATE(YEAR(O71)," год") -> 2020 год | AM71: =1 -> 1
A72: 65 | B72: МЖК Амстердам, 2 очередь, пятна 11-14 | C72: 44187 | D72: г. Астана | E72: ТОО "BAZIS-A Corp." | F72: 960340000376 | G72: ТОО "Amsterdam city" | H72: 180640022394 | I72: 2608583568 | J72: 16101.6 | O72: 44193 | P72: 116 | Q72: 116 | R72: 10 | S72: 43986 | T72: 44712 | X72: 44482 | Y72: 24583147 | Z72: доп.согл. №4 к ДПГ-19-01-001/013 | AA72: 311733873 | AD72: 84 | AI72: г. Астана | AJ72: г. Астана | AK72: =CONCATENATE(YEAR(O72)," год") -> 2020 год | AL72: =CONCATENATE(YEAR(O72)," год") -> 2020 год | AM72: =1 -> 1
A73: 66 | B73: МЖК Ак Дидар, пятна 14, 15 | C73: 44187 | D73: г. Астана | E73: ТОО "BAZIS-A Corp." | F73: 960340000376 | G73: ТОО "Ак Дидар-2" | H73: 170840012253 | I73: 1657025210 | J73: 12551.1 | O73: 44195 | P73: 171 | Q73: 171 | R73: 9.12 | S73: 44090 | T73: 44865 | X73: 44501 | Y73: 15578040 | Z73: доп.согл. №3к ДПГ-19-01-001/022 | AA73: 211128707 | AD73: 84 | AI73: г. Астана | AJ73: г. Астана | AK73: =CONCATENATE(YEAR(O73)," год") -> 2020 год | AL73: =CONCATENATE(YEAR(O73)," год") -> 2020 год | AM73: =1 -> 1
A74: 67 | B74: МЖК Гулдер 3 очередь | C74: 44109 | D74: г. Алматы | E74: ТОО "Компания Индустрия Строительства" | F74: 110640013302 | G74: ТОО "Сармат Групп" | H74: 170840035976 | I74: 4323925897 | J74: 17609.2 | O74: 44165 | P74: 237 | Q74: 237 | R74: 16 | S74: 44090 | T74: 44729 | X74: 44722 | Y74: 85270009 | Z74: ДПГ-20-01-022/048 | AD74: 98 | AI74: г. Алматы | AJ74: г. Алматы | AK74: =CONCATENATE(YEAR(O74)," год") -> 2020 год | AL74: =CONCATENATE(YEAR(O74)," год") -> 2020 год | AM74: =1 -> 1
A75: 68 | B75: МЖК Athletic | C75: 44175 | D75: г. Астана | E75: ТОО "Comfort Development KZ" | F75: 210940032945 | G75: ТОО "Comfort Туран" | H75: 190940031752 | I75: 2855648417 | J75: 13898.8 | O75: 44209 | P75: 126 | Q75: 126 | R75: 12 | S75: 44096 | T75: 44642 | X75: 44376 | Y75: 16 330 080 | Z75: ДПГ-20-01-002/049 | AB75: Нурбаев Н. | AD75: 77 | AI75: г. Астана | AJ75: г. Астана | AK75: =CONCATENATE(YEAR(O75)," год") -> 2021 год | AL75: =CONCATENATE(YEAR(O75)," год") -> 2021 год | AM75: =1 -> 1
A76: 69 | B76: МЖК Аллея тысячелетия, блок 24 | C76: 44232 | D76: г. Астана | E76: ТОО "BAZIS-A Corp." | F76: 960340000376 | G76: ТОО "Аллея тысячелетия-4" | H76: 180540027976 | I76: 2435069335 | J76: 16551 | O76: 44256 | P76: 144 | Q76: 144 | R76: 7 | S76: 43964 | T76: 44574 | X76: 44491 | Y76: 21061933 | Z76: ДПГ-21-01-001/053 | AD76: 84 | AI76: г. Астана | AJ76: г. Астана | AK76: =CONCATENATE(YEAR(O76)," год") -> 2021 год | AL76: =CONCATENATE(YEAR(O76)," год") -> 2021 год | AM76: =1 -> 1
A77: 70 | B77: МЖК Сити Плюс, 1-й пусковой комплекс, блоки 1-11 | C77: 44391 | D77: г. Алматы | E77: ТОО "Елимай-Invest" | F77: 160640016168 | G77: ТОО "Commercial Estate Company" | H77: 200440009039 | I77: 4706806971 | J77: 55984.28 | O77: 44403 | P77: 756 | Q77: 844 | R77: 9 | S77: 44355 | T77: 44561 | X77: 44558 | Y77: 47068070 | Z77: ДПГ-21-02-020/075 | AB77: Сарсембаева Ж. | AD77: 68 | AI77: г. Алматы | AJ77: г. Алматы | AK77: =CONCATENATE(YEAR(O77)," год") -> 2021 год | AL77: =CONCATENATE(YEAR(O77)," год") -> 2021 год | AM77: =1 -> 1
A78: 71 | B78: МЖК Nova City на Рыскулбекова 2 очередь | C78: 44336 | D78: г. Астана | E78: ТОО "Милан-Астана" | F78: 110540015593 | G78: ТОО "Salamat stroy" | H78: 180440012489 | I78: 3935294461 | J78: 19799.46 | O78: 44344 | P78: 207 | Q78: 207 | R78: 9, 12 | S78: 44242 | T78: 44734 | X78: 44522 | Y78: 38776285 | AD78: 81 | AI78: г. Астана | AJ78: г. Астана | AK78: =CONCATENATE(YEAR(O78)," год") -> 2021 год | AL78: =CONCATENATE(YEAR(O78)," год") -> 2021 год | AM78: =1 -> 1
A79: 72 | B79: МЖК Сердце Столицы, 2 оч. | C79: 44287 | D79: г. Астана | E79: ТОО "Милан-Астана" | F79: 110540015593 | G79: ТОО "Turan Towers" | H79: 161040020830 | I79: 6857592308 | J79: 35711.7 | O79: 44309 | P79: 291 | Q79: 291 | R79: 1, 7, 9, 12, 19 | S79: 44293 | T79: 44658 | X79: 44553 | Y79: 67971878 | AD79: 81 | AI79: г. Астана | AJ79: г. Астана | AK79: =CONCATENATE(YEAR(O79)," год") -> 2021 год | AL79: =CONCATENATE(YEAR(O79)," год") -> 2021 год | AM79: =1 -> 1
A80: 73 | B80: МЖК SOHO, блок 3,4 | C80: 44232 | D80: г. Астана | E80: ТОО "BAZIS-A Corp." | F80: 960340000376 | G80: ТОО "Sovico group" | H80: 180240017561 | I80: 3481930375 | J80: 17098.46 | O80: 44256 | P80: 80 | Q80: 80 | R80: 7.9 | S80: 09.12.2020 г. – блок 3 (секции 7,8,9); 19.08.2020 г. – блок 4 (паркинг) | T80: 44592 | X80: 44506 | Y80: 30330124 | AD80: 84 | AI80: г. Астана | AJ80: г. Астана | AK80: =CONCATENATE(YEAR(O80)," год") -> 2021 год | AL80: =CONCATENATE(YEAR(O80)," год") -> 2021 год | AM80: =1 -> 1
A81: 74 | B81: МЖК Шахристан | C81: 44230 | D81: г. Астана | E81: ТОО "Жетісу ЖҚ" | F81: 031240005283 | G81: ТОО "УК Шахристан" | H81: 200140012157 | I81: 3336486162 | J81: 16227.57 | O81: 44251 | P81: 160 | Q81: 182 | R81: 7, 9 | S81: 44158 | T81: 44615 | X81: 44538 | Y81: 28025328 | AD81: 63 | AI81: г. Астана | AJ81: г. Астана | AK81: =CONCATENATE(YEAR(O81)," год") -> 2021 год | AL81: =CONCATENATE(YEAR(O81)," год") -> 2021 год | AM81: =1 -> 1
A82: 75 | B82: МЖК Argento п 1,2 | C82: 44378 | D82: г. Астана | E82: ТОО "BAZIS-A Corp." | F82: 960340000376 | G82: ТОО "Строй Билдинг Астана" | H82: 170840009898 | I82: 2206013208 | J82: 15957 | O82: 44404 | P82: 170 | Q82: 170 | R82: 18 | S82: 44246 | T82: 44611 | X82: 44532 | Y82: 19793732 | AD82: 74 | AI82: г. Астана | AJ82: г. Астана | AK82: =CONCATENATE(YEAR(O82)," год") -> 2021 год | AL82: =CONCATENATE(YEAR(O82)," год") -> 2021 год | AM82: =1 -> 1
A83: 76 | B83: МЖК в г. Атырау | C83: 44375 | D83: г. Атырау | E83: ТОО "Direct Construction Service" | F83: 050440002386 | G83: ТОО "Yerkin Management Group" | H83: 170640031311 | I83: 922782493 | J83: 6326.2 | O83: 44398 | P83: 72 | Q83: 72 | R83: 9 | S83: 44234 | T83: 44642 | X83: 44615 | Y83: 8506904 | Z83: ДПГ-21-06-018/072 | AD83: 80 | AI83: г. Атырау | AJ83: г. Атырау | AK83: =CONCATENATE(YEAR(O83)," год") -> 2021 год | AL83: =CONCATENATE(YEAR(O83)," год") -> 2021 год | AM83: =1 -> 1
A84: 77 | B84: МЖК Алма Тау, пятна 7,8 | C84: 44313 | D84: Алматинская обл. | E84: ТОО "Строительная Компания Элитстрой" | F84: 060740002715 | G84: ТОО "УК "Алма Тау 2021" | H84: 210240029444 | I84: 2271535493 | J84: 11439.2 | O84: 44356 | P84: 234 | Q84: 234 | R84: 9 | S84: 44260 | T84: 44686 | X84: 44510 | Y84: 18977698 | AD84: 73 | AI84: Алматинская область | AJ84: Алматинская область | AK84: =CONCATENATE(YEAR(O84)," год") -> 2021 год | AL84: =CONCATENATE(YEAR(O84)," год") -> 2021 год | AM84: =1 -> 1
A85: 78 | B85: МЖК Esil Tower, 1 оч. | C85: 44287 | D85: г. Астана | E85: ТОО "Ethna Group" | F85: 940940000027 | G85: ТОО "Riverside Tower" | H85: 201040021501 | I85: 2374319871 | J85: 15603.49 | O85: 44309 | P85: 131 | Q85: 159 | R85: 24 | S85: 44235 | T85: 44688 | X85: 44606 | Y85: 20073340 | AD85: 77 | AI85: г. Астана | AJ85: г. Астана | AK85: =CONCATENATE(YEAR(O85)," год") -> 2021 год | AL85: =CONCATENATE(YEAR(O85)," год") -> 2021 год | AM85: =1 -> 1
A86: 79 | B86: МЖК HEAVEN | C86: 44299 | D86: г. Алматы | E86: ТОО "Елимай-Invest" | F86: 160640016168 | G86: ТОО "КапСтрой Девелопмент" | H86: 190140012211 | I86: 1499679126 | J86: 19657.2 | O86: 44309 | P86: 303 | Q86: 322 | R86: 12, 13, 16 | S86: 44217 | T86: 44702 | X86: 44557 | Y86: 13332057 | Z86: ДПГ-21-02-020/060 | AB86: Сарсембаева Ж. | AD86: 95 | AI86: г. Алматы | AJ86: г. Алматы | AK86: =CONCATENATE(YEAR(O86)," год") -> 2021 год | AL86: =CONCATENATE(YEAR(O86)," год") -> 2021 год | AM86: =1 -> 1
A87: 80 | B87: МЖК Асыл Мура, блок F | C87: 44260 | D87: г. Астана | E87: ТОО "Garant stroy" | F87: 170140020417 | G87: ТОО "УКиСС" | H87: 060140001190 | I87: 5890831329 | J87: 29839.25 | O87: 44287 | P87: 256 | Q87: 256 | R87: 9 | S87: 44239 | T87: 44693 | X87: 44686 | Y87: 57798194 | AA87: 1401206941 | AD87: 92 | AI87: г. Астана | AJ87: г. Астана | AK87: =CONCATENATE(YEAR(O87)," год") -> 2021 год | AL87: =CONCATENATE(YEAR(O87)," год") -> 2021 год | AM87: =1 -> 1
A88: 81 | B88: МЖК Gul Ana | C88: 44362 | D88: г. Алматы | E88: ТОО "KazSMU" | F88: 970540007997 | G88: ТОО "Gul-Ana" | H88: 111240020442 | I88: 3185907288 | J88: 14982.7 | O88: 44390 | P88: 184 | Q88: 184 | R88: 12 | S88: 44286 | T88: 44742 | X88: 44672 | Y88: 26936820 | AD88: 68 | AI88: г. Алматы | AJ88: г. Алматы | AK88: =CONCATENATE(YEAR(O88)," год") -> 2021 год | AL88: =CONCATENATE(YEAR(O88)," год") -> 2021 год | AM88: =1 -> 1
A89: 82 | B89: МЖК Әулиет | C89: 44321 | D89: г. Астана | E89: ТОО "Ңұр Астана Құрылыс" | F89: 060140000846 | G89: ТОО "AULET CONSTRUCTION" | H89: 191040008123 | I89: 9247229121 | J89: 37650.2 | O89: 44355 | P89: 328 | Q89: 360 | R89: 9, 12 | S89: 44222 | T89: 44707 | X89: 44694 | Y89: 78601448 | AD89: 70 | AI89: г. Астана | AJ89: г. Астана | AK89: =CONCATENATE(YEAR(O89)," год") -> 2021 год | AL89: =CONCATENATE(YEAR(O89)," год") -> 2021 год | AM89: =1 -> 1
A90: 83 | B90: МЖК Landmark | C90: 44217 | D90: г. Астана | E90: ТОО "BAZIS-A Corp." | F90: 960340000376 | G90: ТОО "Dostyk Land" | H90: 190240034484 | I90: 2762404808 | J90: 17400.61 | O90: 44239 | P90: 136 | Q90: 136 | R90: 18 | S90: 44187 | T90: 44795 | X90: 44792 | Y90: 25201828 | AA90: 1080839705 | AD90: 84 | AI90: г. Астана | AJ90: г. Астана | AK90: =CONCATENATE(YEAR(O90)," год") -> 2021 год | AL90: =CONCATENATE(YEAR(O90)," год") -> 2021 год | AM90: =1 -> 1
A91: 84 | B91: МЖК АТМОСФЕРА | C91: 44462 | D91: г. Астана | E91: ТОО "Tau House Development" | F91: 110540008868 | G91: ТОО "BERKAT-BUILDING" | H91: 190440023486 | I91: 8276765515 | J91: 29337.95 | O91: 44474 | P91: 322 | Q91: 332 | R91: 9 | S91: 44302 | T91: 44758 | X91: 44719 | Y91: 72595753 | AD91: 72 | AI91: г. Астана | AJ91: г. Астана | AK91: =CONCATENATE(YEAR(O91)," год") -> 2021 год | AL91: =CONCATENATE(YEAR(O91)," год") -> 2021 год | AM91: =1 -> 1
A92: 85 | B92: МЖК Гулдер 3 очередь, 1 пусковой | C92: 44287 | D92: г. Алматы | E92: ТОО "Компания Индустрия Строительства" | F92: 110640013302 | G92: ТОО "Сармат Групп" | H92: 170840035976 | I92: 3001447327 | J92: 14814.8 | O92: 44342 | P92: 165 | Q92: 165 | R92: 12 | S92: 44187 | T92: 44734 | X92: 44722 | Y92: 29331899 | Z92: ДПГ-20-01-022/048 от 30.11.2020 доп.согл. №1 от 26.05.2021г. | AA92: 862013053 | AB92: Нуржубалин Н. | AD92: 98 | AI92: г. Алматы | AJ92: г. Алматы | AK92: =CONCATENATE(YEAR(O92)," год") -> 2021 год | AL92: =CONCATENATE(YEAR(O92)," год") -> 2021 год | AM92: =1 -> 1
A93: 86 | B93: МЖК Теремки, 1-й пусковой комплекс, блоки 2-15 | C93: 44375 | D93: г. Алматы | E93: ТОО "Елимай-Invest" | F93: 160640016168 | G93: ТОО "ЖК "Теремки" | H93: 200540007036 | I93: 7142974193 | J93: 73948.3 | O93: 44392 | P93: 882 | Q93: 1058 | R93: 9 | S93: 44347 | T93: 44742 | X93: 44719 | Y93: 71429472 | Z93: ДПГ-20-02-020\042 от 17.06.2020 доп.согл. №2 от 15.07.2021г. | AB93: Сарсембаева Ж. | AD93: 68 | AI93: г. Алматы | AJ93: г. Алматы | AK93: =CONCATENATE(YEAR(O93)," год") -> 2021 год | AL93: =CONCATENATE(YEAR(O93)," год") -> 2021 год | AM93: =1 -> 1
A94: 87 | B94: МЖК Alma City 4-1, 1 этап | C94: 44455 | D94: г. Алматы | E94: ТОО "Елимай-Invest" | F94: 160640016168 | G94: ТОО "Ңұр City Invest" | H94: 160940030233 | I94: 7304262241 | J94: 80501.6 | O94: 44469 | P94: 980 | Q94: 980 | R94: 5 | S94: 44410 | T94: 44744 | X94: 44741 | Y94: 73042624 | Z94: ДПГ-21-02-020/085 | AB94: Сарсембаева Ж. | AD94: 68 | AI94: г. Алматы | AJ94: г. Алматы | AK94: =CONCATENATE(YEAR(O94)," год") -> 2021 год | AL94: =CONCATENATE(YEAR(O94)," год") -> 2021 год | AM94: =1 -> 1
A95: 88 | B95: МЖК Alma City 4-1, 2 этап, Блоки 1-8, 36-39, 43-46 | C95: 44509 | D95: г. Алматы | E95: ТОО "Елимай-Invest" | F95: 160640016168 | G95: ТОО "Ңұр City Invest" | H95: 160940030233 | I95: 4899793782 | J95: 60494 | O95: 44525 | P95: 730 | Q95: 730 | R95: 5 | S95: 44410 | T95: 44744 | X95: 44741 | Y95: 48997938 | Z95: ДПГ-21-02-020/085 от 30.09.2021 доп.согл. №1 от 25.11.2021г. | AB95: Сарсембаева Ж. | AD95: 68 | AI95: г. Алматы | AJ95: г. Алматы | AK95: =CONCATENATE(YEAR(O95)," год") -> 2021 год | AL95: =CONCATENATE(YEAR(O95)," год") -> 2021 год | AM95: =1 -> 1
A96: 89 | B96: МЖК Стандарт, 2 очередь | C96: 44404 | D96: г. Шымкент | E96: ТОО "Оңтүстік құрылыс Сервис" | F96: 010340004024 | G96: ТОО "ЖК Standard" | H96: 190140038552 | I96: 6015465822 | J96: 24557.72 | O96: 44421 | P96: 288 | Q96: 288 | R96: 9 | S96: 44348 | T96: 44805 | X96: 44754 | Y96: 60154658 | Z96: ДПГ-21-13-004/078 | AB96: Нурбаев Н. | AD96: 88 | AI96: г. Шымкент | AJ96: г. Шымкент | AK96: =CONCATENATE(YEAR(O96)," год") -> 2021 год | AL96: =CONCATENATE(YEAR(O96)," год") -> 2021 год | AM96: =1 -> 1
A97: 90 | B97: МЖК Терракота, 3 этап, блоки 3, 6, 9, 11 и 12 | C97: 44238 | D97: г. Алматы | E97: ТОО "Елимай-Invest" | F97: 160640016168 | G97: ТОО "TEES" | H97: 190340014136 | I97: 4039352205 | J97: 47954.7 | O97: 44257 | P97: 353 | Q97: 374 | R97: 1, 18, 20 | S97: 44119 | T97: 44757 | X97: 44750 | Y97: 40393522 | Z97: ДПГ-20-02-020/043 доп.согл. №2 от 02.03.2021г. | AB97: Сарсембаева Ж. | AD97: 95 | AI97: г. Алматы | AJ97: г. Алматы | AK97: =CONCATENATE(YEAR(O97)," год") -> 2021 год | AL97: =CONCATENATE(YEAR(O97)," год") -> 2021 год | AM97: =1 -> 1
A98: 91 | B98: МЖК Ақан Сері | C98: 44306 | D98: г. Астана | E98: ТОО "MabexTrade Ltd" | F98: 040640007005 | G98: ТОО "MAB Qurylys KZ" | H98: 210140033558 | I98: 3601621272 | J98: 17438.6 | O98: 44330 | P98: 165 | Q98: 165 | R98: 7 | S98: 44246 | T98: 44792 | X98: 44706 | Y98: 35250302 | Z98: ДПГ-21-01-027/061 | AB98: Далматова Д. | AD98: 80 | AI98: г. Астана | AJ98: г. Астана | AK98: =CONCATENATE(YEAR(O98)," год") -> 2021 год | AL98: =CONCATENATE(YEAR(O98)," год") -> 2021 год | AM98: =1 -> 1
A99: 92 | B99: МЖК Millenium Park, пятно 3, блок 23 | C99: 44341 | D99: г. Астана | E99: ТОО "BAZIS-A Corp." | F99: 960340000376 | G99: ТОО "Аллея Тысячелетия-4" | H99: 180540027976 | I99: 2037222803 | J99: 16601 | O99: 44358 | P99: 114 | Q99: 114 | R99: 7 | S99: 44271 | T99: 44880 | X99: 44725 | AD99: 84 | AI99: г. Астана | AJ99: г. Астана | AK99: =CONCATENATE(YEAR(O99)," год") -> 2021 год | AL99: =CONCATENATE(YEAR(O99)," год") -> 2021 год | AM99: =1 -> 1
A100: 93 | B100: МЖК Балауса | C100: 44434 | D100: г. Астана | E100: ТОО "Sensata Construction" | F100: 041040007551 | G100: ТОО "Sigma Byild" | H100: 191040024998 | I100: 7302547392 | J100: 26569.7 | O100: 44454 | P100: 285 | Q100: 285 | R100: 9 | S100: 44334 | T100: 44793 | X100: 44726 | Y100: 46197444 | Z100: ДПГ-21-01-036/082 | AB100: Сарсембаева Ж. | AD100: 93 | AI100: г. Астана | AJ100: г. Астана | AK100: =CONCATENATE(YEAR(O100)," год") -> 2021 год | AL100: =CONCATENATE(YEAR(O100)," год") -> 2021 год | AM100: =1 -> 1
A101: 94 | B101: МЖК NEXPO CITY | C101: 44270 | D101: г. Астана | E101: ТОО "Garant stroy" | F101: 170140020417 | G101: ТОО "NEXPO City" | H101: 210140037639 | I101: 9031081158 | J101: 51904.6 | O101: 44287 | P101: 400 | Q101: 447 | R101: 9,10,15 | S101: 44240 | T101: 45029 | X101: 44736 | Y101: 87400172 | Z101: ДПГ-21-01-025/056 | AA101: 3732693043 | AB101: Сарсембаева Ж. | AD101: 92 | AI101: г. Астана | AJ101: г. Астана | AK101: =CONCATENATE(YEAR(O101)," год") -> 2021 год | AL101: =CONCATENATE(YEAR(O101)," год") -> 2021 год | AM101: =1 -> 1
...

Sheet Лист2
B1: ДЕЙСТВУЮЩИЕ | E1: ЗАВЕРШЕННЫЕ
A2: 1 | B2: № | D2: =B2=E2 -> TRUE | E2: № | F2: =B2=G2 -> TRUE | G2: №
A3: 2 | B3: Наименование Проекта | D3: =B3=E3 -> TRUE | E3: Наименование Проекта | F3: =B3=G3 -> TRUE | G3: Наименование Проекта
A4: 3 | B4: Дата решение Правления/СД | D4: =B4=E4 -> TRUE | E4: Дата решение Правления/СД | F4: =B4=G4 -> TRUE | G4: Дата решение Правления/СД
A5: 4 | B5: Регион | D5: =B5=E5 -> TRUE | E5: Регион | F5: =B5=G5 -> TRUE | G5: Регион
A6: 5 | B6: Застройщик | D6: =B6=E6 -> TRUE | E6: Застройщик | F6: =B6=G6 -> TRUE | G6: Застройщик
A7: 6 | B7: БИН Застройщика | D7: =B7=E7 -> TRUE | E7: БИН Застройщика | F7: =B7=G7 -> TRUE | G7: БИН Застройщика
A8: 7 | B8: Уполномоченная компания | D8: =B8=E8 -> TRUE | E8: Уполномоченная компания | F8: =B8=G8 -> TRUE | G8: Уполномоченная компания
A9: 8 | B9: БИН Уполномоченной компании | D9: =B9=E9 -> TRUE | E9: БИН Уполномоченной компании | F9: =B9=G9 -> TRUE | G9: БИН Уполномоченной компании
A10: 9 | B10: Стоимость, тенге | D10: =B10=E10 -> TRUE | E10: Стоимость, тенге | F10: =B10=G10 -> TRUE | G10: Стоимость, тенге
A11: 10 | B11: Площадь, кв.м по Проекту | D11: =B11=E11 -> TRUE | E11: Площадь, кв.м по Проекту | F11: =B11=G11 -> TRUE | G11: Площадь, кв.м по Проекту
A12: 11 | B12: Площадь квартир, кв.м по Проекту | D12: =B12=E12 -> TRUE | E12: Площадь квартир, кв.м по Проекту | F12: =B12=G12 -> TRUE | G12: Площадь квартир, кв.м по Проекту
A13: 12 | B13: Площадь коммерческих помещений, кв.м. | D13: =B13=E13 -> TRUE | E13: Площадь коммерческих помещений, кв.м. | F13: =B13=G13 -> TRUE | G13: Площадь коммерческих помещений, кв.м.
... A40: 39 | B40: Статус | D40: =B40=E40 -> TRUE | E40: Статус | F40: =B40=G40 -> TRUE | G40: Статус
B48: Регион
B49: г. Астана
B50: г. Алматы
B51: г. Уральск
B52: г. Шымкент
B53: Алматинская обл.
B54: г. Атырау
B55: Акмолинская область, г. Косшы
B56: г. Актау
B57: г. Костанай
B58: г. Актобе
B59: Алматинская область г.Конаев
B60: Алматинская обл. c.Бесагаш

Sheet На рассмотрении
B1: Проекты на рассмотрении | O1: 4 р.д. | T1: 4 р.д. | U1: 5 р.д. | W1: 3 р.д. | AC1: планируем
A2: № | B2: Номер в SB | C2: Наименование Проекта | D2: Область | E2: Застройщик | F2: БИН Застройщика | G2: Уполномоченная компания | H2: БИН УК | I2: Стоимость, тенге | J2: Количество квартир по Проекту | K2: Площадь | L2: Дата регистрации заявки | M2: Время регистрации заявки | N2: Исполнитель от фронт-офиса | O2: ДРЮЛ | P2: ДПО | Q2: АПП | R2: ДОЗ | S2: ДТЭМ | T2: ДРМ | U2: ДОРАБОТКА Дата исходящего/Дата входящего | W2: ДРЮЛ | X2: ДПО | Y2: АПП | Z2: ДОЗ | AA2: ДТЭМ | AB2: ДРМ | AC2: ПРАВЛЕНИЕ | AD2: Текущий статус | AE2: в SB дата завершения | AF2: по расчету | AG2: 1 этап | AH2: 2 этап | AI2: выходные | AK2: ЖилПортал
A5: ВСЕГО | I5: =SUM(I3:I4) -> 0 | J5: =SUM(J3:J4) -> 0 | K5: =SUM(K3:K4) -> 0

Sheet На модерации
B1: Проекты на модерации | O1: 5 р.д. | Q1: 5 р.д. | S1: 5 р.д.
A2: № | B2: Номер в SB | C2: Наименование Проекта | D2: Область | E2: Застройщик | F2: БИН Застройщика | G2: Уполномоченная компания | H2: БИН УК | I2: Стоимость, тенге | J2: Количество квартир по Проекту | K2: Дата регистрации заявки | L2: Исполнитель от фронт-офиса | M2: Время регистрации заявки | N2: Направление замечаний/на регистрацию | O2: Регистрация после доработки | P2: Направление замечаний/на регистрацию | Q2: Регистрация после доработки | R2: Направление замечаний/на регистрацию | S2: Текущий статус
A3: 1 | B3: 339 | C3: МЖК Комфортный дом Новом городе 3 | D3: Карагандинская область | E3: ТОО "COMFORT SOLUTIONS" | F3: 201140026308 | G3: ТОО "Eurasia Building1" | H3: 110440011339 | I3: 5609699023 | J3: 197 | K3: 44970 | L3: Жакыпбеков Адильхан | N3: 44973 | O3: 44992 | Q3: 45016 | R3: 45016 | S3: Зашли с новой заявкой
A4: 2 | B4: 320 | C4: МЖК Hayat Apartments | D4: Алматы | E4: ТОО «ТУР-ХАН» | F4: 050940003194 | G4: ТОО «HCG-05» | H4: 210640010894 | I4: 27110239834 | J4: 1009 | K4: 44972 | L4: Исмаков Адиль | N4: 44977 | S4: Исправление замечаний
A5: 3 | B5: 348 | C5: МЖК в мкр.Батыс-2, г.Актобе | D5: Актюбинская область | E5: ТОО "Эдельвейс" | F5: 981040003722 | G5: ТОО "Новострой-Актобе" | H5: 210940016011 | I5: 1226556110 | J5: 60 | K5: 44978 | L5: Исмаков Адиль | N5: 44981 | S5: Исправление замечаний
A6: 4 | B6: 352 | C6: МЖК Garden City | D6: Алматинская область, г. Конаев | E6: ТОО "Центральноазиатский Научно-Исследовательский и Проектный институт "Транс Нефть" | F6: 000840000908 | G6: ТОО "АТС-06" | H6: 060240000126 | I6: 5441382160 | J6: 528 | K6: 44980 | L6: Нурбаев Нурлан | N6: 44984 | S6: Исправление замечаний
A7: 5 | B7: 354 | C7: МЖК Apartex Burabay | D7: Акмолинская область | E7: ТОО "Биik Шаңырақ" | F7: 140740007872 | G7: ТОО "Apartex Burabay" | H7: 140340019900 | I7: 380442507 | J7: 60 | K7: 44981 | L7: Жакыпбеков Адильхан | N7: 44986 | S7: Исправление замечаний
A8: 6 | B8: 381 | C8: ЖК Capital | D8: Шымкент | E8: ТОО "Орда строй групп" | F8: 060240014641 | G8: ТОО "СAPITAL AVENUE" | H8: 210940041270 | I8: 19106709423 | J8: 485 | K8: 45062 | L8: Аяпова Гульнур | N8: 45065 | S8: Зашли с новой заявкой
A9: 7 | B9: 385 | C9: МЖК Комфортный дом Новом городе 3 | D9: Карагандинская область | E9: ТОО "COMFORT SOLUTIONS" | F9: 201140026308 | G9: ТОО "Eurasia Building1" | H9: 110440011339 | I9: 5609699023 | J9: 197 | K9: 45068 | L9: Жакыпбеков Адильхан | N9: 45071 | O9: 45103 | P9: 45106 | Q9: 45134 | R9: 45140 | S9: Исправление замечаний
A10: 8 | B10: 388 | C10: МЖК Маяк в г. Конаев | D10: Алматинская область, г. Конаев | E10: ТОО "Корпорация "Астана-Стройинвест" | F10: 000740002447 | G10: ТОО "MDI Construction" | H10: 190440002700 | I10: 4916104675 | J10: 216 | K10: 45075 | L10: Жусанова Толкын | N10: 45079 | S10: Зашли с новой заявкой
A11: 9 | B11: 397 | C11: МЖК в г. Усть-Каменогорск | D11: Усть-Каменогорск | E11: ТОО "Biryuza Construction» | F11: 040440036894 | G11: ТОО "УК Шанырак Строй" | H11: 230340036850 | I11: 2504748497 | J11: 63 | K11: 45079 | L11: Нурбаев Нурлан | N11: 45085 | S11: Исправление замечаний
A12: 10 | B12: 398 | C12: ЖК ГАЛАМАТ | D12: Алматинская область | E12: ТОО "Элит Проект Инжиниринг" | F12: 120340006886 | G12: ТОО "ЖК ГАЛАМАТ" | H12: 230240000142 | I12: 711510837 | J12: 48 | K12: 45079 | L12: Исмаков Адиль | N12: 45086 | S12: Зашли с новой заявкой
A13: 11 | B13: 402 | C13: ЖК "Capital" | D13: Шымкент | E13: ТОО "Орда строй групп" | F13: 060240014641 | G13: ТОО "СAPITAL AVENUE" | H13: 210940041270 | I13: 18169799082 | J13: 485 | K13: 45089 | L13: Нурбаев Нурлан | N13: 45093 | S13: Исправление замечаний
A14: 12 | B14: 387 | C14: МЖК Landmark, 3 очередь, пятна 1,3 | D14: Астана | E14: ТОО "BAZIS-A Corp." | F14: 960340000376 | G14: ТОО "Dostyk Land" | H14: 190240034484 | I14: 2815219200 | J14: 75 | K14: 45086 | L14: Алимжанова Данира | N14: 45093 | O14: 45203 | P14: 45209 | Q14: 45239 | R14: 45245 | S14: Исправление замечаний
A15: 13 | B15: 401 | C15: МЖК Лесная поляна, 12 очередь, 46Д | D15: Акмолинская обл., г. Косшы | E15: ТОО "Марапат 2011" | F15: 111140016064 | G15: ТОО "LP City" | H15: 211040012059 | I15: 2953550085 | J15: 210 | K15: 45089 | L15: Нурбаев Нурлан | N15: 45093 | S15: Зашли с новой заявкой
A16: 14 | B16: 403 | C16: МЖК | D16: Усть-Каменогорск | E16: ТОО "ВВД Курылыс" | F16: 060240025805 | G16: ТОО "Crystal Oskemen" | H16: 221140027082 | I16: 3730317893 | J16: 162 | K16: 45107 | L16: Алимжанова Данира | N16: 45112 | S16: Зашли с новой заявкой
A17: 15 | B17: 406 | C17: МЖК New City | D17: Астана | E17: ТОО "Ferrum Co." | F17: 091040005188 | G17: ТОО "New City1-2" | H17: 210740017161 | I17: 4002124719 | J17: 117 | K17: 45107 | L17: Уринбасарова Молдир | N17: 45112 | S17: Зашли с новой заявкой
A18: 16 | B18: 407 | C18: МЖК Туран | D18: Шымкент | E18: ТОО "Kanfar Building" | F18: 060340004172 | G18: ТОО "Turan Satu" | H18: 210940020852 | I18: 2934513361 | J18: 80 | K18: 45107 | L18: Башеева Жанна | N18: 45111 | O18: 45119 | P18: 45125 | S18: Зашли с новой заявкой
A19: 17 | B19: 418 | C19: МЖК MoD, 1-2 очередь | D19: Астана | E19: ТОО "Nova City Development" | F19: 110540015593 | G19: ТОО "Senim NC" | H19: 210840011146 | I19: =7244.731*1000000 -> 7244731000 | J19: 257 | K19: 45146 | L19: Башеева Жанна | N19: 45153 | O19: 45154 | P19: 45161 | S19: Зашли с новой заявкой
A20: 18 | B20: 419 | C20: МЖК Лесная поляна, 12 очередь, 49Д | D20: Акмолинская обл., г. Косшы | E20: ТОО "Марапат 2011" | F20: 111140016064 | G20: ТОО "LP City" | H20: 211040012059 | I20: 2623982344 | J20: 140 | K20: 45147 | L20: Нурбаев Нурлан | N20: 45153 | S20: Зашли с новой заявкой
A21: 19 | B21: 421 | C21: МЖК в г.Кокшетау | D21: Акмолинская обл.г.Кокшетау | E21: ТОО "Биik Шаңырақ" | F21: 140740007872 | G21: ТОО "M-Group Asia" | H21: 220240012372 | I21: 1088278078 | J21: 119 | K21: 45147 | L21: Арыстанбекова А. | N21: 45153 | S21: Зашли с новой заявкой
A22: 20 | B22: 422 | C22: МЖК Лесная поляна, 12 очередь, 48 Д | D22: Акмолинская обл., г. Косшы | E22: ТОО "Марапат 2011" | F22: 111140016064 | G22: ТОО "LP City" | H22: 211040012059 | I22: 1635711572 | J22: 110 | K22: 45149 | L22: Нурбаев Нурлан | N22: 45154 | S22: Зашли с новой заявкой
A23: 21 | B23: 424 | C23: МЖК | D23: Алматы | E23: ТОО "Сартай энерго Сервис" | F23: 070240022179 | G23: ТОО "А2 Invest" | H23: 220840003751 | I23: 7088802043 | J23: 176 | K23: 45159 | L23: Арыстанбекова А. | N23: 45163 | S23: Исправление замечаний
A24: 22 | B24: 427 | C24: МЖК | D24: Астана | E24: ТОО "Марапат 2011" | F24: 111140016064 | G24: ТОО "УПРАВЛЯЮЩАЯ КОМПАНИЯ "RESMAN" | H24: 160140004651 | I24: 9904943140 | J24: 55 | K24: 45167 | L24: Баркинхоев А. | N24: 45174 | O24: 45190 | P24: 45195 | S24: Исправление замечаний
A25: 23 | B25: 385 | C25: МЖК Комфортный дом Новом городе 3 | D25: Карагандинская область | E25: ТОО "COMFORT SOLUTIONS" | F25: 201140026308 | G25: ТОО "Eurasia Building1" | H25: 110440011339 | I25: 5609699023 | J25: 197 | K25: 45170 | L25: Жакыпбеков Адильхан | N25: 45176 | O25: 45190 | P25: 45195 | S25: Исправление замечаний
A26: 24 | B26: 430 | C26: МЖК Asar House Plus | D26: Шымкент | E26: ТОО "Композит-7" | F26: 050640012251 | G26: ТОО "Asar house" | H26: 210740014236 | I26: 2860596380 | J26: 65 | K26: 45173 | L26: Исмаков Адиль | N26: 45177 | S26: Зашли с новой заявкой
A27: 25 | B27: 442 | C27: МЖК Австрия, блок 3 | D27: Астана | E27: ТОО "BAZIS-A Corp." | F27: 960340000376 | G27: ТОО "Euro City-2" | H27: 190440041424 | I27: 1544370730 | J27: 54 | K27: 45197 | L27: Аяпова Г./Алимжанова Д. | N27: 45203 | O27: 45243 | P27: 45247 | S27: Зашли с новой заявкой
A28: 26 | B28: 443 | C28: МЖК Австрия, блок 4 | D28: Астана | E28: ТОО "BAZIS-A Corp." | F28: 960340000376 | G28: ТОО "Euro City-2" | H28: 190440041424 | I28: 1372954735 | J28: 40 | K28: 45197 | L28: Жусанова Т./ Жакыпбеков А. | N28: 45203 | O28: 45243 | P28: 45247 | S28: Зашли с новой заявкой
A29: 27 | B29: 445 | C29: МЖК Багыстан, 1 очередь | D29: Астана | E29: ТОО "BUILDINGPLUS" | F29: 180840024962 | G29: ТОО "Бағыстан" | H29: 161140023096 | I29: 9176506252 | J29: 264 | K29: 45198 | L29: Аяпова Г. | N29: 45205 | S29: Зашли с новой заявкой
A30: 28 | B30: 444 | C30: МЖК Soho | D30: Астана | E30: ТОО "BAZIS-A Corp." | F30: 960340000376 | G30: ТОО "SOVICO GROUP" | H30: 180240017561 | I30: 10030993319 | J30: 423 | K30: 45198 | L30: Арыстанбекова А. | N30: 45205 | O30: 45243 | S30: Зашли с новой заявкой
A31: 29 | B31: 446 | C31: МЖК | D31: Шымкент | E31: ТОО "Kanfar Building" | F31: 060340004172 | G31: ТОО "Otbasy Satu" | H31: 230240002119 | I31: 6804685307 | J31: 192 | K31: 45205 | L31: Башеева Ж. | N31: 45212 | S31: Исправление замечаний
A32: 30 | B32: 450 | C32: МЖК Бағыстан 1, 5 оч.позиция 2,4 | D32: Астана | E32: ТОО "Бағыстан" | F32: 161140023096 | G32: ТОО "NEW LINE PROJECT" | H32: 180240031389 | I32: 1.5986085e+10 | J32: 793 | K32: 45219 | L32: Жусанова Т. | N32: 45226 | S32: Зашли с новой заявкой
A33: 31 | B33: 455 | C33: МЖК Otbasy | D33: Шымкент | E33: ТОО "Kanfar Building" | F33: 060340004172 | G33: ТОО "Otbasy Satu" | H33: 230240002119 | I33: 6804685307 | J33: 192 | K33: 45223 | L33: Башеева Ж. | N33: 45231 | S33: Зашли с новой заявкой
A34: 32 | B34: 452 | C34: МЖК Adele | D34: Алматы | E34: ТОО "Елимай-Invest" | F34: 160640016168 | G34: ТОО "ЖК Adele" | H34: 220840053986 | I34: 9194531498 | K34: 45225 | L34: Башеева Ж. | N34: 45232 | S34: Исправление замечаний
A35: 33 | B35: 456 | C35: МЖК Байтерек | D35: Уральск | E35: ТОО "Караванный путь" | F35: 030840007596 | G35: ТОО "Уркер Строй" | H35: 220340033735 | I35: 1886723000 | J35: 75 | K35: 45239 | L35: Жакыпбеков А. | N35: 45246 | O35: 45267 | P35: 45273 | Q35: 45279 | S35: Исправление замечаний
A36: 34 | B36: 459 | C36: МЖК Modern City 2 | D36: Шымкент | E36: ТОО "Оңтүстік құрылыс Сервис" | F36: 010340004024 | G36: ТОО "OKS-Shymcity" | H36: 201140025012 | I36: 8967320951 | J36: 271 | K36: 45245 | L36: Уринбасарова Молдир | N36: 45252 | S36: Зашли с новой заявкой
A37: 35 | B37: 460 | C37: МЖК Престиж 3 | D37: Шымкент | E37: ТОО "Композит-7" | F37: 050640012251 | G37: ТОО "Dostyq Invest Group" | H37: 190140008530 | I37: 2754891000 | J37: 45 | K37: 45245 | L37: Нурбаев Нурлан | N37: 45251 | S37: Исправление замечаний
A38: 36 | B38: 466 | C38: МЖК Атамура | D38: Астана | E38: ТОО "Жетісу ЖҚ" | F38: 031240005283 | G38: ТОО "Горде" | H38: 120540000160 | I38: 7672975159 | J38: 296 | K38: 45268 | L38: Нурбаев Нурлан | N38: 45274 | S38: Исправление замечаний
A39: 37 | B39: 468 | C39: МЖК Star | D39: Алматы | E39: ТОО "EXCLUSIVE KURMANGAZY" | F39: 170840003753 | G39: ТОО "Exclusive Star" | H39: 200440003119 | I39: 7627323844 | J39: 261 | K39: 45289 | L39: Алимжанова Данира | N39: 45299 | S39: Исправление замечаний
A40: 38 | B40: 469 | C40: МЖК в г.Атырау, мкр. Шагала | D40: Атырау | E40: ТОО "КАСПИЙ-ЭКСПО" | F40: 080840016029 | G40: ТОО "BIGMA KZ" | H40: 080240012629 | I40: 3954968060 | J40: 480 | K40: 45289 | L40: Жусанова Т. | N40: 45299 | S40: Исправление замечаний
A41: 39 | B41: 470 | C41: МЖК Landmark, 3 очередь, пятна 1,3 | D41: Астана | E41: ТОО "BAZIS-A Corp." | F41: 960340000376 | G41: ТОО "Dostyk Land" | H41: 190240034484 | I41: 2815219200 | J41: 75 | K41: 45303 | L41: Алимжанова Данира | N41: 45310 | S41: Исправление замечаний
A42: 40 | B42: 474 | C42: МЖК MoD, 1-3 очередь | D42: Астана | E42: ТОО "Nova City Development" | F42: 110540015593 | G42: ТОО "Senim NC" | H42: 210840011146 | I42: 2679891550 | J42: 106 | K42: 45324 | L42: Башеева Ж. | N42: 45330 | S42: Исправление замечаний
A43: 41 | B43: 476 | C43: МЖК Star | D43: Алматы | E43: ТОО "EXCLUSIVE KURMANGAZY" | F43: 170840003753 | G43: ТОО "Exclusive Star" | H43: 200440003119 | I43: 7627323844 | J43: 261 | K43: 45324 | L43: Алимжанова Данира | N43: 45330 | O43: 45335 | P43: 45342 | S43: Исправление замечаний
A44: 42 | B44: 477 | C44: МЖК Мегаполис | D44: Астана | E44: ТОО "Марапат 2011" | F44: 111140016064 | G44: ТОО "УПРАВЛЯЮЩАЯ КОМПАНИЯ "RESMAN" | H44: 160140004651 | I44: 9904943140 | J44: 55 | K44: 45327 | L44: Баркинхоев А. | N44: 45334 | S44: Исправление замечаний
A45: 43 | B45: 478 | C45: МЖК Престиж 3 (дома 5, 6) | D45: г.Шымкент | E45: ТОО "Композит-7" | F45: 050640012251 | G45: ТОО "PRESTIGE INVEST" | H45: 220140016321 | I45: 1613184115 | J45: 45 | K45: 45328 | L45: Исмаков Адиль | N45: 45334 | O45: 45335 | S45: Заявка зарегестрирована
A46: 44 | B46: 479 | C46: ЖК Мангилик парк | D46: г.Астана | E46: ТОО "ТҰРАН ҚҰРЫЛЫС НС" | F46: 050640009251 | G46: ТОО "EL INVEST" | H46: 181140022389 | I46: 7417681106 | J46: 209 | K46: 45330 | L46: Жусанова Т. | N46: 45336 | O46: 45344 | S46: Заявка зарегестрирована
A47: 45 | B47: 481 | C47: МЖК Landmark, 3 очередь, пятна 1,3 | D47: Астана | E47: ТОО "BAZIS-A Corp." | F47: 960340000376 | G47: ТОО "Dostyk Land" | H47: 190240034484 | I47: 2815219200 | J47: 75 | K47: 45330 | L47: Алимжанова Данира | N47: 45337 | S47: Исправление замечаний
A48: 45 | B48: 482 | C48: МЖК Престиж, Жас Канат | D48: г.Шымкент | E48: ТОО "Композит-7" | F48: 050640012251 | G48: ТОО "PRESTIGE INVEST" | H48: 220140016321 | I48: 6223876362 | J48: 264 | K48: 45335 | L48: Исмаков Адиль | N48: 45342 | S48: Исправление замечаний
A49: 46 | B49: 483 | C49: ЖК Максима | D49: г. Алматы | E49: ТОО "KazSMU" | F49: 970540007997 | G49: ТОО "Maxima City" | H49: 030940000344 | I49: 1751727695 | J49: 64 | K49: 45342 | L49: Арыстанбекова А. | N49: 45345 | S49: Исправление замечаний
A50: 47 | B50: 484 | C50: ЖК Даулетті қалашық | D50: г.Астана | E50: ТОО "STROY OPT" | F50: 131240018048 | G50: ТОО "DAULETTI QALASHYQ" | H50: 170940003812 | I50: 13763471058 | J50: 674 | K50: 45343 | L50: Нурбаев Н. | N50: 45348 | S50: Заявка зарегестрирована
A51: 48 | B51: 482 | C51: МЖК Престиж 3 (дома 5, 6) | D51: г.Шымкент | E51: ТОО "Композит-7" | F51: 050640012251 | G51: ТОО "PRESTIGE INVEST" | H51: 220140016321 | I51: 6223876362 | J51: 264 | K51: 45349 | L51: Жусанова Т. | N51: 45355 | S51: Исправление замечаний
A52: 49 | B52: 487 | C52: ЖК Комфортный Дом в Жилом городе 3 | D52: г. Караганда | E52: ТОО "Eurasia Building 1" | F52: 110440011339 | G52: ТОО "Comfort Solution" | H52: 201140026308 | I52: 5609699023 | J52: 209 | K52: 45408 | L52: Жакыпбеков А. | N52: 45415 | S52: Исправление замечаний
A53: 50 | B53: 488 | C53: ЖК Otbasy 2 очередь | D53: г.Шымкент | E53: ТОО "Kanfar Building" | F53: 060340004172 | G53: ТОО "Otbasy Satu" | H53: 230240002119 | I53: 11265640030 | J53: 348 | K53: 45416 | L53: Башеева Ж. | N53: 45425 | S53: Исправление замечаний
A54: 51 | B54: 489 | C54: МЖК "PARASAT II" пятно 10,11 | D54: г. Алматы | E54: ТОО "SHEBERGOOD" | F54: 070240017648 | G54: ТОО "PARASAT II" | H54: 210740017974 | I54: 3103406715 | J54: 142 | K54: 45446 | L54: Исмаков А. | N54: 45449 | S54: Исправление замечаний
A55: 52 | B55: 491 | C55: МЖК Landmark, 3 очередь, пятно 2 | D55: г. Астана | E55: ТОО "BAZIS-A Corp." | F55: 960340000376 | G55: ТОО "Dostyk Land" | H55: 190240034484 | I55: 2589603399 | J55: 102 | K55: 45457 | L55: Смайлова Д. | N55: 45462 | O55: 45504 | S55: Исправление замечаний
A56: 53 | B56: 492 | C56: ЖК Сыр Самалы | D56: г. Кызылорда | E56: ТОО "Алтын Констракшн" | F56: 070340014459 | G56: ТОО "ЖК Сыр Самалы" | H56: 120240004412 | I56: 2479837000 | J56: 54 | K56: 45457 | L56: Арыстанбекова А. | N56: 45462 | S56: Исправление замечаний
A57: 54 | B57: 493 | C57: ЖК Даулетті қалашық | D57: г.Астана | E57: ТОО "STROY OPT" | F57: 131240018048 | G57: ТОО "DAULETTI QALASHYQ" | H57: 170940003812 | I57: =I50 -> 13763471058 | J57: =J50 -> 674 | K57: 45461 | L57: Нурбаев Н. | N57: 45464 | S57: Исправление замечаний
A58: 55 | B58: 494 | C58: ЖК Qasiet | D58: г.Астана | E58: ТОО "SENSATA CONSTRUCTION" | F58: 041040007551 | G58: ТОО "Sensata Urban Development" | H58: 201240028378 | I58: 10243010511 | J58: 377 | K58: 45462 | L58: Алимжанова Данира | N58: 45469 | S58: Исправление замечаний
A59: 56 | B59: 496 | C59: ЖК Maxima City | D59: г. Алматы | E59: ТОО "KazSMU" | F59: 970540007997 | G59: ТОО "Maxima City" | H59: 030940000344 | I59: 2976295000 | J59: 120 | K59: 45463 | L59: Смайлова Д. | N59: 45469 | S59: Исправление замечаний
A60: 57 | B60: 497 | C60: ЖК "Asar house" 3 очередь | D60: г.Шымкент | E60: ТОО "Композит-7" | F60: 050640012251 | G60: ТОО "Asar house" | H60: 210740014236 | I60: 2835753390 | J60: 130 | K60: 45468 | L60: Исмаков А. | N60: 45470 | S60: Исправление замечаний
A61: 58 | B61: 498 | C61: ЖК Центральный сквер, 4 очередь | D61: г.Астана | E61: ТОО "SENSATA CONSTRUCTION" | F61: 041040007551 | G61: ТОО "Sensata Build" | H61: 201240024454 | I61: 5936601406 | J61: 188 | K61: 45482 | L61: Алимжанова Д. | N61: 45485 | S61: Исправление замечаний
A62: 59 | B62: 499 | C62: МЖК Salzburg, блок 1,2,5 | D62: г.Астана | E62: ТОО "BAZIS-A Corp." | F62: 960340000376 | G62: ТОО "Euro City-2" | H62: 190440041424 | I62: 6454916135 | J62: 80 | K62: 45489 | L62: Жакыпбеков А | N62: 45493 | S62: Исправление замечаний
A63: 60 | B63: 500 | C63: МЖК "Energy, 1,2,3,4 очередь" | D63: г.Астана | E63: ТОО "Султан барыс" | F63: 150240018980 | G63: ТОО "Сарыарка Инвест Строй" | H63: 140940009023 | I63: 4829386412 | J63: 180 | K63: 45510 | L63: Жусанова Т. | N63: 45516 | S63: Зашли с новой заявкой
A64: 61 | B64: 501 | C64: МЖК "Мадениет" | D64: г.Алматы | E64: ТОО "KazSMU" | F64: 970540007997 | G64: ТОО "Qazaq Gimarat" | H64: 100240012645 | I64: 7497531000 | J64: 341 | K64: 45524 | L64: Смайлова Д. | N64: 45532 | S64: Исправление замечаний
A65: 62 | B65: 502 | C65: МЖК "Прайм Парк" 2-ой пусковой комплекс | D65: г.Шымкент | E65: ТОО "Standard construction-7" | F65: 190140038552 | G65: ТОО "Prime park" | H65: 200240004050 | I65: 5526120000 | J65: 176 | K65: 45531 | L65: Исмаков А. | N65: 45538 | S65: Зашли с новой заявкой
A66: 63 | B66: 503 | C66: МЖК "Кеменгер" | D66: г.Астана | E66: ТОО "SENSATA CONSTRUCTION" | F66: 041040007551 | G66: ТОО "Tarih CONSTRUCTION" | H66: 220340017367 | I66: 14447740390 | J66: 360 | K66: 45545 | L66: Жакыпбеков А. | N66: 45553 | S66: Зашли с новой заявкой
A67: 64 | B67: 504 | C67: МЖК "Aura Alatau" | D67: Алматинская обл. | E67: ТОО "Atamura group" | F67: 080440009616 | G67: ТОО "Aura Alatau" | H67: 230340012556 | I67: 1875024849 | J67: 106 | K67: 45547 | L67: Жакыпбеков А. | N67: 45553 | S67: Исправление замечаний
A68: 65 | B68: 505 | C68: ЖК "Сыр Самалы" | D68: г. Кызылорда | E68: ТОО "Алтын Констракшн" | F68: 070340014459 | G68: ТОО "ЖК Сыр Самалы" | H68: 120240004412 | I68: 5803005597 | J68: 126 | K68: 45555 | L68: Исмаков А. | N68: 45559 | S68: Исправление замечаний
A69: 66 | B69: 506 | C69: МЖК "Тулпар" | D69: г. Шымкент | E69: ТОО "Standart construction-7" | F69: 190140038552 | G69: ТОО "Tulpar apartments" | H69: 230340018614 | I69: 2444109983 | J69: 75 | K69: 45588 | L69: Аяпова Г.
A70: 67 | B70: 507 | C70: МЖК "Level" | D70: г.Астана | E70: ТОО "BAZIS-A Corp." | F70: 960340000376 | G70: ТОО "Astana real estate 2023" | H70: 221140030716 | I70: 11198517207 | J70: 298 | K70: 45588 | L70: Баркинхоев А.
A71: 68 | B71: 508 | C71: МЖК "Бағыстан-1", 4 очередь, позиция 13 | D71: г.Астана | E71: ТОО "Бағыстан" | F71: 161140023096 | G71: ТОО "Стройквартал" | H71: 190140009448 | I71: 5052468155 | J71: 152 | K71: 45593 | L71: Кенесов М.
A72: 69 | B72: 509 | C72: МЖК "Гранд Виктория (3-1)" | D72: г.Астана | E72: ТОО "Бағыстан" | F72: 161140023096 | G72: ТОО "BestStroy" | H72: 180840024972 | I72: 10028502500 | J72: 272 | K72: 45594 | L72: Аяпова Г.
C73: ВСЕГО | I73: =SUM(I3:I72) -> 4.3785543e+11 | J73: =SUM(J3:J72) -> 15099

Sheet Отказ и расторжение
B1: Проекты, по которым принято решение об отказе
A2: № | B2: Наименование Проекта | C2: Дата решение Правления/СД | D2: Регион | E2: Застройщик | F2: Уполномоченная компания | G2: Стоимость, тенге | H2: Площадь, кв.м | I2: Количество квартир
A3: 1 | B3: МЖК в г. Шымкент | D3: г. Шымкент | E3: ТОО "ЖистройИндустрия" | F3: ТОО "Строй Инвест KZT" | G3: 3179849587 | H3: 25750.68 | I3: 432
A4: 2 | B4: МЖК Адмирал | C4: 44714 | D4: г. Алматы | E4: ТОО "Премьер-Строй" | F4: ТОО"Tauman Qurylys" | G4: 3195524000 | H4: 8444.74 | I4: 120
A5: 3 | B5: МЖК Игилик | C5: 44722 | D5: г. Шымкент | E5: ТОО "Берен" | F5: ТОО "Igilik Park" | G5: 872636238 | H5: 3 154,8 | I5: 50
A6: 4 | B6: МЖК Авалон | C6: 44722 | D6: г. Шымкент | E6: ТОО "Берен" | F6: ТОО "Берен estate development" | G6: 1703254300 | H6: 6258.77 | I6: 52
A7: 5 | B7: МЖК Престиж, Жас Канат | C7: 45399 | D7: г.Шымкент | E7: ТОО "Композит-7" | F7: ТОО "PRESTIGE INVEST" | G7: 6223876362 | H7: 13855.48 | I7: 264
A8: 6 | B8: МЖК Сыр Самалы | C8: 45520 | D8: г. Кызылорда | E8: ТОО "Алтын Констракшн" | F8: ТОО "ЖК Сыр Самалы" | G8: 5803005597 | H8: 14921.84 | I8: 126
A9: 7 | B9: МЖК Energy 1,2,3,4 очередь | C9: 45575 | D9: г.Астана | E9: ТОО "Султан барыс" | F9: ТОО "Сарыарка инвест строй" | G9: 4829386412 | H9: 13122.41 | I9: 180
B10: ВСЕГО | G10: =SUM(G3:G9) -> 25807532496 | H10: =SUM(H3:H9) -> 82353.92 | I10: =SUM(I3:I9) -> 1224
B11: Проекты, по которым принято решение об отказе по DB
A12: № | B12: Наименование Проекта | C12: Дата решение Правления/СД | D12: Область | E12: Застройщик | F12: Уполномоченная компания | G12: Стоимость, тенге | H12: Количество квартир по Проекту | I12: Дата регистрации заявки | J12: Номер в SB | K12: Исполнитель от фронт-офиса | L12: ДРЮЛ | M12: ДПО | N12: СКК | O12: ДОЗ | P12: ДТЭМ | Q12: ДРМ | R12: ДОРАБОТКА Дата исходящего/Дата входящего | T12: ДРЮЛ | U12: ДПО | V12: СКК | W12: ДОЗ | X12: ДТЭМ | Y12: ДРМ
A13: 6 | B13: МЖК (дом 39) Лесная поляна 10 очередь | C13: 15.09.2022 | D13: Акмолинская обл., г. Косшы | E13: ТОО "Марапат 2011" | F13: ТОО "LP Construction" | G13: 758935700 | H13: 75 | I13: 44757 | J13: 232 | K13: Нурбаев Нурлан | L13: 44762 | M13: 44762 | N13: 44761 | O13: 44762 | P13: 44762 | Q13: 44771 | R13: 44774 | S13: 17.08.2022 01.09.2022 | T13: 19.08.2022 Полож. 02.09.2022 Полож. | U13: 20.08.2022 Отриц. 02.09.2022 Полож. | V13: 19.08.2022 Полож. 05.09.2022 Отриц. | W13: 20.08.2022 Полож. 01.09.2022 Соот. | X13: 19.08.2022 Полож.-на доработку 01.09.2022 Полож. | Y13: 19.08.2022 Отриц. 06.09.2022 Отриц.
A14: 7 | B14: МЖК (дом 39) Лесная поляна 10 очередь | C14: 18.10.2022 | D14: Акмолинская обл., г. Косшы | E14: ТОО "Марапат 2011" | F14: ТОО "LP Construction" | G14: 758935700 | H14: 75 | I14: 44827 | J14: 255 | K14: Нурбаев Нурлан | L14: 44833 | M14: 44832 | N14: 44830 | O14: 44827 | P14: 44831 | Q14: 44839
A15: 8 | B15: МЖК Monaco пятно 5 | C15: 01.11.2022 | D15: Астана | E15: ТОО "BAZIS-A Corp." | F15: ТОО "Euro City-1" | G15: 3784768000 | H15: 118 | I15: 44837 | J15: 259 | K15: Жакыпбеков Адильхан | L15: 44845 | M15: 44844 | N15: 44844 | O15: 44845 | P15: 44844 | Q15: 44848 | R15: 44848 | S15: 44853 | T15: 21.10.2022 Полож. | U15: 21.10.2022 Полож. | V15: 22.10.2022 Не выявлено | W15: 20.10.2022 Соотв. | X15: 21.10.2022 Отказ. | Y15: 21.10.2022 Отказ.
A16: 9 | B16: МЖК Ак-Дидар 3, пятна 92,93,94 | C16: 15.11.2022 | D16: Астана | E16: ТОО "BAZIS-А Corp." | F16: ТОО "АК ДИДАР-3" | G16: 2129895950 | H16: 267 | I16: 44856 | J16: 269 | K16: Аяпова Гульнур | L16: 44862 | M16: 44862 | N16: 44860 | O16: 44860 | P16: 44861 | Q16: 44862 | R16: 44865 | S16: 44868 | T16: 03.11.2022 Полож. | U16: 04.11.2022 Отриц. | V16: 44868 | W16: 03.11.2022 Соотв. | X16: 07.11.2022 Отриц. | Y16: 07.11.2022 Отриц.
A17: 10 | B17: МЖК Аман пятно 7 | C17: 29.11.2022 | D17: Астана | E17: ТОО "BAZIS-А Corp." | F17: ТОО "УК Орынбор 2017" | G17: 2596718000 | H17: 135 | I17: 44872 | J17: 269 | K17: Камалитден Бауыржан | L17: 44874 | M17: 44874 | N17: 44873 | O17: 44874 | P17: 44875 | Q17: 44879 | R17: 44880 | S17: 44886 | T17: 23.11.2022 Полож. | U17: 23.11.2022 Отриц. | V17: 44888 | W17: 22.11.2022 Соотв. | X17: 23.11.2022 Отриц. | Y17: 24.11.2022 Отриц.
A18: 11 | B18: МЖК Зангар | C18: 13.11.2022 | D18: Астана | E18: ТОО "BAZIS-А Corp." | F18: ТОО "Gefest-2021" | G18: 5511763448 | H18: 162 | I18: 44880 | J18: 222 | K18: Исмаков Адиль | L18: 44881 | M18: 44882 | N18: 44881 | O18: 44882 | P18: 44881 | Q18: 44883 | R18: 44886 | S18: 44893 | T18: 29.11.2022 Отказ. | U18: 30.11.2022 Отказ. | V18: 29.11.2022 Отриц. | W18: 29.11.2022 Соотв. | X18: 30.11.2022 Отказ. | Y18: 01.12.2022 Отказ.
A19: 12 | B19: МЖК Балауса | C19: 15.11.2022 | D19: Астана | E19: ТОО «SENSATA CONSTRUCTION» | F19: ТОО «Sensata Engineering» | G19: 7681400195 | H19: 280 | I19: 44886 | J19: 281 | K19: Далматова Данира | L19: 44888 | M19: 44889 | N19: 44886 | O19: 44888 | P19: 44890 | Q19: 44895 | R19: 44895 | S19: 44902 | T19: 08.12.2022 Полож. | U19: 08.12.2022 Отриц. | V19: 07.12.2022 Соотв. | W19: 07.12.2022 Не соотв. | X19: 09.12.2022 Отриц. | Y19: 09.12.2022 Отриц.
A20: 13 | B20: МЖК Арлын оч.3 | C20: 29.12.2022 | D20: Алматинская обл. | E20: ТОО «Atamura Group» | F20: ТОО «Arlyn» | G20: 1082543056 | H20: 59 | I20: 44893 | J20: 286 | K20: Нурбаев Нурлан | L20: 30.11.20222 Доработка | M20: 01.12.2022 Доработка | N20: 29.11.2022 Не соотв. | O20: 30.11.2022 Не соотв. | P20: 02.12.2022 Доработка | Q20: 06.12.2022 Доработка | R20: 44902 | S20: 44909 | T20: 14.12.2022 Полож. | U20: 19.12.2022 Отриц. | V20: 15.12.2022 Соотв. | W20: 14.12.2022 Соотв. | X20: 15.12.2022 Полож. | Y20: 19.12.2022 Отриц.
A21: 14 | B21: ЖК в г.Актобе | C21: 29.12.2022 | D21: Актобе | E21: ТОО "SK Qyrulus" | F21: ТОО "Shanyraq Qurylys" | G21: 1812103439 | H21: 95 | I21: 44900 | J21: 294 | K21: Жакыпбеков Адильхан | L21: 07.12.2022 Полож. | M21: 08.12.2022 Доработка | N21: 05.12.2022 Соотв. | O21: 08.12.2022 Не соотв. | P21: 06.12.2022 Доработка | Q21: 13.12.2022 Доработка | R21: 44909 | S21: 44910 | T21: 19.12.2022 Полож. | U21: 21.12.2022 Отриц. | V21: 19.12.2022 Соотв. | W21: 19.12.2022 Не соотв. | X21: 21.12.2022 Полож. | Y21: 20.12.2022 Отказ.
A22: 15 | B22: ЖК Кристалл | C22: 44936 | D22: Алматы | E22: ТОО "ВВД-Құрылыс" | F22: ТОО "CRYSTAL SHYMKENT" | G22: 2757296296 | H22: 103 | I22: 44908 | J22: 299 | K22: Далматова Данира | L22: 15.12.2022 Полож. | M22: 15.12.2022 Доработка | N22: 14.12.2022 Соотв. | O22: 15.12.2022 Соотв. | P22: 15.12.2022 Доработка | Q22: 22.12.2022 Доработка | R22: 44918 | S22: 44922 | T22: 28.12.2022 Полож. | U22: 29.12.2022 Отриц. | V22: 27.12.2022 Соотв. | W22: 27.12.2022 Соотв. | X22: 29.12.2022 Полож. | Y22: 28.12.2022 Отказ.
A23: 16 | B23: МЖК Jetisu Aqsu | C23: 10.01.2023 | D23: Астана | E23: ТОО "Nova City Development" | F23: ТОО "Азат-М" | G23: 9058222630 | H23: 338 | I23: 44909 | J23: 295 | K23: Аяпова Гульнур | L23: 20.12.2022 Доработка | M23: 20.12.2022 Доработка | N23: 19.12.2022 Соотв. | O23: 19.12.2022 Не соотв. | P23: 20.12.2022 Доработка | Q23: 23.12.2022 Доработка | R23: 44921 | S23: 44936
A24: 17 | B24: МЖК Престиж, 2 очередь | C24: 44957 | D24: Шымкент | E24: ТОО "Композит-7" | F24: ТОО "Dostyq Invest Group" | G24: 4285521044 | H24: 90 | I24: 44930 | J24: 307 | K24: Исмаков Адиль | L24: 09.01.2023 Доработка | M24: 09.01.2023 Доработка | N24: 05.01.2023 Соотв. | O24: 06.01.2023 Соотв. | P24: 10.01.2023 Доработка | Q24: 16.01.2023 Отриц. | R24: 44942 | S24: 44949 | T24: 24.01.2023 Полож. | U24: 25.01.2023 Отриц. | V24: 24.01.2023 Соотв. | W24: 24.01.2023 Соотв. | X24: 25.01.2023 Отриц. | Y24: 26.01.2023 Отриц.
A25: 18 | B25: МЖК Достык в г.Уральск | C25: 16.02.2023 | D25: Уральск | E25: ТОО "ALEM GROUP KAZAKHSTAN" | F25: ТОО "ATM GROUP KAZAKHSTAN" | G25: 2625205130 | H25: 136 | I25: 44943 | J25: 303 | K25: Уринбасарова Молдир | L25: 23.01.2023 Доработка | M25: 20.01.2023 Доработка | N25: 17.01.2023 Соотв. | O25: 18.01.2023 Не соотв. | P25: 18.01.2023 Доработка | Q25: 26.01.2023 Доработка | R25: 44953 | S25: 44595 | T25: 07.02.2023 Отриц. | U25: 06.02.2023 Отриц. | V25: 06.02.2023 Соотв. | W25: 06/02/2023 Не соотв. | X25: 06.02.2023 Отриц.
A26: 19 | B26: МЖК Jetisu Aqsu | C26: 10.03.2023 | D26: Астана | E26: ТОО "Nova City Development" | F26: ТОО "Азат-М" | G26: 9058222630 | H26: 338 | I26: 44974 | J26: 340 | K26: Алимжанова Данира | L26: 21.02.2023 Доработка | M26: 21.02.2023 Доработка | N26: 17.02.2023 Соотв. | O26: 22.02.2023 Не соотв. | P26: 22.02.2023 Доработка | Q26: 24.02.2023 Доработка | R26: 44981 | S26: 44985
A27: 20 | B27: МЖК Sezim Qala Shattyq | C27: 28.03.2023 | D27: Астана | E27: ТОО "Nova City Development" | F27: ТОО "Тенгри Хаус Астана" | G27: 6.70542e+09 | H27: 319 | I27: 44980 | J27: 330 | K27: Бажиева Жанна | L27: 28.02.2023 Доработка | M27: 27.02.2023 Доработка | N27: 24.02.2023 Соотв. | P27: 27.02.2023 Доработка | Q27: 03.03.2023 Доработка | R27: 44991 | S27: 44998 | T27: 15.03.2023 Полож. | U27: 15.03.2023 Отриц. | V27: 15.03.2023 Соотв. | W27: 14.03.2023 Соотв. | X27: 16.03.2023 Отриц. | Y27: 16.03.2023 Отриц.
A28: 21 | B28: МЖК Дастюр | C28: 07.04.2023 | D28: Астана | E28: ТОО "РинЭлд" | F28: ТОО "Алтын Саулет Астана" | G28: 12416737533 | H28: 526 | I28: 44988 | J28: 343 | K28: Башеева Жанна | L28: 09.03.2023 Доработка | M28: 09.03.2023 Полож. | N28: 07.03.2023 Соотв. | O28: 07.03.2023 Не соотв. | P28: 10.03.2023 Доработка | Q28: 14.03.2023 Доработка | R28: 45000 | S28: 45002 | T28: 20.03.2023 Отриц. | U28: 24.03.2023 Полож. | V28: 20.03.2023 Соотв. | W28: 24.03.2023 Не соотв. | X28: 27.03.2023 Отриц. | Y28: 27.03.2023 Отриц.
A29: 22 | B29: МЖК Sezim Qala, очередь 13 | C29: 13.04.2023 | D29: Астана | E29: ТОО "Nova City Development" | F29: ТОО "Ғимарат НС" | G29: 6608817195 | H29: 278 | I29: 44995 | J29: 353 | K29: Алимжанова Данира | L29: 13.03.2023 Доработка | M29: 14.03.2023 Доработка | N29: 10.03.2023 Соотв. | O29: 10.03.2023 Соотв. | P29: 14.03.2023 Доработка | Q29: 20.03.2023 Доработка | R29: 45009 | S29: 45016 | T29: 03.04.2023 Полож. | U29: 04.03.2023 Отриц. | V29: 31.03.2023 Соотв. | W29: 31.03.2023 Соотв. | X29: 04.04.2023 Полож. | Y29: 05.04.2023 Отриц.
A30: 23 | B30: МЖК в г.Косшы | C30: 25.04.2023 | D30: Акмолинская обл., г. Косшы | E30: ТОО "Марапат" | F30: ТОО "LP City" | G30: 2953550085 | H30: 210 | I30: 45013 | J30: 357 | K30: Нурбаев Нурлан | L30: 30.03.2023 Полож. | M30: 30.03.2023 Доработка | N30: 30.03.2023 Соотв. | O30: 30.03.2023 Не соотв. | P30: 30.03.2023 Полож. | Q30: 45021 | R30: 45021 | S30: 45028
A31: 24 | B31: МЖК Комфортный дом Новом городе 3 | C31: 05.05.2023 | D31: Караганда | E31: ТОО "Eurasia Building1" | F31: ТОО "COMFORT SOLUTIONS" | G31: 5609699023 | H31: 197 | I31: 45019 | J31: 339 | K31: Жакыпбеков Адильхан | L31: 06.04.2023 Доработка | M31: 05.04.2023 Доработка | N31: 04.04.2023 Не соотв. | O31: 45021 | P31: 06.04.2023 Доработка | Q31: 12.04.2023 Доработка | R31: 45029 | S31: 45036 | T31: 45040 | U31: 24.04.2023 Отриц. | V31: 1.04.2023 Не соотв. | W31: 21.04.2023 Не соотв. | X31: 25.04.2023 Отриц. | Y31: 26.04.2023 Отриц.
A32: 25 | B32: МЖК Алтын Сапа | C32: 01.06.2023 | D32: Астана | E32: ТОО "Алтын Сапа Астана" | F32: ТОО "Медремсервис" | G32: 7929463000 | H32: 301 | I32: 45069 | J32: 365 | K32: Исмаков Адиль | L32: 04.05.2023 доработка | M32: 04.05.2023 доработка | N32: 04.05.2023 соответ. | O32: 04.05.2023 соответс. | P32: 05.05.2023 доработка | Q32: 15.05.2023 Доработка | R32: 45062 | S32: 45069 | T32: 26.05.2023 отказ | U32: 24.05.2023 полож. | V32: 24.05.2023 полож. | W32: 24.05.2023 соотв. | X32: 26.05.2023 отказ. | Y32: 26.05.2023 отказ
A33: 26 | B33: МЖК в г. Усть-Каменогорск | C33: 45134 | D33: г. Усть-Каменогорск | E33: ТОО "Biryuza Construction» | F33: ТОО "УК Шанырак Строй" | G33: 2504748497 | H33: 63 | I33: 45097 | J33: 397 | K33: Бижанова Назым | L33: 23.06.2023 Полож. | M33: 23.06.2023 Доработка | N33: 21.06.2023 Соотв. | O33: 23.06.2023 Не соотв. | P33: 21.06.2023 Доработка | Q33: 01.07.2023 отриц. | R33: 45110 | S33: 45119 | T33: 14.07.2023 Полож. | U33: 17.07.2023 Отказ. | V33: 17.07.2023 Соотв. | W33: 14.07.2023 Не соотв. | X33: 14.07.2023 Полож. | Y33: 19.07.2023 Отриц.
A34: 27 | B34: ЖК ГАЛАМАТ | C34: 45134 | D34: Алматинская область Илийский р-н, п. Боралдай | E34: ТОО "Элит Проект Инжиниринг" | F34: ТОО ""ЖК ГАЛАМАТ" | G34: 711510837 | H34: 48 | I34: 45098 | J34: 398 | K34: Исмаков Адиль | L34: 27.06.2023 Доработка | M34: 26.06.2023 Доработка | N34: 45099 | O34: 26.06.2023 Соотв. | P34: 26.06.2023 Доработка | Q34: 01.07.2023 отриц. | R34: 45110 | S34: 45118 | T34: 13.07.2023 Отриц. | U34: 13.07.2023 Полож. | V34: 17.07.2023 Соотв. | W34: 12.07.20.23 Соотв. | X34: 12.07.2023 Отриц. | Y34: 17.07.2023 Отриц.
A35: - | B35: Наружные инженерные сети МЖК Aisar | C35: 45209 | D35: г.Астана | E35: ТОО "Nova City Development" | F35: ТОО "Family Village NS" | G35: 2655642045 | I35: 45180 | K35: Алимжанова Данира | L35: 13.09.2023 Полож. | M35: 12.09.2023 Доработка | N35: 11.09.2023 Соотв. | P35: 14.09.2023 Доработка | Q35: 15.09.2023 Доработка | R35: 45187 | S35: 45191 | T35: 27.09.2023 Отриц. | U35: 26.09.2023 Полож. | V35: 25.09.2023 Соотв. | X35: 27.09.2023 Отказ | Y35: 45201
A36: 28 | B36: МЖК Престиж 3 | C36: 45300 | D36: г. Шымкент | E36: ТОО "Композит-7" | F36: ТОО "PRESTIGE INVEST" | G36: 2754891000 | H36: 45 | I36: 45264 | J36: 460 | K36: Нурбаев Нурлан | L36: 07.12.2023 отриц. | M36: 07.12.2023 отриц. | N36: 08.12.2023 соответ. | O36: 06.12.2023 соответ. | P36: 08.12.2023 отриц. | Q36: 13.12.2023 отриц. | R36: 45274 | S36: 45282 | T36: 22.12.2023 отриц. | U36: 25.12.2023 отриц. | V36: 26.12.2023 соответ. | W36: 22.12.2023 сооответ. | X36: 25.12.2023 полож. | Y36: 26.12.2023 отриц.
B37: ВСЕГО | G37: =SUM(G13:G36) -> 1.0475201e+11 | H37: =SUM(H13:H36) -> 4258
C39: количество проектов | D39: стоимость по Проектам | F39: Количество квартир
A40: ВСЕГО ОТКАЗАНО | C40: 28 | D40: =G37+G10 -> 1.3055954e+11 | F40: =H37+I10 -> 5482
B42: Проекты, по которым ДПГ не заключен
A43: № | B43: Наименование Проекта, регион, уровень и дата принятия решения и ДПГ | C43: Дата решение Правления/СД | D43: Регион | E43: Застройщик | F43: Уполномоченная компания | G43: Стоимость, тенге | H43: Площадь, кв.м | I43: Количество квартир | S43: Дата завершения
A44: 1 | B44: ЖК "Айнабулак" Отказано в подписании ДПГ ввиду завершения строительства ЖК | C44: 43903 | D44: г. Алматы | E44: ТОО "ЖВК" | F44: ТОО "Aigerim Development" | G44: 673138280 | H44: 5443.1 | I44: 72
A45: 2 | B45: ЖК Capital Park Договор не заключен, отзыв заявки | C45: 44060 | D45: г. Астана | E45: ТОО Милан-Астана" | F45: ТОО "Capital Park" | G45: 6217205830 | H45: 26499.13 | I45: 236
A46: 3 | B46: МЖК Capital Park 3E Договор не заключен, отзыв заявки | C46: 44260 | D46: г. Астана | E46: ТОО "Garant stroy" | F46: ТОО "ИсМи" | G46: 9447781555 | H46: 42948.1 | I46: 319
A47: 4 | B47: МЖК Бестерек 3 очередь Договор не заключен, отзыв заявки | C47: 44260 | D47: г. Астана | E47: ТОО "Garant stroy" | F47: ТОО "Premier Palace" | G47: 3387069648 | H47: 14673.44 | I47: 169
A48: 5 | B48: МЖК в г.Усть-каменогорск Договор не заключен, отзыв заявки | C48: 44873 | D48: г. Усть-Каменогорск | E48: ТОО "Service СМУ" | F48: ТОО "VK Diamond" | G48: 2844036000 | H48: 9241.63 | I48: 92
A49: 6 | B49: МЖК Ак-Дидар 3, пятна 92,93,94 Договор не заключен, отзыв заявки, в связи с отказом в подписании ДИУ | C49: 44966 | D49: г.Астана | E49: ТОО "BAZIS-A Corp." | F49: ТОО "АК ДИДАР-3" | G49: 2129895950 | H49: 18482.5 | I49: 267
A50: 7 | B50: МЖК Sensata City, 3 очередь Договор не заключен, отзыв заявки, в связи с отказом в подписании ДИУ | C50: 44978 | D50: г.Алматы | E50: ТОО «SENSATA CONSTRUCTION» | F50: ТОО «ASTANA REALITY GROUP» | G50: 16315105994 | H50: 48359.74 | I50: 621
A51: 8 | B51: МЖК Diplomat Договор не заключен, отзыв заявки, в связи с отказом в подписании ДИУ | C51: 45048 | D51: г. Актау | E51: ТОО "Astana 2021 KA" | F51: ТОО "МАКСТРОЙ АСТАНА" | G51: 5639392560 | H51: 20816 | I51: 120
A52: 9 | B52: МЖК Jetisu Aqsu 3 Договор не заключен, отзыв заявки, в связи с отказом в подписании ДИУ | C52: 45063 | D52: г. Астана | E52: ТОО "Nova City Development" | F52: ТОО "Азат-М" | G52: 8666911187 | H52: 24550.5 | I52: 338
B53: ВСЕГО | G53: =SUM(G44:G52) -> 55320537004 | H53: =SUM(H44:H52) -> 211014.14 | I53: =SUM(I44:I52) -> 2234
B56: Проекты, по которым ДПГ был расторгнут
A57: № | B57: Наименование Проекта, регион, уровень и дата принятия решения и ДПГ | C57: Дата решение Правления/СД | D57: Регион | E57: Застройщик | F57: Уполномоченная компания | G57: Стоимость, тенге | H57: Площадь, кв.м | I57: Дата заключения договора о предоставлении гарантии | J57: Количество квартир | K57: Этажность | L57: Дата начала строительства | M57: Дата расторжения ДПГ | N57: Гарантийный взнос, тенге
A58: 1 | B58: МЖК в г. Актобе | C58: 43895 | D58: г. Актобе | E58: ТОО "ЕРЕН-групп" | F58: ТОО "City Club Construction" | G58: 1246827090 | H58: 10153.9 | I58: 43976 | J58: 108 | K58: 14 | L58: 43874 | M58: 44196 | N58: 22629853
A59: 2 | B59: ЖК в г. Караганды | C59: 43998 | D59: г. Караганды | E59: ТОО "Eurasia Building" | F59: ТОО "Eurasia Building3" | G59: 4027747750 | H59: 24565.5 | I59: 44176 | J59: 240 | K59: 16 | L59: 43601 | M59: 44329 | N59: 71542243
A60: 3 | B60: МЖК Баян Сулу | C60: 44908 | D60: г. Шымкент | E60: ТОО «А.Р.Т. -ҚҰРЫЛЫС» | F60: ТОО «TURAN NEW BUILD» | G60: 3613195374 | H60: 18486.9 | I60: 44946 | J60: 240 | K60: 5 | L60: 44872 | M60: 45043 | N60: =32444395.91-14484105.36 -> 17960291
A61: 4 | B61: МЖК Discovery 3-оч. (пятно 4) | C61: 44616 | D61: г. Астана | E61: ТОО "BAZIS-A Corp." | F61: ТОО "Аstana real estate 2017" | G61: 2448882300 | H61: 17982.62 | I61: 44651 | J61: 180 | K61: 19 | L61: 44581 | M61: 45145 | N61: 24037733
A62: 5 | B62: МЖК Баян Сулу | C62: 45029 | D62: г. Актобе | E62: ТОО "SK Qyrulus" | F62: ТОО "Shanyraq Qurylys" | G62: 1812103439 | H62: 9847.3 | I62: 45065 | J62: 95 | K62: 5 | L62: 44816 | M62: 45259 | N62: 14465474
A63: 6 | B63: МЖК Достар пятно 12 | C63: 44840 | D63: Алматинская обл. | E63: ТОО "Элитстрой Алматы" | F63: ТОО "Уполномоченная компания "Достар" | G63: 3221033193 | H63: 17698.6 | I63: 44869 | J63: 233 | K63: 9 | L63: 44732 | M63: 45309 | N63: 27491853
A64: 7 | B64: МЖК Crystal | C64: 45139 | D64: г. Усть-Каменогорск | E64: ТОО "ВВД-Құрылыс" | F64: ТОО "Crystal Oskemen" | G64: 3730317893 | H64: 13840.12 | I64: 45104 | J64: 162 | K64: 12.14 | L64: 45104 | M64: 45378 | N64: 34341501
A65: 8 | B65: ЖК ГАЛАМАТ | C65: 45155 | D65: Алматинская обл. п.Боралдай | E65: ТОО "Элит Проект Инжиниринг" | F65: ТОО "ЖК ГАЛАМАТ" | G65: 745892709 | H65: 2868.92 | I65: 45176 | J65: 48 | K65: 5 | L65: 45077 | M65: 45468 | N65: 7265264
B66: ВСЕГО | G66: =SUM(G60:G65) -> 15571424908 | H66: =SUM(H60:H65) -> 80724.46 | J66: =SUM(J60:J65) -> 958 | N66: =SUM(N60:N65) -> 1.2556212e+08
A69: ВСЕГО ОТКАЗАНО | C69: =C40 -> 28 | D69: =D40 -> 1.3055954e+11 | F69: =F40 -> 5482
A70: ДПГ НЕ ЗАКЛЮЧЕН | C70: =A52 -> 9 | D70: =G53 -> 55320537004 | E70: =H53 -> 211014.14 | F70: =I53 -> 2234
A71: ДПГ РАСТОРГНУТ | C71: 7 | D71: =G66 -> 15571424908 | E71: =H66 -> 80724.46 | F71: =J66 -> 958

Sheet Отозванные
B1: Проекты, по которым отозвана Заявка до решения Правления
A2: № | B2: Номер в SB | C2: Наименование Проекта | D2: Область | E2: Застройщик | G2: уполномоченная компания | I2: Стоимость, тенге | J2: Количество квартир по Проекту | K2: Дата регистрации заявки | N2: Исполнитель от фронт-офиса | O2: ДСГиС | P2: ДПО | Q2: СКК | R2: ДОЗ | S2: ДТЭМ | T2: ДРМ | U2: ДОРАБОТКА Дата исходящего/Дата входящего | W2: ДСГиС | X2: ДПО | Y2: СКК | Z2: ДОЗ | AA2: ДТЭМ | AB2: ДРМ | AC2: Текущий статус
A3: 1 | B3: 211 | C3: МЖК в г.Усть-каменогорск | D3: Усть-Каменогорск | E3: ТОО "ТОО "Service СМУ" | G3: ТОО "ТОО "VK Diamond" | I3: 1908879358 | J3: 57 | K3: 44726 | N3: Кабашев Куат | O3: заключение пред-но | P3: заключение пред-но | Q3: заключение пред-но | R3: заключение пред-но | S3: заключение пред-но | T3: заключение пред-но | U3: 44736 | V3: Заявка отозвана вх.письмом в SimBase, произведен возврат комиссии 05.07.2022, в Dijital Baiterek заявка еще не отозвана
A4: 2 | B4: 220 | C4: МЖК в г.Уральск | D4: Уральск | E4: ТОО "Каз-Хол" | G4: ТОО "JYLTYR KURYLYS" | I4: 1923682907 | J4: нет ПСД | K4: 44735 | N4: Уринбасарова Молдир | O4: 44739 | P4: 44741 | Q4: 44740 | R4: 44747 | S4: 44736 | T4: 44747 | U4: 44747 | V4: 44754 | W4: Заявка отозвана в Dijital Baiterek от 13.07.2022 г., письмо о возврате комиссии от 14.07.2022 в SimBase
A5: 3 | B5: 231 | C5: МЖК в г.Астана (пер. пр.Кабанбай батыра и ул.Т.Рыскулова) | D5: Асатана | E5: ТОО "МТС КОМПАНИ ЛТД" | G5: ТОО "СК ТАСТЕМИР" | I5: 5758858727 | J5: 344 | K5: 44753 | N5: Курманбаева Айгерим | O5: 44757 | P5: 44755 | Q5: 44755 | R5: 44753 | S5: 44756 | T5: 44762 | U5: 44762 | V5: 44770 | W5: SimBase 29.07.2022 заявка приостановлена инициатором в связи с неполадаками в SimBase
A6: 4 | B6: 227 | C6: МЖК в г.Нур-Султан | D6: Асатана | E6: ТОО "КОМПАНИЯ СЕВ-РЕГИОН СТРОЙ" | G6: ТОО "КУТТЫ МЕКЕН 2022" | I6: 3655024230 | J6: 312 | K6: 44741 | N6: Нурбаев Нурлан | O6: 44746 | P6: 44747 | Q6: 44747 | R6: 44746 | S6: 44746 | T6: 44754 | U6: 44754 | V6: 44762 | W6: Заявка отозвана в Dijital Baiterek от 25.07.2022 г., письмо о возврате комиссии от 26.07.2022 в SimBase
A7: 5 | B7: 233 | C7: МЖК в г.Уральск | D7: Уральск | E7: ТОО " ALEM GROUP KAZAKHSTAN" | G7: ТОО "ATM GROUP KAZAKHSTAN" | I7: 2625205130 | J7: 136 | K7: 44762 | N7: Жаныбек Айман | O7: 44767 | P7: 44767 | Q7: 44767 | R7: 44764 | S7: 44767 | T7: 44774 | U7: 44775 | V7: Заявка приостановлена
A8: 6 | B8: 237 | C8: МЖК «ECO-PARK ALATAU» первая очередь Пятно 3, 4 | D8: Алматинская обл. | E8: ТОО "Строительная компания Элитстрой" | G8: ТОО "Уполномоченная компания "ЭКО-2022" | I8: 2282540061 | J8: 180 | K8: 44762 | N8: Далматова Данира | O8: 44767 | P8: 44767 | Q8: 44764 | R8: 44768 | S8: 44768 | T8: 44774 | U8: 44774 | V8: 44784 | W8: 16.08.2022 Полож. | X8: 16.08.2022 Отриц. | AA8: 15.08.2022 Отриц. | AB8: 16.08.2022 Отриц.
A9: 7 | B9: 247 | C9: МЖК Престиж Сити в г.Шымкент | D9: Шымкент | E9: ТОО "DAMDES ҚҰРЫЛЫС INVEST" | G9: ТОО "ER-DAM INVESTMENT GROUP" | I9: 5663317430 | J9: 208 | K9: 44784 | N9: Исмаков Адиль | O9: 16.08.2022 Полож. | P9: 16.08.2022 Отриц. | Q9: 44788 | R9: 15.08.2022 Полож. | S9: 16.08.2022 Отриц. | T9: 23.08.2022 Отриц. | U9: 44797 | V9: Заявка отозвана
A10: 8 | B10: 206 | C10: МЖК "Жана Арка" | D10: Астана | E10: ТОО "Трансстрой"" | G10: ТОО BBS GOLD" | I10: 7777340509 | J10: 373 | K10: 44783 | N10: Камалитден Бауыржан | O10: 15.08.2022 Отриц. | P10: 15.08.2022 Отриц. | Q10: 15.08.2022 Полож. | R10: 12.08.2022 Отриц. | S10: 15.08.2022 Отриц. | T10: 19.08.2022 Отриц. | U10: 44795 | V10: 44804 | W10: 05.09.2022 Отриц. | X10: 04.09.2022 Полож. | Y10: 05.09.2022 Полож. | Z10: 05.09.2022 Отриц. | AA10: 05.09.2022 Отриц. | AB10: 05.09.2022 Отриц.
A11: 9 | B11: 242 | C11: МЖК г.Шымкент | D11: Шымкент | E11: ТОО "Kanfar Building"" | G11: ТОО "OTYRAR SATU" | I11: 2088288586 | J11: 42 | K11: 44785 | N11: Уринбасарова Молдир | O11: 18.08.2022 Отриц. | P11: 17.08.2022 Отриц. | Q11: 44791 | R11: 16.08.2022 Отриц. | S11: 17.08.2022 Отриц. | T11: 23.08.2022 Отриц. | U11: 44798 | V11: 44811 | W11: 07.09.2022 Отказ | X11: 07.09.2022 Отказ
A12: 10 | B12: 250 | C12: МЖК Nova City на Туране | D12: Астана | E12: ТОО "Nova City Development" | G12: ТОО "NC 22" | I12: 6536713477 | J12: 234 | K12: 44811 | N12: Далматова Данира | O12: 44817 | P12: 44817 | Q12: 44816 | R12: 44813 | S12: 44817 | T12: 44823 | U12: 44824 | V12: Заявка отозвана
A13: 11 | B13: 252 | C13: МЖК Sun City, Блок 1 | D13: Алматинская область, г. Конаев | E13: ТОО "KAZSMU" | G13: ТОО "JK Sun City" | I13: 3974338040 | J13: 132 | K13: 44816 | N13: Уринбасарова Молдир | O13: 44820 | P13: 44820 | Q13: 44819 | R13: 44819 | S13: 44820 | T13: 44826 | U13: 44826 | V13: 44834 | W13: 04.10.2022 Полож. | X13: 04.10.2022 Полож. | Y13: 03.10.2022 Отриц. | Z13: 44837 | AA13: 04.10.2022 Полож. | AB13: 05.10.2022 Полож. | AC13: Заявка отозвана
A14: 12 | B14: 253 | C14: МЖК Sun City, Блок 3 | D14: Алматинская область, г. Конаев | E14: ТОО "KAZSMU" | G14: ТОО "JK Sun City" | I14: 4087535350 | J14: 144 | K14: 44816 | N14: Уринбасарова Молдир | O14: 44820 | P14: 44820 | Q14: 44819 | R14: 44819 | S14: 44820 | T14: 44826 | U14: 44826 | V14: 44834 | W14: 04.10.2022 Полож. | X14: 04.10.2022 Полож. | Y14: 03.10.2022 Отриц. | Z14: 44837 | AA14: 04.10.2022 Полож. | AB14: 05.10.2022 Полож. | AC14: Заявка отозвана
A15: 13 | B15: 258 | C15: МЖК г.Шымкент | D15: Шымкент | E15: ТОО "Kanfar Building"" | G15: ТОО "OTYRAR SATU" | I15: 2088288586 | J15: 42 | K15: 44833 | N15: Камалитден Бауыржан | O15: 44839 | P15: 44839 | Q15: 44837 | R15: 44834 | S15: 44839 | T15: 44846 | U15: 44847 | V15: 44854 | W15: 21.10.2022 Полож. | X15: 21.10.2022 Отриц. | Y15: 44856 | Z15: 21.10.2022 Соотв. | AA15: 22.10.2022 Полож. | AB15: 22.10.2022 Полож. | AC15: Заявка отозвана 28.10.2022
C16: ВСЕГО | I16: =SUM(I3:I15) -> 50370012391 | J16: =SUM(J3:J15) -> 2204
A21: - | C21: Наружные инженерные сети МЖК Бағыстан позиция №12 | D21: г.Астана | E21: ТОО "Аргон Строй" | G21: ТОО "BESTLIFE SOLUTIONS" | I21: 980451470 | J21: - | K21: - | L21: 45121 | N21: Аяпова Гульнур | O21: 21.07.2023 Полож. | P21: 17.07.2023 Полож. | Q21: 17.07.2023 Соотв. | R21: - | S21: 18.07.2023 Доработка | T21: 20.07.2023 Доработка | U21: 45133 | V21: Отзыв Заявки от 03.08.2023г.

Sheet СВОД ПО ГОДАМ
B2: Свод проектов по годам по состоянию на 30.10.2024г.
M3: Данные для Жилищного портала
B4: В разрезе по годам по действующим проектам | C4: количество проектов | D4: стоимость по Проектам | E4: площадь по Проектам | F4: кол-во квартир по Проектам | M4: В разрезе по годам по действующим проектам | N4: количество проектов | O4: стоимость по Проектам | P4: площадь по Проектам | Q4: кол-во квартир по Проектам
B5: 2021 год | C5: =Действующие!C70 -> 2 | D5: =Действующие!D70 -> 22006871432 | E5: =Действующие!E70 -> 100781.58 | F5: =Действующие!F70 -> 950 | M5: 2021 год | N5: =C5 -> 2 | O5: =D5 -> 22006871432 | P5: =E5 -> 100781.58 | Q5: =F5 -> 950
B6: 2022 год | C6: =Действующие!C71 -> 3 | D6: =Действующие!D71 -> 9948161748 | E6: =Действующие!E71 -> 51188.83 | F6: =Действующие!F71 -> 455 | M6: 2022 год | N6: =C6 -> 3 | O6: =D6 -> 9948161748 | P6: =E6 -> 51188.83 | Q6: =F6 -> 455
B7: 2023 год | C7: =Действующие!C72 -> 17 | D7: =Действующие!D72 -> 8.7536011e+10 | E7: =Действующие!E72 -> 343001.63 | F7: =Действующие!F72 -> 3637 | M7: 2023 год | N7: =C7 -> 17 | O7: =D7 -> 8.7536011e+10 | P7: =E7 -> 343001.63 | Q7: =F7 -> 3637
B8: 2024 год | C8: =Действующие!C73 -> 25 | D8: =Действующие!D73 -> 132096124126 | E8: =Действующие!E73 -> 513169.44 | F8: =Действующие!F73 -> 5219 | L8: минус 1 Saltzburg | M8: 2024 год | N8: =15+3+1 -> 19 | O8: =D8 -> 132096124126 | P8: =E8 -> 513169.44 | Q8: =F8 -> 5219
B9: ВСЕГО | C9: =SUM(C5:C8) -> 47 | D9: =SUM(D5:D8) -> 2.5158717e+11 | E9: =SUM(E5:E8) -> 1008141.5 | F9: =SUM(F5:F8) -> 10261 | M9: ВСЕГО | N9: =SUM(N5:N8) -> 41 | O9: =SUM(O5:O8) -> 2.5158717e+11 | P9: =SUM(P5:P8) -> 1008141.5 | Q9: =SUM(Q5:Q8) -> 10261
B13: В разрезе по годам по завершенным проектам | C13: количество проектов | D13: стоимость по Проектам | E13: площадь по Проектам | F13: площадь по Проектам (с уменьшением и расторжением) | G13: кол-во квартир по Проектам (согласно ПСД) | H13: кол-во квартир по факту | I13: кол-во квартир по Проектам (с уменьшением и расторжением) | M13: В разрезе по годам по завершенным проектам | N13: количество проектов | O13: стоимость по Проектам | P13: площадь по Проектам с учетом снижения | Q13: площадь по Проектам без учета снижения | R13: кол-во квартир согласно ПСД | S13: кол-во квартир по факту | T13: кол-во квартир по факту без учета снижения
B14: 2017 год | C14: =Завершенные!C226 -> 2 | D14: =Завершенные!D226 -> 9383792080 | E14: =Завершенные!E226 -> 49371.3 | F14: =Завершенные!J4+Завершенные!J5 -> 49371.3 | G14: =Завершенные!F226 -> 578 | H14: =Завершенные!G226 -> 574 | I14: =Завершенные!Q4+Завершенные!Q5 -> 574 | M14: 2017 год | N14: =C14 -> 2 | O14: =D14 -> 9383792080 | P14: =E14 -> 49371.3 | Q14: =F14 -> 49371.3 | R14: =G14 -> 578 | S14: =H14 -> 574 | T14: =I14 -> 574
B15: 2018 год | C15: =Завершенные!C227 -> 16 | D15: =Завершенные!D227 -> 56621715974 | E15: =Завершенные!E227 -> 358067.8 | F15: =Завершенные!J6+Завершенные!J7+Завершенные!J8+Завершенные!J9+Завершенные!J10+Завершенные!J11+Завершенные!J12+Завершенные!J13+Завершенные!J14+Завершенные!J15+Завершенные!J16+Завершенные!J17+Завершенные!J18+Завершенные!J19+Завершенные!J20+Завершенные!J21 -> 358067.8 | G15: =Завершенные!F227 -> 4378 | H15: =Завершенные!G227 -> 4713 | I15: =SUM(Завершенные!Q6:Q21) -> 4713 | M15: 2018 год | N15: =C15 -> 16 | O15: =D15 -> 56621715974 | P15: =E15 -> 358067.8 | Q15: =F15 -> 358067.8 | R15: =G15 -> 4378 | S15: =H15 -> 4713 | T15: =I15 -> 4713
B16: 2019 год | C16: =Завершенные!C228 -> 24 | D16: =Завершенные!D228 -> 90883205479 | E16: =Завершенные!E228 -> 530593.09 | F16: =Завершенные!J22+Завершенные!J23+Завершенные!J24+Завершенные!J25+Завершенные!J26+Завершенные!J27+Завершенные!J28+Завершенные!J29+Завершенные!J30+Завершенные!J31+Завершенные!J32+Завершенные!J33+Завершенные!J34+Завершенные!J35+Завершенные!J36+Завершенные!J37+Завершенные!J39+Завершенные!J40+Завершенные!J41+Завершенные!J42+Завершенные!J43+Завершенные!J44+Завершенные!J46+Завершенные!J47 -> 530593.09 | G16: =Завершенные!F228 -> 6067 | H16: =Завершенные!G228 -> 6145 | I16: =SUM(Завершенные!Q22:Q47) -> 6145 | M16: 2019 год | N16: =C16 -> 24 | O16: =D16 -> 90883205479 | P16: =E16 -> 530593.09 | Q16: =F16 -> 530593.09 | R16: =G16 -> 6067 | S16: =H16 -> 6145 | T16: =I16 -> 6145
B17: 2020 год | C17: =Завершенные!C229 -> 27 | D17: =Завершенные!D229 -> 112169197898 | E17: =Завершенные!E229 -> 705461.05 | F17: =Завершенные!J48+Завершенные!J49+Завершенные!J50+Завершенные!J51+Завершенные!J52+Завершенные!J38+Завершенные!J53+Завершенные!J54+Завершенные!J55+Завершенные!J56+Завершенные!J57+Завершенные!J59+Завершенные!J60+Завершенные!J61+Завершенные!J62+Завершенные!J63+Завершенные!J64+Завершенные!J65+Завершенные!J67+Завершенные!J68+Завершенные!J69+Завершенные!J70+Завершенные!J71+Завершенные!J72+Завершенные!J73+Завершенные!J74+Завершенные!J121+Завершенные!J159 -> 705461.05 | G17: =Завершенные!F229 -> 8425 | H17: =Завершенные!G229 -> 8828 | I17: =Завершенные!Q48+Завершенные!Q49+Завершенные!Q50+Завершенные!Q51+Завершенные!Q52+Завершенные!Q53+Завершенные!Q54+Завершенные!Q55+Завершенные!Q56+Завершенные!Q57+Завершенные!Q59+Завершенные!Q60+Завершенные!Q61+Завершенные!Q62+Завершенные!Q63+Завершенные!Q64+Завершенные!Q65+Завершенные!Q67+Завершенные!Q68+Завершенные!Q69+Завершенные!Q70+Завершенные!Q71+Завершенные!Q72+Завершенные!Q73+Завершенные!Q74+Завершенные!Q121+Завершенные!Q159 -> 8828 | M17: 2020 год | N17: =C17 -> 27 | O17: =D17 -> 112169197898 | P17: =E17 -> 705461.05 | Q17: =F17 -> 705461.05 | R17: =G17 -> 8425 | S17: =H17 -> 8828 | T17: =I17 -> 8828
B18: 2021 год | C18: =Завершенные!C230 -> 69 | D18: =Завершенные!D230 -> 353425107689 | E18: =Завершенные!E230 -> 1893325.4 | F18: =Завершенные!J75+Завершенные!J76+Завершенные!J77+Завершенные!J78+Завершенные!J79+Завершенные!J80+Завершенные!J81+Завершенные!J82+Завершенные!J83+Завершенные!J84+Завершенные!J85+Завершенные!J86+Завершенные!J87+Завершенные!J88+Завершенные!J89+Завершенные!J90+Завершенные!J91+Завершенные!J92+Завершенные!J118+Завершенные!J93+Завершенные!J94+Завершенные!J95+Завершенные!J96+Завершенные!J97+Завершенные!J98+Завершенные!J99+Завершенные!J100+Завершенные!J101+Завершенные!J102+Завершенные!J103+Завершенные!J104+Завершенные!J105+Завершенные!J106+Завершенные!J107+Завершенные!J111+Завершенные!J114+Завершенные!J115+Завершенные!J116+Завершенные!J117+Завершенные!J119+Завершенные!J120+Завершенные!J122+Завершенные!J123+Завершенные!J124+Завершенные!J125+Завершенные!J126+Завершенные!J128+Завершенные!J129+Завершенные!J131+Завершенные!J133+Завершенные!J135+Завершенные!J138+Завершенные!J139+Завершенные!J140+Завершенные!J141+Завершенные!J145+Завершенные!J146+Завершенные!J149+Завершенные!J151+Завершенные!J152+Завершенные!J153+Завершенные!J154+Завершенные!J155+Завершенные!J156+Завершенные!J157+Завершенные!J158+Завершенные!J162+Завершенные!J164+Завершенные!J176+Завершенные!J178+Завершенные!J180+Завершенные!J181+Завершенные!J182+Завершенные!J186 -> 1855521.4 | G18: =Завершенные!F230 -> 20284 | H18: =Завершенные!G230 -> 20763 | I18: =Завершенные!Q176+Завершенные!Q164+Завершенные!Q162+Завершенные!Q158+Завершенные!Q157+Завершенные!Q156+Завершенные!Q155+Завершенные!Q154+Завершенные!Q153+Завершенные!Q152+Завершенные!Q151+Завершенные!Q149+Завершенные!Q146+Завершенные!Q145+Завершенные!Q141+Завершенные!Q140+Завершенные!Q139+Завершенные!Q138+Завершенные!Q135+Завершенные!Q133+Завершенные!Q131+Завершенные!Q129+Завершенные!Q128+Завершенные!Q126+Завершенные!Q125+Завершенные!Q124+Завершенные!Q123+Завершенные!Q122+Завершенные!Q120+Завершенные!Q119+Завершенные!Q117+Завершенные!Q116+Завершенные!Q115+Завершенные!Q114+Завершенные!Q111+Завершенные!Q107+Завершенные!Q106+Завершенные!Q105+Завершенные!Q104+Завершенные!Q103+Завершенные!Q102+Завершенные!Q101+Завершенные!Q100+Завершенные!Q99+Завершенные!Q98+Завершенные!Q97+Завершенные!Q96+Завершенные!Q95+Завершенные!Q94+Завершенные!Q93+Завершенные!Q118+Завершенные!Q92+Завершенные!Q91+Завершенные!Q90+Завершенные!Q89+Завершенные!Q88+Завершенные!Q87+Завершенные!Q86+Завершенные!Q85+Завершенные!Q84+Завершенные!Q83+Завершенные!Q82+Завершенные!Q81+Завершенные!Q80+Завершенные!Q79+Завершенные!Q78+Завершенные!Q77+Завершенные!Q76+Завершенные!Q75+Завершенные!Q178+Завершенные!Q180+Завершенные!Q181+Завершенные!Q182+Завершенные!Q186 -> 20385 | L18: Алия +, Лайф таун + | M18: 2021 год | N18: =70 -> 70 | O18: =D18 -> 353425107689 | P18: =E18 -> 1893325.4 | Q18: =F18 -> 1855521.4 | R18: =G18 -> 20284 | S18: =H18 -> 20763 | T18: =I18 -> 20385
B19: 2022 год | C19: =Завершенные!C231 -> 31 | D19: =Завершенные!D231 -> 196154054444 | E19: =Завершенные!E231 -> 986337.46 | F19: =Завершенные!J109+Завершенные!J110+Завершенные!J112+Завершенные!J113+Завершенные!J130+Завершенные!J134+Завершенные!J136+Завершенные!J137+Завершенные!J142+Завершенные!J143+Завершенные!J147+Завершенные!J148+Завершенные!J161+Завершенные!J163+Завершенные!J165+Завершенные!J166+Завершенные!J167+Завершенные!J168+Завершенные!J169+Завершенные!J170+Завершенные!J171+Завершенные!J172+Завершенные!J173+Завершенные!J174+Завершенные!J175+Завершенные!J183+Завершенные!J188+Завершенные!J189+Завершенные!J190 -> 788646.58 | G19: =Завершенные!F231 -> 11074 | H19: =Завершенные!G231 -> 11229 | I19: =Завершенные!Q108+Завершенные!Q109+Завершенные!Q110+Завершенные!Q112+Завершенные!Q113+Завершенные!Q127+Завершенные!Q130+Завершенные!Q134+Завершенные!Q136+Завершенные!Q137+Завершенные!Q142+Завершенные!Q143+Завершенные!Q147+Завершенные!Q148+Завершенные!Q150+Завершенные!Q160+Завершенные!Q161+Завершенные!Q163+Завершенные!Q165+Завершенные!Q166+Завершенные!Q167+Завершенные!Q168+Завершенные!Q169+Завершенные!Q170+Завершенные!Q171+Завершенные!Q172+Завершенные!Q173+Завершенные!Q174+Завершенные!Q175+Завершенные!Q183+Завершенные!Q188+Завершенные!Q189+Завершенные!Q190 -> 9165 | M19: 2022 год | N19: =C19 -> 31 | O19: =D19 -> 196154054444 | P19: =E19 -> 986337.46 | Q19: =F19 -> 788646.58 | R19: =G19 -> 11074 | S19: =H19 -> 11229 | T19: =I19 -> 9165
B20: 2023 год | C20: =Завершенные!C232 -> 20 | D20: =Завершенные!D232 -> 70233975981 | E20: =Завершенные!E232 -> 250686.26 | F20: =Завершенные!J177+Завершенные!J179+Завершенные!J184+Завершенные!J185 -> 42592.2 | G20: =Завершенные!F232 -> 2942 | H20: =Завершенные!G232 -> 3003 | I20: =Завершенные!Q177+Завершенные!Q179+Завершенные!Q184+Завершенные!Q185 -> 338 | M20: 2023 год | N20: =C20 -> 20 | O20: =D20 -> 70233975981 | P20: =E20 -> 250686.26 | Q20: =F20 -> 42592.2 | R20: =G20 -> 2942 | S20: =H20 -> 3003 | T20: =I20 -> 338
B21: 2024 год | C21: =Завершенные!C233 -> 1 | D21: =Завершенные!D233 -> 2899077545 | E21: =Завершенные!E233 -> 7217.35 | F21: =E21 -> 7217.35 | G21: =Завершенные!F233 -> 106 | H21: =Завершенные!G233 -> 106 | I21: 106 | M21: 2024 год | N21: =C21 -> 1 | O21: =D21 -> 2899077545 | P21: =E21 -> 7217.35 | Q21: =F21 -> 7217.35 | R21: =G21 -> 106 | S21: =H21 -> 106 | T21: =I21 -> 106
B22: ВСЕГО | C22: =SUM(C14:C21) -> 190 | D22: =SUM(D14:D21) -> 891770127090 | E22: =SUM(E14:E21) -> 4781059.7 | F22: =SUM(F14:F21) -> 4337470.8 | G22: =SUM(G14:G21) -> 53854 | H22: =SUM(H14:H21) -> 55361 | I22: =SUM(I14:I21) -> 50254 | M22: ВСЕГО | N22: =SUM(N14:N21) -> 191 | O22: =SUM(O14:O21) -> 891770127090 | P22: =SUM(P14:P21) -> 4781059.7 | Q22: =SUM(Q14:Q21) -> 4337470.8 | R22: =SUM(R14:R21) -> 53854 | S22: =SUM(S14:S21) -> 55361 | T22: =SUM(T14:T21) -> 50254
B26: Проекты, по которым ДПГ был расторгнут | C26: количество проектов | D26: стоимость по Проектам | E26: площадь по Проектам | F26: кол-во квартир по Проектам | M26: Проекты, по которым ДПГ был расторгнут | N26: количество проектов | O26: стоимость по Проектам | P26: площадь по Проектам | Q26: кол-во квартир по Проектам
B27: 2022 год | C27: 2 | D27: ='Отказ и расторжение'!G61+'Отказ и расторжение'!G63 -> 5669915493 | E27: ='Отказ и расторжение'!H61+'Отказ и расторжение'!H63 -> 35681.22 | F27: ='Отказ и расторжение'!J61+'Отказ и расторжение'!J63 -> 413 | M27: 2022 год | N27: 2 | O27: =D27 -> 5669915493 | P27: =E27 -> 35681.22 | Q27: =F27 -> 413
B28: 2023 год | C28: 4 | D28: ='Отказ и расторжение'!G60+'Отказ и расторжение'!G62+'Отказ и расторжение'!G64+'Отказ и расторжение'!G65 -> 9901509415 | E28: ='Отказ и расторжение'!H60+'Отказ и расторжение'!H62+'Отказ и расторжение'!H64+'Отказ и расторжение'!H65 -> 45043.24 | F28: ='Отказ и расторжение'!J60+'Отказ и расторжение'!J62+'Отказ и расторжение'!J64+'Отказ и расторжение'!J65 -> 545 | M28: 2023 год | N28: 4 | O28: =D28 -> 9901509415 | P28: =E28 -> 45043.24 | Q28: =F28 -> 545
B29: ВСЕГО | C29: =SUM(C27:C28) -> 6 | D29: =SUM(D27:D28) -> 15571424908 | E29: =SUM(E27:E28) -> 80724.46 | F29: =SUM(F27:F28) -> 958 | M29: ВСЕГО | N29: =SUM(N27:N28) -> 6 | O29: =SUM(O27:O28) -> 15571424908 | P29: =SUM(P27:P28) -> 80724.46 | Q29: =SUM(Q27:Q28) -> 958
B33: Итого в разрезе по годам | C33: количество проектов | D33: стоимость по Проекту | E33: площадь по Проекту | F33: площадь по Проектам (с уменьшением и расторжением) | G33: кол-во квартир согласно ПСД | H33: кол-во квартир согласно ПСД (с уменьшением и расторжением) | I33: кол-во квартир по факту | J33: DWH | M33: Итого в разрезе по годам | N33: количество проектов | O33: стоимость по Проекту | P33: площадь по Проекту с учетом снижения | Q33: площадь по Проекту без учета снижения | R33: кол-во квартир согласно ПСДс учетом снижения | S33: кол-во квартир согласно ПСД без учета снижения | T33: кол-во квартир по факту с учетом снижения | U33: кол-во квартир по факту без учета снижения
B34: 2017 год | C34: =C14 -> 2 | D34: =D14 -> 9383792080 | E34: =E14 -> 49371.3 | F34: =E14 -> 49371.3 | G34: =G14 -> 578 | H34: =G14 -> 578 | I34: =H14 -> 574 | M34: 2017 год | N34: =N14 -> 2 | O34: =O14 -> 9383792080 | P34: =P14 -> 49371.3 | Q34: =P14 -> 49371.3 | R34: =R14 -> 578 | S34: =R14 -> 578 | T34: =S14 -> 574 | U34: =S14 -> 574
B35: 2018 год | C35: =C15 -> 16 | D35: =D15 -> 56621715974 | E35: =E15 -> 358067.8 | F35: =E15 -> 358067.8 | G35: =G15 -> 4378 | H35: =G15 -> 4378 | I35: =H15 -> 4713 | M35: 2018 год | N35: =N15 -> 16 | O35: =O15 -> 56621715974 | P35: =P15 -> 358067.8 | Q35: =P15 -> 358067.8 | R35: =R15 -> 4378 | S35: =R15 -> 4378 | T35: =S15 -> 4713 | U35: =S15 -> 4713
B36: 2019 год | C36: =C16 -> 24 | D36: =D16 -> 90883205479 | E36: =E16 -> 530593.09 | F36: =E16 -> 530593.09 | G36: =G16 -> 6067 | H36: =G16 -> 6067 | I36: =H16 -> 6145 | M36: 2019 год | N36: =N16 -> 24 | O36: =O16 -> 90883205479 | P36: =P16 -> 530593.09 | Q36: =P16 -> 530593.09 | R36: =R16 -> 6067 | S36: =R16 -> 6067 | T36: =S16 -> 6145 | U36: =S16 -> 6145
B37: 2020 год | C37: =C17 -> 27 | D37: =D17 -> 112169197898 | E37: =E17 -> 705461.05 | F37: =E17 -> 705461.05 | G37: =G17 -> 8425 | H37: =G17 -> 8425 | I37: =H17 -> 8828 | M37: 2020 год | N37: =N17 -> 27 | O37: =O17 -> 112169197898 | P37: =P17 -> 705461.05 | Q37: =P17 -> 705461.05 | R37: =R17 -> 8425 | S37: =R17 -> 8425 | T37: =S17 -> 8828 | U37: =S17 -> 8828
B38: 2021 год | C38: =C5+C18 -> 71 | D38: =D5+D18 -> 375431979121 | E38: =E5+E18 -> 1994107 | F38: =E5+E18 -> 1994107 | G38: =G18+F5 -> 21234 | H38: =G18+F5 -> 21234 | I38: =H18+F5 -> 21713 | M38: 2021 год | N38: =N5+N18 -> 72 | O38: =O5+O18 -> 375431979121 | P38: =P5+P18 -> 1994107 | Q38: =P5+P18 -> 1994107 | R38: =R18+Q5 -> 21234 | S38: =R18+Q5 -> 21234 | T38: =S18+Q5 -> 21713 | U38: =S18+Q5 -> 21713
B39: 2022 год | C39: =C19+C6+C27 -> 36 | D39: =D6+D19+D27 -> 211772131685 | E39: =E6+E19+E27 -> 1073207.5 | F39: =E6+E19+E27 -> 1073207.5 | G39: =G19+F6+F27 -> 11942 | H39: =G19+F6+F27 -> 11942 | I39: =H19+F6+F27 -> 12097 | M39: 2022 год | N39: =N19+N6+N27 -> 36 | O39: =O6+O19+O27 -> 211772131685 | P39: =P6+P19+P27 -> 1073207.5 | Q39: =P6+P19+P27 -> 1073207.5 | R39: =R19+Q6+Q27 -> 11942 | S39: =R19+Q6+Q27 -> 11942 | T39: =S19+Q6+Q27 -> 12097 | U39: =S19+Q6+Q27 -> 12097
B40: 2023 год | C40: =C7+C28+C20 -> 41 | D40: =D7+D28+D20 -> 1.676715e+11 | E40: =E7+E20+E28 -> 638731.13 | F40: =E7+E28+F20 -> 430637.07 | G40: =F7+G20+F28 -> 7124 | H40: =F7+F28+I20 -> 4520 | I40: =F7+F28+H20 -> 7185 | J40: 638742 | M40: 2023 год | N40: =N7+N28+N20 -> 41 | O40: =O7+O28+O20 -> 1.676715e+11 | P40: =P7+P20+P28 -> 638731.13 | Q40: =P7+P28+Q20 -> 430637.07 | R40: =Q7+R20+Q28 -> 7124 | S40: =Q7+Q28+T20 -> 4520 | T40: =Q7+Q28+S20 -> 7185 | U40: =Q7+Q28+T20 -> 4520
B41: 2024 год | C41: =C8+C21 -> 26 | D41: =D8+D21 -> 134995201671 | E41: =E8+E21 -> 520386.79 | F41: =E8+F21 -> 520386.79 | G41: =F8+G21 -> 5325 | H41: =F8+I21 -> 5325 | I41: =F8+H21 -> 5325 | J41: 491956 | M41: 2024 год | N41: =N8+N21 -> 20 | O41: =O8+O21 -> 134995201671 | P41: =P8+P21 -> 520386.79 | Q41: =P8 -> 513169.44 | R41: =Q8 -> 5219 | S41: =Q8 -> 5219 | T41: =Q8 -> 5219 | U41: =Q8 -> 5219
B42: ВСЕГО | C42: =SUM(C34:C41) -> 243 | D42: =SUM(D34:D41) -> 1.1589287e+12 | E42: =SUM(E34:E41) -> 5869925.7 | F42: =SUM(F34:F41) -> 5661831.6 | G42: =SUM(G34:G41) -> 65073 | H42: =SUM(H34:H41) -> 62469 | I42: =SUM(I34:I41) -> 66580 | M42: ВСЕГО | N42: =SUM(N34:N41) -> 238 | O42: =SUM(O34:O41) -> 1.1589287e+12 | P42: =SUM(P34:P41) -> 5869925.7 | Q42: =SUM(Q34:Q41) -> 5654614.3 | R42: =SUM(R34:R41) -> 64967 | S42: =SUM(S34:S41) -> 62363 | T42: =SUM(T34:T41) -> 66474 | U42: =SUM(U34:U41) -> 63809
B45: В разрезе регионов | C45: количество проектов | D45: из них завершенные | E45: из них действующие | F45: из них расторгнутые
B46: г. Астана | C46: =SUM(D46:F46) -> 127 | D46: =Завершенные!C237 -> 104 | E46: =Действующие!C78 -> 22 | F46: =Действующие!F95 -> 1
B47: стоимость проекта | C47: =SUM(D47:F47) -> 6.486901e+11 | D47: =Завершенные!D237 -> 489865029079 | E47: =Действующие!D78 -> 1.5637619e+11 | F47: ='Отказ и расторжение'!G61 -> 2448882300
B48: г. Алматы | C48: =SUM(D48:F48) -> 52 | D48: =Завершенные!C238 -> 49 | E48: =Действующие!C79 -> 3 | F48: =Действующие!F96 -> 0
B49: стоимость проекта | C49: =SUM(D49:F49) -> 289339149216 | D49: =Завершенные!D238 -> 267922917915 | E49: =Действующие!D79 -> 21416231301
B50: Алматинская обл. | C50: =SUM(D50:F50) -> 12 | D50: =Завершенные!C239 -> 9 | E50: =Действующие!C80 -> 1 | F50: =Действующие!F97 -> 2
B51: стоимость проекта | C51: =SUM(D51:F51) -> 32707903496 | D51: =Завершенные!D239 -> 23824872919 | E51: =Действующие!D80 -> 4916104675 | F51: ='Отказ и расторжение'!G63+'Отказ и расторжение'!G65 -> 3966925902
